Workbook

Sheet Pucusana
A1: Encuesta | B1: Nombre_Encuestador | C1: Fecha_Encuesta | D1: Nombre_Pescador | E1: DNI | F1: Años_Pesca | G1: Años_Altura | H1: Distrito_Vivienda | I1: Puerto_Zarpe | J1: Puerto_Arribo | K1: Fecha_Nacimiento | L1: Edad | M1: Sexo | N1: Estado_Civil | O1: Grado_Instruccion | P1: Alfabeto | Q1: Seguro_Salud | R1: Rol_Pescador | S1: OSPA | T1: Nombre_OSPA | U1: Otra_Pesca | V1: Arte_Costera1 | W1: Rec_Costero1 | X1: Arte_Costera2 | Y1: Rec_Costero2 | Z1: Arte_Costera3 | AA1: Rec_Costero3 | AB1: Alterna_Pesca | AC1: Actividad_Alterna | AD1: Personas_Dependientes | AE1: Numero_hijos | AF1: Pareja | AG1: Actividades_Pareja | AH1: FamiliaDirecta_Pesca | AI1: Rol_Familiares | AJ1: Genero_Opotunidades | AK1: GenOpor_No | AL1: Genero_Pago | AM1: GenPago_No | AN1: Num_Embarcaciones | AO1: Embarcacion_Propia | AP1: Nombre1_EmbarcacionAltura | AQ1: Matricula_1 | AR1: SISESAT_1 | AS1: Radiobaliza_1 | AT1: PTH_1 | AU1: TN_Bodega_1 | AV1: Nombre2_EmbarcacionAltura | AW1: Matricula_2 | AX1: SISESAT_2 | AY1: Radiobaliza_2 | AZ1: PTH_2 | BA1: TN_Bodega_2 | BB1: Galones_Combustible | BC1: Arte_1 | BD1: Num_Tripulantes1 | BE1: Edades_Tripulantes1 | BF1: Nacionalidad_Trip1 | BG1: Recurso_1 | BH1: Carnada1 | BI1: Temporada1 | BJ1: Viajes_Temporada1 | BK1: Detalles_Arte1 | BL1: Dias_Faena1 | BM1: Horas_Efectivas1 | BN1: Lances_Faena1 | BO1: Kg_Lance1 | BP1: Kg_Faena1 | BQ1: Venta_Recurso1 | BR1: Precio_Kg1 | BS1: Arte_2 | BT1: Num_Tripulantes2 | BU1: Edades_Tripulantes2 | BV1: Nacionalidad_Trip2 | BW1: Recurso_2 | BX1: Carnada2 | BY1: Temporada2 | BZ1: Viajes_Temporada2 | CA1: Detalles_Arte2 | CB1: Dias_Faena2 | CC1: Horas_Efectivas2 | CD1: Lances_Faena2 | CE1: Kg_Lance2 | CF1: Kg_Faena2 | CG1: Venta_Recurso2 | CH1: Precio_Kg2 | CI1: Arte_3 | CJ1: Recurso_3 | CK1: Carnada3 | CL1: Temporada3 | CM1: Viajes_Temporada3 | CN1: Detalles_Arte3 | CO1: Dias_Faena3 | CP1: Horas_Efectivas3 | CQ1: Lances_Faena3 | CR1: Captura_Lance3 | CS1: Captura_Faena3 | CT1: Venta_Recurso3 | CU1: Precio_Kg3 | CV1: Observaciones | CW1: Telefono
A2: KD-PUCUSANA-001 | B2: Kelly Diaz | C2: 45883 | D2: Manuel Jose Avalos Carrillo | E2: 42939396 | F2: 27 | G2: 27 | H2: Pucusana | I2: Pucusana | J2: Pucusana, Pisco, San Andrés | K2: 23182 | L2: =DATEDIF(K2, DATE(2025,8,29), "Y") -> 62 | M2: M | N2: Casado/Conviviente | O2: Secundaria | P2: si | Q2: si | R2: Armador, Patrón | S2: si | T2: Asociación Gremio de Pescadores de Pucusana | U2: no | V2: NA | W2: NA | X2: NA | Y2: NA | Z2: NA | AA2: NA | AB2: si | AC2: Secretario del Gremio | AD2: 4 | AE2: 3 | AF2: si | AG2: Ama de casa | AH2: no | AI2: NA | AJ2: no | AK2: La fuerza fisica natural no es la misma | AL2: si | AM2: NA | AN2: 1 | AO2: si | AP2: EL GRAN SHADAI | AQ2: CO-05274-BM | AR2: no | AS2: no | AT2: si | AU2: 5 | AV2: NA | AW2: NA | AX2: NA | AY2: NA | AZ2: NA | BA2: NA | BB2: 68-85 | BC2: Cortina superficial | BD2: 4 | BE2: 25-40 | BF2: Peruana | BG2: Bonito | BH2: no | BI2: Octubre-Mayo | BJ2: 40 | BK2: #paños: 10, cocada: 4 pulgadas, malla 4.5 x ?? M | BL2: 7 | BM2: 4 | BN2: 12-15 | BO2: 1000-2000 | BP2: 6000 | BQ2: Acopiador | BR2: 1-10 | BS2: Trampa Ovas | BT2: 3 | BU2: 25-40 | BV2: Peruana | BW2: Ova | BX2: no | BY2: Octubre-Noviembre | BZ2: 2-3 | CA2: Esteras y palmeras. Usa 20-21 trampas, en 3 filas de 5. Dimensiones de trampa 3x1.5 metros | CB2: 30 | CC2: 72-96 | CD2: 10 | CE2: 200-500 | CF2: 1400 | CG2: Acopiador | CH2: 37-40 | CI2: no | CJ2: NA | CK2: NA | CL2: NA | CM2: NA | CN2: NA | CO2: NA | CP2: NA | CQ2: NA | CR2: NA | CS2: NA | CT2: NA | CU2: NA | CV2: Precio (kg) de ova con ojo: 5 soles. Temperatura para la ova debe ser entre 18-20 C. Si el agua esta fria, la trampa se queda en el agua por 4 dias; si esta caliente, por 2.5 a 3 dias | CW2: 995 555 047
A3: KD-PUCUSANA-002 | B3: Kelly Diaz | C3: 45883 | D3: Rene Yupanqui Mendoza | E3: 04636818 | F3: 34 | G3: 34 | H3: Pucusana | I3: Pucusana | J3: Pucusana, Atico, La Planchada, Ancón, Marcona | K3: 24667 | L3: =DATEDIF(K3, DATE(2025,8,29), "Y") -> 58 | M3: M | N3: Casado/Conviviente | O3: Secundaria | P3: si | Q3: si | R3: Armador, Patrón | S3: no | T3: NA | U3: no | V3: NA | W3: NA | X3: NA | Y3: NA | Z3: NA | AA3: NA | AB3: no | AC3: NA | AD3: 1 | AE3: 3 | AF3: si | AG3: Administra la embarcación y el recurso | AH3: si | AI3: 1 hijo: dueño de lancha en Ilo | AJ3: si | AK3: NA | AL3: no | AM3: Costumbre y opiniones antiguas | AN3: 2 | AO3: si | AP3: FAVIMAR | AQ3: CO-65441-BM | AR3: no | AS3: si | AT3: si | AU3: 5 | AV3: FAVIMAR I | AW3: PT-40356-BM | AX3: no | AY3: no | AZ3: si | BA3: 6 | BB3: 200-250 | BC3: Pinta Potera | BD3: 4 | BE3: 20-40 | BF3: Peruana | BG3: Pota | BH3: no | BI3: Enero-Diciembre | BJ3: 24 | BK3: 2 viajes/mes | BL3: 4-5 | BM3: NS | BN3: NS | BO3: 2000 | BP3: 8000 | BQ3: Acopiador | BR3: 1.5-2 | BS3: Cortina superficial | BT3: 4 | BU3: 20-40 | BV3: Peruana | BW3: Bonito | BX3: no | BY3: Enero-Diciembre | BZ3: 24 | CA3: #paños: 6, cocada: 4 pulgadas, malla 4.5x9 metros | CB3: 6 | CC3: 3 | CD3: 15-18 | CE3: 200-1000 | CF3: 3000-4000 | CG3: Acopiador | CH3: 5 | CI3: Trampa Ovas | CJ3: Ova | CK3: no | CL3: Noviembre-Febrero | CM3: 2-3 | CN3: Esteras con palmeras, a veces zargazo. Usa 18 trampas, en 6 filas de 3. Dimension de tampa 3x2 m | CO3: 30-40 | CP3: 72 | CQ3: 10 | CR3: 80-150 | CS3: 1000-1500 | CT3: Acopiador | CU3: 30 | CV3: Zona: Ova (70-80 millas fuera de Marcona y La Planchada); Bonito (60 millas fuera); Pota (60-200 millas fuera de Callao a Pucusana). Precio (kg) de ova con ojo: 5-10 soles. Pescador cree que ova con ojo es destinada a la sierra del Peru o a Bolivia. Hace 2 años, la ova costaba S/.50 por kg. Temperatura necesaria para Perico: 20-22 C. Comenta que SISESAT no es necesario, es caro y el pago no es mensual; si se malogra, deben regresar. Pucusana necesita un desembarcadero, ya que es el punto de arribo preferido por muchos embarcadores ya que el precio es mas alto aqui, y hay mas seguridad y tranquilidad que en callao. | CW3: 908 619 439 | CY3: Ova (70-80 millas fuera de Marcona y La Planchada)
A4: KD-PUCUSANA-003 | B4: Kelly Diaz | C4: 45884 | D4: Adolfo Climber Molina Cespedes | E4: 80006544 | F4: 18 | G4: 16 | H4: Pucusana | I4: Pucusana | J4: Pucusana, Chimbote, Ilo | K4: 28344 | L4: =DATEDIF(K4, DATE(2025,8,29), "Y") -> 48 | M4: M | N4: Casado/Conviviente | O4: Secundaria | P4: si | Q4: Privado | R4: Patrón | S4: si | T4: Asociación Gremio de Pescadores de Pucusana | U4: no | V4: NA | W4: NA | X4: NA | Y4: NA | Z4: NA | AA4: NA | AB4: si | AC4: Turismo | AD4: 3 | AE4: 2 | AF4: si | AG4: Mantenimiento en la isla de Pucusana | AH4: no | AI4: NA | AJ4: si | AK4: NA | AL4: si | AM4: NA | AN4: NS | AO4: no | AP4: DON VICTOR | AQ4: NS | AR4: si | AS4: no | AT4: si | AU4: 8 | AV4: JUANITA | AW4: NS | AX4: si | AY4: no | AZ4: no | BA4: 8 | BB4: 250-300 | BC4: Espinel | BD4: 4 | BE4: 30-40 | BF4: Peruana | BG4: Perico | BH4: si, pota, lisa, tamborin | BI4: Enero-Marzo | BJ4: 4-8 | BK4: Linea madre: 17 millas. #anzuelos: 2500. 1 anzuelo/linea. Calibre: 5 | BL4: 15-30 | BM4: 4-5 | BN4: 10-15 | BO4: 1500-2000 | BP4: 10000 | BQ4: Acopiador | BR4: 10-12 | BS4: Trampa Ovas | BT4: 3 | BU4: 30-40 | BV4: Peruana | BW4: Ova | BX4: no | BY4: Septiembre-Enero | BZ4: 3-4 | CA4: Esteras y manta, con palmeras. Usa 20 trampas, en 4 filas de 5. Dimensiones de trampa 3x2 metros | CB4: 30-45 | CC4: 72 | CD4: 10-12 | CE4: 100-500 | CF4: 3000-5000 | CG4: Acopiador | CH4: 30-35 | CI4: Cortina Superficial | CJ4: Bonito | CK4: no | CL4: Enero-Marzo | CM4: 20-24 | CN4: #paños: 10, cocada: 4 pulgadas, malla 6x500 metros | CO4: 7 | CP4: 2 | CQ4: 20-25 | CR4: 20-5000 | CS4: 5000-10000 | CT4: Acopiador | CU4: 4-7 | CV4: Zona: Ova (150-200 millas fuera de Marcona y La Planchada); Bonito (60-200 millas fuera de Pisco, Pucusana y Huacho); Perico (150 millas fuera de Paita,, Pucusana, Pisco, Ancon, Huacho, Ilo). Precio (kg) de ova con ojo: 3 soles. Para la huevera, las trampas se colocan y la embarcacion queda a la deriva. El zargazo dura 2 faenas de uso, se malogra rapido; la palmera dura 2 meses (llevan reemplazos). Si la trampa se queda 5 a 6 dias, la huevera desarrolla ojo y ya no sirve. | CW4: 967 688 205 | CY4: Ova (150-200 millas fuera de Marcona y La Planchada)
A5: KD-PUCUSANA-004 | B5: Kelly Diaz | C5: 45884 | D5: Jose Carlos Florian Peña | E5: 42953858 | F5: 22 | G5: 22 | H5: Pucusana | I5: Pucusana | J5: Pucusana, Ancón, Pisco | K5: 19889 | L5: =DATEDIF(K5, DATE(2025,8,29), "Y") -> 71 | M5: M | N5: Casado/Conviviente | O5: Secundaria | P5: si | Q5: Privado | R5: Armador, Patrón | S5: si | T5: Asociación Gremio de Pescadores de Pucusana | U5: no | V5: NA | W5: NA | X5: NA | Y5: NA | Z5: NA | AA5: NA | AB5: no | AC5: NA | AD5: 1 | AE5: 1 | AF5: si | AG5: Enfermera | AH5: no | AI5: NA | AJ5: si | AK5: NA | AL5: si | AM5: NA | AN5: 1 | AO5: si | AP5: JOSEPH SCHALOOM II | AQ5: CO-37277-BM | AR5: no | AS5: no | AT5: si | AU5: 6.19 | AV5: NA | AW5: NA | AX5: NA | AY5: NA | AZ5: NA | BA5: NA | BB5: 300-340 | BC5: Cortina superficial | BD5: 4 | BE5: 25-60 | BF5: Peruana | BG5: Bonito | BH5: no | BI5: Septiembre-Abril | BJ5: 30-40 | BK5: #paños: 8-10, cocada: 4-4.5 pulgadas, malla 4.5 x 1500 m | BL5: 3-4 | BM5: 1.5-2 | BN5: 10-15 | BO5: 1000-4000 | BP5: 4000-6000 | BQ5: Acopiador | BR5: 2-5 | BS5: Espinel | BT5: 4 | BU5: 25-60 | BV5: Peruana | BW5: Perico | BX5: si, pota, caballa | BY5: Noviembre-Enero | BZ5: 3-4 | CA5: Linea madre: 9000 m. #anzuelos: 600-1000. 1 anzuelo/linea. Calibre: 5 | CB5: 6 | CC5: 3-4 | CD5: 6 | CE5: 500-1000 | CF5: 4000-5000 | CG5: Acopiador | CH5: 4-5 | CI5: Trampa Ovas | CJ5: Ova | CK5: no | CL5: Octubre-Enero | CM5: 4 | CN5: Esteras y manta con palmeras. Usa 12 trampas, en 6 filas de 2. Dimension de tampa 1.5x3 m | CO5: 25 | CP5: 72 | CQ5: 7-8 | CR5: 500-1000 | CS5: 4000-7000 | CT5: Acopiador | CU5: 24 | CV5: Zona: Ova (40 millas fuera de Marcona); Bonito (20-100 millas fuera de Marcona, Callao, Pisco); Perico (150 millas fuera de Marcona). Ova con ojo: no se compra. | CY5: Ova (40 millas fuera de Marcona)
A6: KD-PUCUSANA-005 | B6: Kelly Diaz | C6: 45884 | D6: Zacarias Juan Chavez Truevas | E6: 41845641 | F6: 20 | G6: 20 | H6: Pucusana | I6: Pucusana | J6: Pucusana | K6: 30430 | L6: =DATEDIF(K6, DATE(2025,8,29), "Y") -> 42 | M6: M | N6: Casado/Conviviente | O6: Superior Técnico | P6: si | Q6: si | R6: Armador, Patrón | S6: si | T6: Asociación Gremio de Pescadores de Pucusana | U6: no | V6: NA | W6: NA | X6: NA | Y6: NA | Z6: NA | AA6: NA | AB6: si | AC6: Entrenador de futbol | AD6: 2 | AE6: 3 | AF6: si | AG6: Turismo y Limpieza | AH6: si | AI6: 1 hijo: tripulante | AJ6: si | AK6: NA | AL6: si | AM6: NA | AN6: 3 (solo 1 opera) | AO6: si | AP6: NIÑO JESUS | AQ6: TA-60295-BM | AR6: no | AS6: no | AT6: si | AU6: 8 | AV6: NA | AW6: NA | AX6: NA | AY6: NA | AZ6: NA | BA6: NA | BB6: 200-250 | BC6: Pinta Potera | BD6: 4-5 | BE6: 25-46 | BF6: Peruana | BG6: Pota | BH6: no | BI6: Enero-Diciembre | BJ6: 24-48 | BK6: 2-4 viajes/mes | BL6: 7 | BM6: NS | BN6: NS | BO6: 500-1000 | BP6: 1000-5000 | BQ6: Acopiador | BR6: 1-4 | BS6: Pinta | BT6: 3 | BU6: 25-46 | BV6: Peruana | BW6: Bonito | BX6: no | BY6: Enero-Diciembre | BZ6: 12 | CA6: 1 viaje/mes. No es una pesca constante | CB6: 4-5 | CC6: NS | CD6: NS | CE6: 100-400 | CF6: 200-2000 | CG6: Acopiador | CH6: 5 | CI6: NA | CJ6: NA | CK6: NA | CL6: NA | CM6: NA | CN6: NA | CO6: NA | CP6: NA | CQ6: NA | CR6: NA | CS6: NA | CT6: NA | CU6: NA | CV6: Zona: Bonito (15 millas fuera de Pachacamac y Pucusana); Pota (50-170 millas fuera de Paita a Pucusana). Opina que los costos de los pescadores para participar en la pesca exploratoria deben ser cubiertos por IMARPE. El SISESAT debe tener contratos mas cortos (el minimo es de 6 meses) porque cuando quedan varados (por ejemplo, por veda) se gastan esos meses de contrato pero ellos no estan generando dinero. Sobre la ova, la ova del Peru es mas rica en nutrientes, por lo que se vende mas caro. | CW6: 959 963 258
A7: KD-PUCUSANA-006 | B7: Kelly Diaz | C7: 45884 | D7: Carlos Alfonso Navarrete La Madrid | E7: 10819413 | F7: 39 | G7: 1 | H7: Pucusana | I7: Pucusana | J7: Pucusana, Pisco, Callao | K7: 26850 | L7: =DATEDIF(K7, DATE(2025,8,29), "Y") -> 52 | M7: M | N7: Casado/Conviviente | O7: Secundaria | P7: si | Q7: Privado | R7: Armador | S7: si | T7: Asociación Gremio de Pescadores de Pucusana | U7: si | V7: Pinta | W7: bonito | X7: Cerco costero | Y7: Caballa, lorna | Z7: NA | AA7: NA | AB7: no | AC7: NA | AD7: 2 | AE7: 2 | AF7: si | AG7: Obstetra | AH7: no | AI7: NA | AJ7: si | AK7: NA | AL7: si | AM7: NA | AN7: 2 | AO7: si | AP7: MICAELA Y ADRIAN | AQ7: CO-59871-BM | AR7: no | AS7: no | AT7: si | AU7: 6 | AV7: MICAELA Y ADRIAN | AW7: PS-56767-BM | AX7: no | AY7: no | AZ7: si | BA7: 6 | BB7: 300-350 | BC7: Pinta Potera | BD7: 3-4 | BE7: 30-60 | BF7: Peruana | BG7: Pota | BH7: no | BI7: Diciembre-Junio | BJ7: 25-28 | BK7: 4 viajes/mes | BL7: 4 | BM7: NS | BN7: NS | BO7: 500-1000 | BP7: 4000-5000 | BQ7: Acopiador, minorista (chinchanos, para el mercado local compran la pota chancada) | BR7: 1-6 | BS7: NA | BT7: NA | BU7: NA | BV7: NA | BW7: NA | BX7: NA | BY7: NA | BZ7: NA | CA7: NA | CB7: NA | CC7: NA | CD7: NA | CE7: NA | CF7: NA | CG7: NA | CH7: NA | CI7: NA | CJ7: NA | CK7: NA | CL7: NA | CM7: NA | CN7: NA | CO7: NA | CP7: NA | CQ7: NA | CR7: NA | CS7: NA | CT7: NA | CU7: NA | CV7: Zona: Pota (20-150 millas fuera de Marcona y La Planchada). La pesca de la pota la realizan todo el dia, parando talvez 1 hora de vez en cuando para descansar, pero tomando turnos para que alguien siempre este atento a la muestra (1 linea siempre queda en el agua). El comprador minorista de la pota le llaman "chinchano" que compran la pota chancada para el mercado local. Sobre la ova, el sabe que las hembras liberan sus huevos debajo de la estera, y los machos su esperma por encima de la estera. La estera queda como espoonja. | CW7: 941 451 916
A8: KD-PUCUSANA-007 | B8: Kelly Diaz | C8: 45884 | D8: Ismael Porfirio Rueda Navarro | E8: 07896918 | F8: 52 | G8: 44 | H8: Pucusana | I8: Pucusana | J8: Pucusana | K8: 23359 | L8: =DATEDIF(K8, DATE(2025,8,29), "Y") -> 61 | M8: M | N8: Divorciado | O8: Secundaria | P8: si | Q8: si | R8: Armador, Patrón | S8: si | T8: Asociación Gremio de Pescadores de Pucusana | U8: si | V8: Cortina costera | W8: pejerrey | X8: NA | Y8: NA | Z8: NA | AA8: NA | AB8: no | AC8: NA | AD8: 2 | AE8: 2 | AF8: no | AG8: NA | AH8: si | AI8: 1 hijo: mantenimiento y a veces tripulante | AJ8: no | AK8: La fuerza fisica natural no es la misma | AL8: no | AM8: no se suele llevar mujeres a altura | AN8: 2 | AO8: si | AP8: ISMAEL Y LEO | AQ8: CO-39328-BM | AR8: no | AS8: no | AT8: si | AU8: 3.7 | AV8: ISMAEL Y LEO III | AW8: CO-43396-BM | AX8: no | AY8: no | AZ8: si | BA8: 6.48 | BB8: 140-270 | BC8: Cortina superficial | BD8: 3-4 | BE8: 30-40 | BF8: Peruana | BG8: Bonito | BH8: no | BI8: Octubre-Abril | BJ8: 25-28 | BK8: #paños: 10, cocada: 4 pulgadas, malla 6 x 100 m | BL8: 4-5 | BM8: 2-3 | BN8: 12-20 | BO8: 300-2000 | BP8: 3000-6000 | BQ8: Acopiador | BR8: 5 | BS8: Pinta Potera | BT8: 3-4 | BU8: 30-40 | BV8: Peruana | BW8: Pota | BX8: no | BY8: Septiembre-Junio | BZ8: 35-40 | CA8: 4 viajes/mes | CB8: 4-5 | CC8: NS | CD8: NS | CE8: 500-1000 | CF8: 4000-5000 | CG8: Acopiador | CH8: 1.8 | CI8: Trampa Ovas | CJ8: Ova | CK8: no | CL8: Septiembre-Diciembre | CM8: 3 | CN8: Esteras y manta con palmeras y manguera. Usa 12 trampas, en 4 filas de 3. Dimension de tampa 2x2.9 m | CO8: 40 | CP8: 72 | CQ8: 10-12 | CR8: 80-100 | CS8: 1000-1500 | CT8: Acopiador | CU8: 26-37 | CV8: Zona: Ova (40 millas fuera de Marcona); Bonito (40 millas fuera de Pisco y Chancay); Pota (40 millas fuera de Pisco y Chancay). Ova con ojo no se vende. La manguera es mas economica a largo plazo. La trampa se coloca al ras del agua. | CW8: 940 906 288 | CY8: Ova (40 millas fuera de Marcona)
A9: KD-PUCUSANA-008 | B9: Kelly Diaz | C9: 45884 | D9: Isaias Torrejon Fernandez | E9: 07896692 | F9: 60 | G9: 37 | H9: Pucusana | I9: Pucusana | J9: Pucusana, Salaverry, Marcona, Callao | K9: 18052 | L9: =DATEDIF(K9, DATE(2025,8,29), "Y") -> 76 | M9: M | N9: Viudo | O9: Primaria | P9: si | Q9: Privado | R9: Armador | S9: si | T9: Asociación Gremio de Pescadores de Pucusana | U9: no | V9: NA | W9: NA | X9: NA | Y9: NA | Z9: NA | AA9: NA | AB9: si | AC9: Mantenimiento | AD9: 0 | AE9: 2 | AF9: no | AG9: NA | AH9: si | AI9: 1 hijo: armador | AJ9: si | AK9: NA | AL9: si | AM9: NA | AN9: 2 | AO9: si | AP9: MI JHOMA | AQ9: CO-06461-BM | AR9: no | AS9: no | AT9: si | AU9: 4 | AV9: MI JHOMA II | AW9: CO-19588-BM | AX9: no | AY9: no | AZ9: si | BA9: 5 | BB9: 320-360 | BC9: Trampa Ovas | BD9: 3 | BE9: 30-60 | BF9: Peruana | BG9: Ova | BH9: no | BI9: Septiembre-Marzo | BJ9: 3-4 | BK9: Esteras y manta, con palmeras. Usa 15-20 trampas, en 4 filas de 5. Dimensiones de trampa 3x2 metros | BL9: 30 | BM9: 72 | BN9: 10 | BO9: 300-450 | BP9: 1000-2000 | BQ9: Acopiador | BR9: 42 | BS9: NA | BT9: NA | BU9: NA | BV9: NA | BW9: NA | BX9: NA | BY9: NA | BZ9: NA | CA9: NA | CB9: NA | CC9: NA | CD9: NA | CE9: NA | CF9: NA | CG9: NA | CH9: NA | CI9: NA | CJ9: NA | CK9: NA | CL9: NA | CM9: NA | CN9: NA | CO9: NA | CP9: NA | CQ9: NA | CR9: NA | CS9: NA | CT9: NA | CU9: NA | CV9: Zona: Ova (100-120 millas fuera de Atico, Pisco, Marcona, Bayovar). Precio (kg) de ova con ojo: 5 soles. 70 a 80 kg de 1000 a 2000 kg del total, son ovas con ojo. Palmera puede costar S/.12 c/u, llevan 250. Antes, salian a la ova por 2 a 3 semanas, pero desde hace 2 años salen mminimo 1 mes, para que sea 1 solo gasto. Es posible hacer estos viajes largos para la ova porque al recoger la ova, la salan y la dejan al sol por 1 a 2 horas. Esto hace que se reduzca el tamano y que dure mas tiempo el producto. Una vez en muelle, se echa la ova en una tina por 1 a 2 hr y vuelve a la normalidad. La estera y la manta van al nivel del agua, y luego de 15 a 20 cm va la palmera. | CW9: 995 951 601 | CY9: Ova (100-120 millas fuera de Atico, Pisco, Marcona, Bayovar)
A10: KD-PUCUSANA-009 | B10: Kelly Diaz | C10: 45884 | D10: Andres Jesus Alberto Caycho Carrillo | E10: 73478799 | F10: 3 | G10: 2 | H10: Pucusana | I10: Pucusana | J10: Pucusana | K10: 35143 | L10: =DATEDIF(K10, DATE(2025,8,29), "Y") -> 29 | M10: M | N10: Soltero | O10: Superior Universitario | P10: si | Q10: si | R10: Tripulación | S10: si | T10: Asociación Gremio de Pescadores de Pucusana | U10: no | V10: NA | W10: NA | X10: NA | Y10: NA | Z10: NA | AA10: NA | AB10: si | AC10: Integración comunitaria | AD10: 1 | AE10: 1 | AF10: no | AG10: NA | AH10: no | AI10: NA | AJ10: no | AK10: por el machismo | AL10: no | AM10: aun hay muchos pescadores machistas | AN10: NS | AO10: no | AP10: NA | AQ10: NA | AR10: NA | AS10: NA | AT10: NA | AU10: NA | AV10: NA | AW10: NA | AX10: NA | AY10: NA | AZ10: NA | BA10: NA | BB10: NS | BC10: Cerco | BD10: 4-5 | BE10: 25-35 | BF10: Peruana | BG10: Bonito | BH10: no | BI10: Noviembre-Enero | BJ10: 25-35 | BK10: no recuerda | BL10: 4-7 | BM10: 1-2 | BN10: 8-20 | BO10: 300-1000 | BP10: 4000 | BQ10: Acopiador | BR10: 2.5 | BS10: Espinel | BT10: 4 | BU10: 25-35 | BV10: Peruana | BW10: Perico | BX10: si | BY10: Noviembre-Marzo | BZ10: 5-10 | CA10: no sabe | CB10: 5-20 | CC10: 3-4 | CD10: 5-15 | CE10: 500-1000 | CF10: 2000-4000 | CG10: Acopiador | CH10: NS | CI10: NA | CJ10: NA | CK10: NA | CL10: NA | CM10: NA | CN10: NA | CO10: NA | CP10: NA | CQ10: NA | CR10: NA | CS10: NA | CT10: NA | CU10: NA | CV10: Zona: Bonito (50-60 millas fuera de Pucusana); Perico (120 millas fuera de Lima a Pucusana). Se dedica mas a la integracion comunitaria en temas marinos, enseñando a niños | CW10: 961 830 866
A11: KD-PUCUSANA-010 | B11: Kelly Diaz | C11: 45885 | D11: Segundo Luis Morales Huertas "cochecho" | E11: 03325844 | F11: 30 | G11: 30 | H11: Pucusana | I11: Pucusana | J11: Pucusana | K11: 25106 | L11: =DATEDIF(K11, DATE(2025,8,29), "Y") -> 56 | M11: M | N11: Casado/Conviviente | O11: Primaria | P11: si | Q11: si | R11: Armador, Patrón | S11: si | T11: Asociación de Armadores de Lanchas | U11: si | V11: Cortina costera | W11: bonito | X11: NA | Y11: NA | Z11: NA | AA11: NA | AB11: si | AC11: Mototaxi | AD11: 1 | AE11: 5 | AF11: si | AG11: Ama de casa | AH11: no | AI11: NA | AJ11: si | AK11: NA | AL11: si | AM11: NA | AN11: 1 | AO11: si | AP11: MAR DE LOS ANGELES | AQ11: CO-65907-BM | AR11: no | AS11: no | AT11: si | AU11: 13.73 | AV11: NA | AW11: NA | AX11: NA | AY11: NA | AZ11: NA | BA11: NA | BB11: 300-400 | BC11: Cortina superficial | BD11: 5 | BE11: 25-40 | BF11: Peruana | BG11: Tollo, Espada | BH11: si, caballa, tamborin | BI11: Enero-Diciembre | BJ11: 24-48 | BK11: malla 4.5 x 9250 m; con llevador (winche) | BL11: 17-18 | BM11: 3 | BN11: 15 | BO11: 300-500 | BP11: 8000-9000 | BQ11: Acopiador | BR11: 1.5 | BS11: Trampa Ovas | BT11: 2-4 | BU11: 25-40 | BV11: Peruana | BW11: Ova | BX11: no | BY11: Septiembre-Febrero | BZ11: 2 | CA11: Esteras y manta, con palmeras. Usa 18-20 trampas, en 3 filas de 6. Dimensiones de trampa 1.5x2 metros | CB11: 30-60 | CC11: 72 | CD11: 20-30 | CE11: 75-300 | CF11: 1000-5000 | CG11: Acopiador | CH11: 25-70 | CI11: Espinel | CJ11: Perico, Tollo | CK11: si, pota | CL11: Enero-Diciembre; Noviembre-Marzo | CM11: 12-24 | CN11: Linea madre: 12000 m. #anzuelos: 2500. 1 anzuelo/linea. Calibre: Tollo 2, Perico 5-6 | CO11: 8-10 | CP11: 2-3 | CQ11: 16 | CR11: 1000-3000 | CS11: 8000-9000 | CT11: Acopiador | CU11: 5 | CV11: Zona: Tollo (150-170 millas fuera de Ilo, La Planchada, Pisco); Ova (20 millas fuera de Ilo a Huacho); Perico (400 millas fuera de Pucusana). Sobre la ova, de Sep-Nov la trampa se deja 3 dias, y de Nov-Feb por 2 dias. Muy colaborador | CW11: 945 516 722 | CY11: Ova (20 millas fuera de Ilo a Huacho)
A12: KD-PUCUSANA-011 | B12: Kelly Diaz | C12: 45885 | D12: Juan De Dios Alvarez Garcia | E12: 07897247 | F12: 53 | G12: 45 | H12: Pucusana | I12: Pucusana | J12: Pucusana | K12: 21983 | L12: =DATEDIF(K12, DATE(2025,8,29), "Y") -> 65 | M12: M | N12: Viudo | O12: Superior Técnico | P12: si | Q12: si | R12: Tripulación | S12: si | T12: Asociación Gremio de Pescadores de Pucusana | U12: si | V12: Cortina costera | W12: pejerrey | X12: pinta | Y12: pota | Z12: NA | AA12: NA | AB12: si | AC12: Armador de embarcacion de costa | AD12: 0 | AE12: 2 | AF12: no | AG12: NA | AH12: si | AI12: 1 hijo: tripulante | AJ12: si | AK12: NA | AL12: si | AM12: NA | AN12: 2 (de costa ambas) | AO12: si | AP12: TITAN I | AQ12: CO-52539-BM | AR12: no | AS12: no | AT12: si | AU12: NS | AV12: TITAN II | AW12: CO-52540-BM | AX12: no | AY12: no | AZ12: si | BA12: NA | BB12: 450 | BC12: Cerco | BD12: 3 | BE12: 20-50 | BF12: Peruana | BG12: Bonito | BH12: no | BI12: Diciembre-Marzo | BJ12: 8 | BK12: con llevador (winche) | BL12: 7 | BM12: 1.5-3 | BN12: 10-14 | BO12: 200-250 | BP12: 2000 | BQ12: Acopiador | BR12: 1-5 | BS12: Cerco | BT12: 3 | BU12: 20-50 | BV12: Peruana | BW12: Tollo | BX12: no | BY12: Diciembre-Marzo | BZ12: 4-5 | CA12: con llevador (winche) | CB12: 15 | CC12: 10 | CD12: 12-15 | CE12: 300 | CF12: 6000-8000 | CG12: Acopiador | CH12: 2-7 | CI12: NA | CJ12: NA | CK12: NA | CL12: NA | CM12: NA | CN12: NA | CO12: NA | CP12: NA | CQ12: NA | CR12: NA | CS12: NA | CT12: NA | CU12: NA | CV12: Zona: Tollo (120-150 millas fuera de Pisco a Callao); Bonito (60-80 millas fuera de Pisco a Callao). | CW12: 923 593 622
A13: KD-PUCUSANA-012 | B13: Kelly Diaz | C13: 45885 | D13: Maria Antonieta Yzarnotegui Moreno | E13: 07386158 | F13: 25 | G13: 2 | H13: Pucusana | I13: Pucusana | J13: Pucusana | K13: 23900 | L13: =DATEDIF(K13, DATE(2025,8,29), "Y") -> 60 | M13: F | N13: Soltero | O13: Primaria | P13: si | Q13: Privado | R13: Tripulación | S13: no | T13: NA | U13: si | V13: Cortina costera | W13: pejerrey, bonito | X13: NA | Y13: NA | Z13: NA | AA13: NA | AB13: si | AC13: Decoración, Armador de embarcacion de costa | AD13: 0 | AE13: 2 | AF13: no | AG13: NA | AH13: si | AI13: 1 hijo: dueño | AJ13: si | AK13: NA | AL13: si | AM13: NA | AN13: 1 (de costa) | AO13: si | AP13: VICENZO | AQ13: CO-56337-BM | AR13: no | AS13: no | AT13: si | AU13: NA | AV13: NA | AW13: NA | AX13: NA | AY13: NA | AZ13: NA | BA13: NA | BB13: 340-360 | BC13: Cerco | BD13: 3-4 | BE13: 20-55 | BF13: Peruana | BG13: Bonito | BH13: no | BI13: Febrero-Mayo | BJ13: 7-9 | BK13: sin winche; superficial | BL13: 3-7 | BM13: 2-3 | BN13: 10-15 | BO13: 100-1000 | BP13: 400-4000 | BQ13: Acopiador | BR13: 1.5 | BS13: Trampa Ovas | BT13: 3-4 | BU13: 20-55 | BV13: Peruana | BW13: Ova | BX13: no | BY13: Septiembre-Febrero | BZ13: 4-5 | CA13: Esteras y manta, con zargazo. | CB13: 30 | CC13: 48-72 | CD13: 10-15 | CE13: 100 | CF13: 100-1000 | CG13: Acopiador | CH13: 16-45 | CI13: NA | CJ13: NA | CK13: NA | CL13: NA | CM13: NA | CN13: NA | CO13: NA | CP13: NA | CQ13: NA | CR13: NA | CS13: NA | CT13: NA | CU13: NA | CV13: Zona:Bonito (20-70 millas fuera de Marcona); Ova (150 millas fuera de Marcona). Una vez humedecida la trampa, ya no se puede volver a usar. Algunos peces voladores mueren despues de liberar sus gametos. La trampa se coloca al ras del agua, la embarcacion va al garete (a la deriva). Muy colaboradora | CW13: 945 489 966 | CY13: Ova (150 millas fuera de Marcona)
A14: KD-PUCUSANA-013 | B14: Kelly Diaz | C14: 45885 | D14: Erick Santacruz | E14: 48352437 | F14: 8 | G14: 8 | H14: Chilca | I14: Pucusana | J14: Pucusana | K14: 33891 | L14: =DATEDIF(K14, DATE(2025,8,29), "Y") -> 32 | M14: M | N14: Casado/Conviviente | O14: Secundaria | P14: si | Q14: si | R14: Tripulación | S14: no | T14: NA | U14: no | V14: NA | W14: NA | X14: NA | Y14: NA | Z14: NA | AA14: NA | AB14: si | AC14: Negocio | AD14: 3 | AE14: 2 | AF14: si | AG14: Ama de casa | AH14: no | AI14: NA | AJ14: no | AK14: La fuerza fisica natural no es la misma | AL14: si | AM14: NA | AN14: 0 | AO14: no | AP14: NA | AQ14: NA | AR14: NA | AS14: NA | AT14: NA | AU14: NA | AV14: NA | AW14: NA | AX14: NA | AY14: NA | AZ14: NA | BA14: NA | BB14: 300-400 | BC14: Pinta Potera | BD14: 3-4 | BE14: 16-55 | BF14: Peruana | BG14: Pota | BH14: no | BI14: Enero-Diciembre | BJ14: 24-36 | BK14: 2-3 viajes/mes | BL14: 4-11 | BM14: NS | BN14: NS | BO14: 1000-2000 | BP14: 15000-20000 | BQ14: Acopiador | BR14: 3 | BS14: NA | BT14: NA | BU14: NA | BV14: NA | BW14: NA | BX14: NA | BY14: NA | BZ14: NA | CA14: NA | CB14: NA | CC14: NA | CD14: NA | CE14: NA | CF14: NA | CG14: NA | CH14: NA | CI14: NA | CJ14: NA | CK14: NA | CL14: NA | CM14: NA | CN14: NA | CO14: NA | CP14: NA | CQ14: NA | CR14: NA | CS14: NA | CT14: NA | CU14: NA | CV14: Zona: Pota (30-200 millas fuera de Marcona a Pisco).
A15: KD-PUCUSANA-014 | B15: Kelly Diaz | C15: 45885 | D15: Jose Luis Sanchez Cardenas | E15: 07895056 | F15: 51 | G15: 36 | H15: Pucusana | I15: Pucusana | J15: Pucusana | K15: 23685 | L15: =DATEDIF(K15, DATE(2025,8,29), "Y") -> 60 | M15: M | N15: Casado/Conviviente | O15: Primaria | P15: si | Q15: si | R15: Patrón | S15: si | T15: Asociación Gremio de Pescadores de Pucusana | U15: si | V15: Cortina costera | W15: pejerrey | X15: NA | Y15: NA | Z15: NA | AA15: NA | AB15: no | AC15: NA | AD15: 5 | AE15: 2 | AF15: si | AG15: Negocio | AH15: no | AI15: NA | AJ15: si | AK15: NA | AL15: si | AM15: NA | AN15: 0 | AO15: no | AP15: NA | AQ15: NA | AR15: NA | AS15: NA | AT15: NA | AU15: NA | AV15: NA | AW15: NA | AX15: NA | AY15: NA | AZ15: NA | BA15: NA | BB15: 340-360 | BC15: Cortina superficial | BD15: 4-5 | BE15: 20-40 | BF15: Peruana | BG15: Bonito | BH15: no | BI15: Diciembre-Marzo | BJ15: 12 | BK15: #paños: 7, cocada: 4 pulgadas, malla 4.5 x 100 m | BL15: 7 | BM15: 2-3 | BN15: 12-18 | BO15: 1000 | BP15: 5000-6000 | BQ15: Acopiador | BR15: 1.5 | BS15: Cortina superficial | BT15: 4-5 | BU15: 20-40 | BV15: Peruana | BW15: Perico | BX15: no | BY15: Diciembre-Marzo | BZ15: 12 | CA15: #paños: 7, cocada: 5 pulgadas, malla 50 x 105 m | CB15: 7 | CC15: 2-3 | CD15: 10-12 | CE15: 1000 | CF15: 5000-6000 | CG15: Acopiador | CH15: 3.5-4 | CI15: Trampa Ovas | CJ15: Ova | CK15: no | CL15: Octubre-Marzo | CM15: 2 | CN15: Esteras y manta, con palmeras. Usa 15-16 trampas. Dimensiones de trampa 1.5x2.5 metros | CO15: 45-60 | CP15: 72 | CQ15: 15-20 | CR15: 150-300 | CS15: 1000-5000 | CT15: Acopiador | CU15: 40 | CV15: Zona: Bonito (20-60 millas fuera de Pucusana, Pisco); Perico (20-100 millas fuera de Pucusana, Pisco); Ova (100-120 millas fuera de Marcona). La estera cuando tiene huevos llama a mas peces. Llevan 30 esteras extras | CW15: 976 118 007 | CY15: Ova (100-120 millas fuera de Marcona)
A16: KD-PUCUSANA-015 | B16: Kelly Diaz | C16: 45885 | D16: Hilder Yangua Lloclla | E16: 42878933 | F16: 20 | G16: 20 | H16: Pucusana | I16: Pucusana | J16: Pucusana | K16: 30904 | L16: =DATEDIF(K16, DATE(2025,8,29), "Y") -> 41 | M16: M | N16: Casado/Conviviente | O16: Secundaria | P16: si | Q16: si | R16: Armador, Patrón | S16: no | T16: NA | U16: no | V16: NA | W16: NA | X16: NA | Y16: NA | Z16: NA | AA16: NA | AB16: no | AC16: NA | AD16: 3 | AE16: 2 | AF16: si | AG16: Ama de casa | AH16: no | AI16: NA | AJ16: si | AK16: NA | AL16: si | AM16: NA | AN16: 2 (solo 1 opera) | AO16: si | AP16: MILAGRO DE JESUS II | AQ16: IO-21998-BM | AR16: no | AS16: no | AT16: no | AU16: 21.4 | AV16: NA | AW16: NA | AX16: NA | AY16: NA | AZ16: NA | BA16: NA | BB16: 1000 | BC16: Espinel | BD16: 5 | BE16: 25-40 | BF16: Peruana | BG16: Tollo | BH16: si, caballa | BI16: Abril-Octubre | BJ16: 6 | BK16: Linea madre: 18 millas. #anzuelos: 1000. 1 anzuelo/linea. Calibre: 3 | BL16: 26 | BM16: 14 | BN16: 10-15 | BO16: 100-1000 | BP16: 4000-12000 | BQ16: Acopiador | BR16: 4 | BS16: NA | BT16: NA | BU16: NA | BV16: NA | BW16: NA | BX16: NA | BY16: NA | BZ16: NA | CA16: NA | CB16: NA | CC16: NA | CD16: NA | CE16: NA | CF16: NA | CG16: NA | CH16: NA | CI16: NA | CJ16: NA | CK16: NA | CL16: NA | CM16: NA | CN16: NA | CO16: NA | CP16: NA | CQ16: NA | CR16: NA | CS16: NA | CT16: NA | CU16: NA | CV16: Zona: Tollo azul (100-400 millas fuera de Marcona) | CW16: 982 088 280
A17: KD-PUCUSANA-016 | B17: Kelly Diaz | C17: 45887 | D17: Roberto Augusto Chumpitaz Flores | E17: 07897817 | F17: 47 | G17: 20 | H17: Pucusana | I17: Pucusana | J17: Pucusana | K17: 25848 | L17: =DATEDIF(K17, DATE(2025,8,29), "Y") -> 54 | M17: M | N17: Casado/Conviviente | O17: Secundaria | P17: si | Q17: si | R17: Armador, Patrón | S17: si | T17: Asociación Gremio de Pescadores de Pucusana | U17: si | V17: Cortina costera | W17: pejerrey | X17: NA | Y17: NA | Z17: NA | AA17: NA | AB17: no | AC17: NA | AD17: 1 | AE17: 3 | AF17: si | AG17: Promotora de educación | AH17: no | AI17: NA | AJ17: si | AK17: NA | AL17: si | AM17: NA | AN17: 1 | AO17: si | AP17: TORNADO | AQ17: CO-37583-BM | AR17: no | AS17: no | AT17: si | AU17: 5 | AV17: NA | AW17: NA | AX17: NA | AY17: NA | AZ17: NA | BA17: NA | BB17: 320-360 | BC17: Cortina superficial | BD17: 4 | BE17: 40-50 | BF17: Peruana | BG17: Tollo | BH17: no | BI17: Enero-Febrero | BJ17: 4 | BK17: #paños: 20, cocada: 6 pulgadas, malla 6 x 75 m | BL17: 10-15 | BM17: 10-12 | BN17: 10-12 | BO17: 300-500 | BP17: 1500 | BQ17: Acopiador | BR17: 1.2-2.5 | BS17: Espinel | BT17: 4 | BU17: 40-50 | BV17: Peruana | BW17: Perico | BX17: si, pota | BY17: Noviembre-Diciembre | BZ17: 4 | CA17: Linea madre: 1500 m. #anzuelos:1000. 1 anzuelo/linea. Calibre: 2 | CB17: 8-10 | CC17: 2-5 | CD17: 6-10 | CE17: 300-1000 | CF17: 3000-4000 | CG17: Acopiador | CH17: 7-8 | CI17: NA | CJ17: NA | CK17: NA | CL17: NA | CM17: NA | CN17: NA | CO17: NA | CP17: NA | CQ17: NA | CR17: NA | CS17: NA | CT17: NA | CU17: NA | CV17: Zona: Tollo (70-80 millas fuera de Pisco); Perico (100 millas fuera de Pucusana, Pisco, Ancon). Para el espinel, recorren la linea por completo revisando, y al segundo recorrido levantan toda la linea (total 10 horas) | CW17: 990 478 848
A18: KD-PUCUSANA-017 | B18: Kelly Diaz | C18: 45887 | D18: Marcos Eugenio Santisteban Sandoval | E18: 02737661 | F18: 20 | G18: 20 | H18: Pucusana | I18: Pucusana | J18: Pucusana | K18: 26290 | L18: =DATEDIF(K18, DATE(2025,8,29), "Y") -> 53 | M18: M | N18: Casado/Conviviente | O18: Secundaria | P18: si | Q18: no | R18: Armador | S18: si | T18: Asociación Gremio de Pescadores de Pucusana | U18: si | V18: Cortina costera | W18: pejerrey | X18: NA | Y18: NA | Z18: NA | AA18: NA | AB18: no | AC18: NA | AD18: 4 | AE18: 3 | AF18: si | AG18: Ama de casa | AH18: si | AI18: 1 hijo: tripulante | AJ18: no | AK18: Pesca de altura es peligrosa, vientos fuertes | AL18: si | AM18: NA | AN18: 1 | AO18: si | AP18: JIRETH I | AQ18: PS-26309-BM | AR18: no | AS18: si | AT18: si | AU18: 8 | AV18: JIRETH I | AW18: NA | AX18: NA | AY18: NA | AZ18: NA | BA18: NA | BB18: 250-300 | BC18: Cortina superficial | BD18: 4-5 | BE18: 20-40 | BF18: Peruana | BG18: Bonito | BH18: no | BI18: Diciembre-Junio | BJ18: 12-14 | BK18: #paños: 6-7, cocada: 4 pulgadas, malla 9 x 105 m | BL18: 7 | BM18: 2-4 | BN18: 4-5 | BO18: 500-1000 | BP18: 2000-5000 | BQ18: Acopiador | BR18: 2 | BS18: Pinta Potera | BT18: 4-5 | BU18: 20-40 | BV18: Peruana | BW18: Pota | BX18: no | BY18: Mayo-Julio | BZ18: 6-9 | CA18: 2-3 viajes/mes | CB18: 7 | CC18: NS | CD18: NS | CE18: 1000-2000 | CF18: 6000-7000 | CG18: Acopiador | CH18: 2.2 | CI18: NA | CJ18: NA | CK18: NA | CL18: NA | CM18: NA | CN18: NA | CO18: NA | CP18: NA | CQ18: NA | CR18: NA | CS18: NA | CT18: NA | CU18: NA | CV18: Zona: Bonito (70-80 millas fuera de Callao a Pisco); Pota (70-80 millas fuera de Callao, Pucusana, Pisco). | CW18: 933 957 502
A19: KD-PUCUSANA-018 | B19: Kelly Diaz | C19: 45887 | D19: Carlos Alexander Florian Peña | E19: 40515591 | F19: 27 | G19: 20 | H19: Pucusana | I19: Pucusana | J19: Pucusana, Callao, etc | K19: 29288 | L19: =DATEDIF(K19, DATE(2025,8,29), "Y") -> 45 | M19: M | N19: Casado/Conviviente | O19: Superior Técnico | P19: si | Q19: Privado | R19: Patrón | S19: si | T19: Asociación Gremio de Pescadores de Pucusana | U19: si | V19: Cortina costera | W19: pejerrey, chauchilla | X19: NA | Y19: NA | Z19: NA | AA19: NA | AB19: no | AC19: NA | AD19: 3 | AE19: 2 | AF19: si | AG19: Cocinera | AH19: no | AI19: NA | AJ19: si | AK19: NA | AL19: si | AM19: NA | AN19: 0 | AO19: no | AP19: NA | AQ19: NA | AR19: NA | AS19: NA | AT19: NA | AU19: NA | AV19: NA | AW19: NA | AX19: NA | AY19: NA | AZ19: NA | BA19: NA | BB19: 180 | BC19: Espinel | BD19: 4 | BE19: 25-30 | BF19: Peruana | BG19: Perico | BH19: si, pota, barrilete | BI19: Diciembre-Enero | BJ19: 5-7 | BK19: Linea madre: 8000 metros. #anzuelos: 1000. 1 anzuelo/linea. Calibre: 3 | BL19: 6 | BM19: 2-5 | BN19: 4-5 | BO19: 200-400 | BP19: 2000 | BQ19: Acopiador | BR19: 5-10 | BS19: Trampa Ovas | BT19: 4 | BU19: 25-30 | BV19: Peruana | BW19: Ova | BX19: no | BY19: Septiembre-Noviembre | BZ19: 2 | CA19: Esteras y manta, con palmeras. Usa 3 trampas. | CB19: 30 | CC19: 48-72 | CD19: 10-15 | CE19: 100-200 | CF19: 1000-1500 | CG19: Acopiador | CH19: 32 | CI19: NA | CJ19: NA | CK19: NA | CL19: NA | CM19: NA | CN19: NA | CO19: NA | CP19: NA | CQ19: NA | CR19: NA | CS19: NA | CT19: NA | CU19: NA | CV19: Zona: Perico (80-100 millas fuera de Pucusana); Ovas (100 millas fuera de Marcona). Las trampas se colocan, en orden de abajo hacia arriba: palmera, estera, manta. | CW19: 961 285 950 | CY19: Ovas (100 millas fuera de Marcona)
A20: KD-PUCUSANA-019 | B20: Kelly Diaz | C20: 45887 | D20: Frank Ericson Bravo Tapia | E20: 42154834 | F20: 15 | G20: 15 | H20: Pucusana | I20: Pucusana | J20: Pucusana | K20: 30314 | L20: =DATEDIF(K20, DATE(2025,8,29), "Y") -> 42 | M20: M | N20: Divorciado | O20: Secundaria | P20: si | Q20: si | R20: Tripulación | S20: si | T20: Asociación Gremio de Pescadores de Pucusana | U20: no | V20: NA | W20: NA | X20: NA | Y20: NA | Z20: NA | AA20: NA | AB20: si | AC20: Turismo | AD20: 0 | AE20: 2 | AF20: no | AG20: NA | AH20: no | AI20: NA | AJ20: si | AK20: NA | AL20: si | AM20: NA | AN20: 0 | AO20: no | AP20: NA | AQ20: NA | AR20: NA | AS20: NA | AT20: NA | AU20: NA | AV20: NA | AW20: NA | AX20: NA | AY20: NA | AZ20: NA | BA20: NA | BB20: 140-160 | BC20: Cortina superficial | BD20: 3 | BE20: 30-40 | BF20: Peruana | BG20: Bonito | BH20: no | BI20: Junio-Julio | BJ20: 6-8 | BK20: #paños: 10, cocada: 3.5-4 pulgadas | BL20: 3-4 | BM20: 1-2 | BN20: 12-18 | BO20: 200-1000 | BP20: 800-1400 | BQ20: Acopiador | BR20: no recuerda | BS20: Espinel | BT20: 3 | BU20: 30-40 | BV20: Peruana | BW20: Perico | BX20: si | BY20: Diciembre-Febrero | BZ20: 6-8 | CA20: #anzuelos:1200. 1 anzuelo/linea. Calibre: 3 | CB20: 10-11 | CC20: 2-5 | CD20: 10 | CE20: 800-1000 | CF20: 3000-5000 | CG20: Acopiador | CH20: NS | CI20: NA | CJ20: NA | CK20: NA | CL20: NA | CM20: NA | CN20: NA | CO20: NA | CP20: NA | CQ20: NA | CR20: NA | CS20: NA | CT20: NA | CU20: NA | CV20: Zona: Bonito (50 millas fuera de Pucusana); Perico (80-120 millas fuera de Marcona, Ilo). | CW20: 933 040 270
A21: KD-PUCUSANA-020 | B21: Kelly Diaz | C21: 45887 | D21: William Junior Machare Farfan | E21: 46412591 | F21: 12 | G21: 12 | H21: Pucusana | I21: Pucusana | J21: Pucusana, Atico, La Planchada | K21: 32740 | L21: =DATEDIF(K21, DATE(2025,8,29), "Y") -> 36 | M21: M | N21: Soltero | O21: Primaria | P21: si | Q21: No tiene | R21: Patrón | S21: no | T21: NA | U21: no | V21: NA | W21: NA | X21: NA | Y21: NA | Z21: NA | AA21: NA | AB21: no | AC21: NA | AD21: 5 | AE21: 3 | AF21: si | AG21: Profesional Independiente | AH21: no | AI21: NA | AJ21: si | AK21: NA | AL21: si | AM21: NA | AN21: 1 | AO21: no | AP21: MIKELA | AQ21: CO-20058-BM | AR21: no | AS21: no | AT21: si | AU21: 10 | AV21: NA | AW21: NA | AX21: NA | AY21: NA | AZ21: NA | BA21: NA | BB21: 250-280 | BC21: Trampa Ovas | BD21: 3-5 | BE21: 28-41 | BF21: Peruana | BG21: Ova | BH21: no | BI21: Septiembre-Marzo | BJ21: 7 | BK21: Esteras y manta, con palmeras o manguera. Usa 18 trampas, en 3 filas de 6. Dimensiones de trampa 3.2x3 metros | BL21: 30-40 | BM21: 72 | BN21: 10-12 | BO21: 120-150 | BP21: 800-2000 | BQ21: Acopiador | BR21: 35 | BS21: NA | BT21: NA | BU21: NA | BV21: NA | BW21: NA | BX21: NA | BY21: NA | BZ21: NA | CA21: NA | CB21: NA | CC21: NA | CD21: NA | CE21: NA | CF21: NA | CG21: NA | CH21: NA | CI21: NA | CJ21: NA | CK21: NA | CL21: NA | CM21: NA | CN21: NA | CO21: NA | CP21: NA | CQ21: NA | CR21: NA | CS21: NA | CT21: NA | CU21: NA | CV21: Zona: Ova (70-80 millas fuera de Atico, La Planchada). Ova con ojo no se vende. | CW21: 907 458 484 | CY21: Ova (70-80 millas fuera de Atico, La Planchada)
A22: KD-PUCUSANA-021 | B22: Kelly Diaz | C22: 45887 | D22: Genaro Angulo Guerra | E22: 07897867 | F22: 43 | G22: 41 | H22: Pucusana | I22: Pucusana | J22: Pucusana, Pisco | K22: 25679 | L22: =DATEDIF(K22, DATE(2025,8,29), "Y") -> 55 | M22: M | N22: Soltero | O22: Primaria | P22: si | Q22: si | R22: Armador, Patrón | S22: si | T22: Asociación Gremio de Pescadores de Pucusana | U22: si | V22: Pinta | W22: jurel, caballa, lorna, chauchilla | X22: Cortina costera | Y22: jurel, caballa, lorna, chauchilla | Z22: Cerco costero | AA22: jurel, caballa, lorna, chauchilla | AB22: no | AC22: NA | AD22: 1 | AE22: 3 | AF22: si | AG22: Compra y venta de pesca | AH22: si | AI22: 1 hijo: patrón y dueño | AJ22: si | AK22: NA | AL22: si | AM22: NA | AN22: 3 (solo 1 opera) | AO22: si | AP22: MI SEBASTIAN | AQ22: CO-41020-BM | AR22: no | AS22: no | AT22: si | AU22: 8 | AV22: NA | AW22: NA | AX22: NA | AY22: NA | AZ22: NA | BA22: NA | BB22: 180-360 | BC22: Cortina superficial | BD22: 8 | BE22: 25-50 | BF22: Peruana | BG22: Bonito | BH22: no | BI22: Octubre-Marzo | BJ22: 45-65 | BK22: #paños: 10, cocada: 4 pulgadas, malla 4.5 x 120 m | BL22: 2-7 | BM22: 1-2 | BN22: 6-30 | BO22: 200-2000 | BP22: 2000 | BQ22: Acopiador | BR22: 4-5 | BS22: Cortina superficial | BT22: 4 | BU22: 25-50 | BV22: Peruana | BW22: Perico | BX22: no | BY22: Octubre-Marzo | BZ22: 6 | CA22: #paños: 20, cocada: 6 pulgadas, malla 4.5 x 120 m | CB22: 15-30 | CC22: 3-4 | CD22: 30-40 | CE22: 200-2000 | CF22: 20000 | CG22: Acopiador | CH22: 9-18 | CI22: NA | CJ22: NA | CK22: NA | CL22: NA | CM22: NA | CN22: NA | CO22: NA | CP22: NA | CQ22: NA | CR22: NA | CS22: NA | CT22: NA | CU22: NA | CV22: Zona: Bonito (10-100 millas fuera de Chimbote a Callao); Perico (100-180 millas fuera de Ancon, Pisco). | CW22: 937 139 760
A23: KD-PUCUSANA-022 | B23: Kelly Diaz | C23: 45887 | D23: Pedro Miguel Baldiño Pisconte | E23: 44354186 | F23: 20 | G23: 20 | H23: Pucusana | I23: Pucusana | J23: Pucusana, Pisco, Callao | K23: 31592 | L23: =DATEDIF(K23, DATE(2025,8,29), "Y") -> 39 | M23: M | N23: Casado/Conviviente | O23: Secundaria | P23: si | Q23: si | R23: Armador | S23: si | T23: Asociación Gremio de Pescadores de Pucusana | U23: si | V23: Pinta | W23: pota, bonito, jurel | X23: NA | Y23: NA | Z23: NA | AA23: NA | AB23: no | AC23: NA | AD23: 5 | AE23: 2 | AF23: si | AG23: Ama de casa | AH23: no | AI23: NA | AJ23: si | AK23: NA | AL23: si | AM23: NA | AN23: 1 | AO23: si | AP23: JESUS RIVALDO | AQ23: CO-35916-BM | AR23: no | AS23: no | AT23: si | AU23: 4.5 | AV23: NA | AW23: NA | AX23: NA | AY23: NA | AZ23: NA | BA23: NA | BB23: 120 | BC23: Cortina superficial | BD23: 4 | BE23: 20-60 | BF23: Peruana | BG23: Bonito | BH23: no | BI23: Octubre-Febrero | BJ23: 10-15 | BK23: #paños: 8, cocada: 4 pulgadas, malla 4.5 x 4.5 m | BL23: 3-7 | BM23: 2-3 | BN23: 6-12 | BO23: 1000-4000 | BP23: 4000 | BQ23: Acopiador | BR23: 1-5 | BS23: Pinta Potera | BT23: 4 | BU23: 20-60 | BV23: Peruana | BW23: Pota | BX23: no | BY23: Enero-Diciembre | BZ23: 48 | CA23: 4 viajes/mes | CB23: 3-7 | CC23: NS | CD23: NS | CE23: 1000-2000 | CF23: 4000 | CG23: Acopiador | CH23: 1-13 | CI23: NA | CJ23: NA | CK23: NA | CL23: NA | CM23: NA | CN23: NA | CO23: NA | CP23: NA | CQ23: NA | CR23: NA | CS23: NA | CT23: NA | CU23: NA | CV23: Zona: Bonito (40-50 millas fuera de Pisco); Pota (40-50 millas fuera de Pisco). Comenta molestia en que los pescadores solo conocen el precio del comprador de pota, pero no conocen el precio de la empresa | CW23: 936 219 115
A24: KD-PUCUSANA-023 | B24: Kelly Diaz | C24: 45887 | D24: Luis Benito Castillo Yataco | E24: 07895444 | F24: 51 | G24: 35 | H24: Pucusana | I24: Pucusana | J24: Pucusana, Pisco, Callao, Atico, La Planchada | K24: 18486 | L24: =DATEDIF(K24, DATE(2025,8,29), "Y") -> 75 | M24: M | N24: Casado/Conviviente | O24: Primaria | P24: si | Q24: si | R24: Armador | S24: si | T24: Asociación Gremio de Pescadores de Pucusana | U24: no | V24: NA | W24: NA | X24: NA | Y24: NA | Z24: NA | AA24: NA | AB24: no | AC24: NA | AD24: 1 | AE24: 2 | AF24: si | AG24: Negocio | AH24: no | AI24: NA | AJ24: si | AK24: NA | AL24: si | AM24: NA | AN24: 1 | AO24: si | AP24: KELLY II | AQ24: CO-22405-BM | AR24: no | AS24: no | AT24: si | AU24: 10 | AV24: NA | AW24: NA | AX24: NA | AY24: NA | AZ24: NA | BA24: NA | BB24: 200-300 | BC24: Pinta Potera | BD24: 4 | BE24: 20-30 | BF24: Peruana | BG24: Pota | BH24: no | BI24: Enero-Diciembre | BJ24: 24 | BK24: 2 viajes/mes | BL24: 8-15 | BM24: NS | BN24: NS | BO24: 2000-3000 | BP24: 10000-15000 | BQ24: Acopiador | BR24: 1.5-3 | BS24: NA | BT24: NA | BU24: NA | BV24: NA | BW24: NA | BX24: NA | BY24: NA | BZ24: NA | CA24: NA | CB24: NA | CC24: NA | CD24: NA | CE24: NA | CF24: NA | CG24: NA | CH24: NA | CI24: NA | CJ24: NA | CK24: NA | CL24: NA | CM24: NA | CN24: NA | CO24: NA | CP24: NA | CQ24: NA | CR24: NA | CS24: NA | CT24: NA | CU24: NA | CV24: Zona: Pota (40-80 millas fuera de Pisco e Ilo). Suelen pescar la pota 6 a 8 hr en la noche | CW24: 931 998 662
A25: KD-PUCUSANA-024 | B25: Kelly Diaz | C25: 45887 | D25: Jose Carlos Carrera Astete | E25: 04641260 | F25: 30 | G25: 20 | H25: Pucusana | I25: Pucusana | J25: Pucusana | K25: 25713 | L25: =DATEDIF(K25, DATE(2025,8,29), "Y") -> 55 | M25: M | N25: Casado/Conviviente | O25: Superior Técnico | P25: si | Q25: si | R25: Armador, Patrón | S25: si | T25: Asociación de Pescadores Armaderos de Pucusana | U25: no | V25: NA | W25: NA | X25: NA | Y25: NA | Z25: NA | AA25: NA | AB25: no | AC25: NA | AD25: 1 | AE25: 3 | AF25: si | AG25: Ama de casa | AH25: no | AI25: NA | AJ25: no | AK25: La fuerza fisica natural no es la misma | AL25: no | AM25: tendria dificultad en rendir fisicamente como un hombre | AN25: 1 | AO25: si | AP25: MICHAEL JORDAN 3 | AQ25: MO-57592-BM | AR25: si | AS25: si | AT25: si | AU25: 12 | AV25: NA | AW25: NA | AX25: NA | AY25: NA | AZ25: NA | BA25: NA | BB25: 1200-1500 | BC25: Pinta Potera | BD25: 6 | BE25: 25-40 | BF25: Peruana | BG25: Pota | BH25: no | BI25: Enero-Diciembre | BJ25: 12-48 | BK25: 1-4 viajes/mes | BL25: 4-22 | BM25: NS | BN25: NS | BO25: NS | BP25: 12000-20000 | BQ25: Acopiador | BR25: 2.3 | BS25: Espinel | BT25: 6 | BU25: 25-40 | BV25: Peruana | BW25: Perico | BX25: si | BY25: Octubre-Febrero | BZ25: 5-6 | CA25: Linea madre: 26000 m. #anzuelos:2200. 1 anzuelo/linea. Calibre: 5 | CB25: 20 | CC25: 3-4 | CD25: 15-20 | CE25: 100-1500 | CF25: 8000-1000 | CG25: Acopiador | CH25: 6 | CI25: Espinel | CJ25: Tollo | CK25: si, caballa | CL25: Octubre-Febrero | CM25: 4 | CN25: Linea madre: 26000 m. #anzuelos:2200. 1 anzuelo/linea. Calibre: 5 | CO25: 25-30 | CP25: 10-12 | CQ25: 12-15 | CR25: 80-300 | CS25: 4000-5000 | CT25: Acopiador | CU25: 3.3-3.5 | CV25: Zona: Pota (200 millas fuera de Tumbes a Tacna); Perico (200-250 millas fuera de Ilo a Piura); Tollo (150-200 millas fuera de Ilo a Piura). | CW25: 999 001 359
A26: KD-PUCUSANA-025 | B26: Kelly Diaz | C26: 45888 | D26: Ignacio Luis Alfredo Noa Chambi | E26: 80265947 | F26: 34 | G26: 29 | H26: Mollendo | I26: Pucusana | J26: Pucusana | K26: 28004 | L26: =DATEDIF(K26, DATE(2025,8,29), "Y") -> 48 | M26: M | N26: Soltero | O26: Primaria | P26: si | Q26: No tiene | R26: Patrón | S26: no | T26: NA | U26: si | V26: Cortina costera | W26: pejerrey | X26: NA | Y26: NA | Z26: NA | AA26: NA | AB26: no | AC26: NA | AD26: 3 | AE26: 2 | AF26: no | AG26: NA | AH26: no | AI26: NA | AJ26: no | AK26: La fuerza fisica natural no es la misma; en huevera si es mas posible | AL26: si | AM26: NA | AN26: 1 | AO26: no | AP26: RODRIGO Y ALVARO | AQ26: PS-57411-BM | AR26: no | AS26: no | AT26: si | AU26: 4 | AV26: NA | AW26: NA | AX26: NA | AY26: NA | AZ26: NA | BA26: NA | BB26: 140-200 | BC26: Pinta Potera | BD26: 4 | BE26: 17-55 | BF26: Peruana y Extranjera | BG26: Pota | BH26: no | BI26: Enero-Diciembre | BJ26: 48 | BK26: 4 viajes/mes | BL26: 7 | BM26: NS | BN26: NS | BO26: 500-1000 | BP26: 1000-7000 | BQ26: Acopiador | BR26: 1.5-6 | BS26: NA | BT26: NA | BU26: NA | BV26: NA | BW26: NA | BX26: NA | BY26: NA | BZ26: NA | CA26: NA | CB26: NA | CC26: NA | CD26: NA | CE26: NA | CF26: NA | CG26: NA | CH26: NA | CI26: NA | CJ26: NA | CK26: NA | CL26: NA | CM26: NA | CN26: NA | CO26: NA | CP26: NA | CQ26: NA | CR26: NA | CS26: NA | CT26: NA | CU26: NA | CV26: Zona: Pota (30-200 millas fuera de Pucusana). | CW26: 967 898 473 | CX26: NC
A27: KD-PUCUSANA-026 | B27: Kelly Diaz | C27: 45888 | D27: Wilson Requejo Cueva | E27: 46955312 | F27: 18 | G27: 18 | H27: Pucusana | I27: Pucusana | J27: Pucusana | K27: 33507 | L27: =DATEDIF(K27, DATE(2025,8,29), "Y") -> 33 | M27: M | N27: Soltero | O27: Secundaria | P27: si | Q27: si | R27: Patrón | S27: no | T27: NA | U27: no | V27: NA | W27: NA | X27: NA | Y27: NA | Z27: NA | AA27: NA | AB27: no | AC27: NA | AD27: 3 | AE27: 3 | AF27: no | AG27: NA | AH27: no | AI27: NA | AJ27: si | AK27: NA | AL27: si | AM27: NA | AN27: 0 | AO27: no | AP27: MICHAELL JORDAN 1 | AQ27: MO-60112-BM | AR27: no | AS27: no | AT27: si | AU27: NS | AV27: NA | AW27: NA | AX27: NA | AY27: NA | AZ27: NA | BA27: NA | BB27: 1000 | BC27: Espinel | BD27: 4 | BE27: 22-30 | BF27: Peruana | BG27: Tollo | BH27: si | BI27: Junio-Julio | BJ27: 2-3 | BK27: Linea madre: 29600 metros. #anzuelos: 900. 1 anzuelo/linea. Calibre: 3 | BL27: 18-25 | BM27: 5-6 | BN27: 12-15 | BO27: 600-700 | BP27: 8000-10000 | BQ27: Acopiador | BR27: 6 | BS27: Espinel | BT27: 6 | BU27: 22-30 | BV27: Peruana | BW27: Perico | BX27: si | BY27: Octubre-Marzo | BZ27: 6-7 | CA27: Linea madre: 29600 metros. #anzuelos: 900. 1 anzuelo/linea. Calibre: 5 | CB27: 15-18 | CC27: 1-2 | CD27: 30 | CE27: 600-700 | CF27: 8000-10000 | CG27: Acopiador | CH27: 8-15 | CI27: NA | CJ27: NA | CK27: NA | CL27: NA | CM27: NA | CN27: NA | CO27: NA | CP27: NA | CQ27: NA | CR27: NA | CS27: NA | CT27: NA | CU27: NA | CV27: Zona: Tollo (400 millas fuera de Ilo); Perico (500-600 millas fuera de Pucusana). | CW27: 953 084 203
A28: KD-PUCUSANA-027 | B28: Kelly Diaz | C28: 45888 | D28: Carlos Ancajima Martinez | E28: 80430112 | F28: 35 | G28: 35 | H28: Pucusana | I28: Pucusana | J28: Pucusana | K28: 27646 | L28: =DATEDIF(K28, DATE(2025,8,29), "Y") -> 49 | M28: M | N28: Casado/Conviviente | O28: Secundaria | P28: si | Q28: si | R28: Patrón | S28: si | T28: Asociación Gremio de Pescadores de Pucusana | U28: si | V28: Cortina costera | W28: pejerrey, cachema, lorna | X28: NA | Y28: NA | Z28: NA | AA28: NA | AB28: no | AC28: NA | AD28: 3 | AE28: 2 | AF28: si | AG28: Limpia pejerrey | AH28: no | AI28: NA | AJ28: si | AK28: NA | AL28: si | AM28: NA | AN28: 1 | AO28: no | AP28: RUTH | AQ28: NS | AR28: no | AS28: no | AT28: si | AU28: 8 | AV28: NA | AW28: NA | AX28: NA | AY28: NA | AZ28: NA | BA28: NA | BB28: 350 | BC28: Espinel | BD28: 6 | BE28: 20-50 | BF28: Peruana | BG28: Perico | BH28: si | BI28: Septiembre-Noviembre | BJ28: 5-6 | BK28: Linea madre: 18500 metros. #anzuelos: 2000. 1 anzuelo/linea. Calibre: 5 | BL28: 30 | BM28: 3-4 | BN28: 6 | BO28: 700-1000 | BP28: 4000-5000 | BQ28: Acopiador | BR28: 8-9 | BS28: Trampa Ovas | BT28: 4 | BU28: 20-50 | BV28: Peruana | BW28: Ova | BX28: no | BY28: Octubre-Diciembre | BZ28: 1-2 | CA28: Esteras y manta, con palmeras. Usa 40 trampas, en 4 filas de 10. Dimensiones de trampa 2.5x1.5 metros | CB28: 30 | CC28: 72 | CD28: 10 | CE28: 50-100 | CF28: 800-1000 | CG28: Acopiador | CH28: 40 | CI28: NA | CJ28: NA | CK28: NA | CL28: NA | CM28: NA | CN28: NA | CO28: NA | CP28: NA | CQ28: NA | CR28: NA | CS28: NA | CT28: NA | CU28: NA | CV28: Zona: Perico (250 millas fuera de Huacho y Mataran); Ova (250 millas fuera de Huacho hacia el sur). Tira sus trampas de 10 en 10. Ova con ojo no se vende. | CY28: Ova (250 millas fuera de Huacho hacia el sur)
A29: KD-PUCUSANA-028 | B29: Kelly Diaz | C29: 45888 | D29: Olger Jeefer Panta Silupu | E29: 47808459 | F29: 10 | G29: 10 | H29: Pucusana | I29: Pucusana | J29: Pucusana, Ilo, Callao, Salaverry | K29: 33165 | L29: =DATEDIF(K29, DATE(2025,8,29), "Y") -> 34 | M29: M | N29: Soltero | O29: Secundaria | P29: si | Q29: Privado | R29: Patrón | S29: no | T29: NA | U29: no | V29: NA | W29: NA | X29: NA | Y29: NA | Z29: NA | AA29: NA | AB29: si | AC29: Turismo | AD29: 0 | AE29: 0 | AF29: no | AG29: NA | AH29: no | AI29: NA | AJ29: no | AK29: La fuerza fisica natural no es la misma; la habilidad es la misma | AL29: si | AM29: NA | AN29: 1 | AO29: no | AQ29: IO-29620-BM | AR29: no | AS29: no | AT29: si | AU29: 10 | AV29: NA | AW29: NA | AX29: NA | AY29: NA | AZ29: NA | BA29: NA | BB29: 400-800 | BC29: Espinel | BD29: 5-6 | BE29: 20-50 | BF29: Peruana | BG29: Tollo | BH29: si | BI29: Enero-Diciembre | BJ29: 12-20 | BK29: Linea madre: 13500 metros. #anzuelos: 2000. 1 anzuelo/linea. Calibre: 4 | BL29: 15-30 | BM29: 3-5 | BN29: 20-50 | BO29: 300-4000 | BP29: 5000-12000 | BQ29: Acopiador | BR29: 5 | BS29: Espinel | BT29: 5-6 | BU29: 20-50 | BV29: Peruana | BW29: Perico | BX29: si | BY29: Octubre-Marzo | BZ29: 6-10 | CA29: Linea madre: 22500 metros. #anzuelos: 2500. 1 anzuelo/linea. Calibre: 5 | CB29: 15-20 | CC29: 3-4 | CD29: 40-60 | CE29: 200-1000 | CF29: 5000-14000 | CG29: Acopiador | CH29: 6-20 | CI29: NA | CJ29: NA | CK29: NA | CL29: NA | CM29: NA | CN29: NA | CO29: NA | CP29: NA | CQ29: NA | CR29: NA | CS29: NA | CT29: NA | CU29: NA | CV29: Zona: Perico (90-200 millas fuera de Pucusana hasta Chile); Tollo (500 millas fuera de Pucusana hasta Chile). El espinel del tollo usa un alambre en vez de linea, para sujetar el anzuelo. | CW29: 932 329 924
A30: KD-PUCUSANA-029 | B30: Kelly Diaz | C30: 45888 | D30: Luis Alberto Avila Bravo | E30: 80091938 | F30: 44 | G30: 37 | H30: Pucusana | I30: Pucusana | J30: Pucusana, Marcona, Callao, Ancón | K30: 26752 | L30: =DATEDIF(K30, DATE(2025,8,29), "Y") -> 52 | M30: M | N30: Divorciado | O30: Secundaria | P30: si | Q30: si | R30: Tripulación | S30: si | T30: Asociación Gremio de Pescadores de Pucusana | U30: si | V30: Cortina costera | W30: pejerrey, lorna | X30: NA | Y30: NA | Z30: NA | AA30: NA | AB30: no | AC30: NA | AD30: 0 | AE30: 2 | AF30: no | AG30: NA | AH30: si | AI30: 1 hijo: tripulante | AJ30: si | AK30: NA | AL30: si | AM30: NA | AN30: 0 | AO30: no | AP30: NA | AQ30: NA | AR30: NA | AS30: NA | AT30: NA | AU30: NA | AV30: NA | AW30: NA | AX30: NA | AY30: NA | AZ30: NA | BA30: NA | BB30: 50-100 | BC30: Cortina superficial | BD30: 3 | BE30: 25-55 | BF30: Peruana | BG30: Bonito | BH30: no | BI30: Octubre-Febrero | BJ30: 25-35 | BK30: #paños: 16, cocada: 4 pulgadas, malla 4.5 x 90 m | BL30: 1-7 | BM30: 2-3 | BN30: 2-8 | BO30: 40-500 | BP30: 4000-5000 | BQ30: Acopiador | BR30: 1.2-4 | BS30: Pinta Potera | BT30: 3-4 | BU30: 25-55 | BV30: Peruana | BW30: Pota | BX30: no | BY30: Junio-Agosto | BZ30: 6-12 | CA30: 2-4 viajes/mes | CB30: 4-15 | CC30: NS | CD30: NS | CE30: NS | CF30: 4000-10000 | CG30: Acopiador | CH30: 1-20 | CI30: NA | CJ30: NA | CK30: NA | CL30: NA | CM30: NA | CN30: NA | CO30: NA | CP30: NA | CQ30: NA | CR30: NA | CS30: NA | CT30: NA | CU30: NA | CV30: Zona: Bonito (50-170 millas fuera de Marcona); Pota (50-100 millas fuera de Marcona).
A31: KD-PUCUSANA-030 | B31: Kelly Diaz | C31: 45888 | D31: Oswer Ivan Dominguez Rondoy | E31: 46376229 | F31: 10 | G31: 4 | H31: Pucusana | I31: Pucusana | J31: Pucusana, Callao | K31: 32957 | L31: =DATEDIF(K31, DATE(2025,8,29), "Y") -> 35 | M31: M | N31: Casado/Conviviente | O31: Secundaria | P31: si | Q31: si | R31: Patrón | S31: no | T31: NA | U31: no | V31: NA | W31: NA | X31: NA | Y31: NA | Z31: NA | AA31: NA | AB31: si | AC31: Negocio | AD31: 4 | AE31: 1 | AF31: si | AG31: Profesional Independiente | AH31: no | AI31: NA | AJ31: no | AK31: La fuerza fisica natural no es la misma | AL31: si | AM31: NA | AN31: 0 | AO31: no | AQ31: CO-45544-CM | AR31: si | AS31: no | AT31: si | AU31: 10 | AV31: NA | AW31: NA | AX31: NA | AY31: NA | AZ31: NA | BA31: NA | BB31: 1200-1400 | BC31: Espinel | BD31: 8 | BE31: 20-55 | BF31: Peruana | BG31: Perico | BH31: si | BI31: Noviembre-Abril | BJ31: 6 | BK31: Linea madre: 15000 metros. #anzuelos: 2500. 1 anzuelo/linea. Calibre: 5 | BL31: 20-30 | BM31: 2-3 | BN31: 9-15 | BO31: 500-2000 | BP31: 4000-20000 | BQ31: Acopiador | BR31: 6-12 | BS31: Pinta Potera | BT31: 5-6 | BU31: 20-55 | BV31: Peruana | BW31: Pota | BX31: no | BY31: Enero-Diciembre | BZ31: 24-48 | CA31: 2-4 viajes/mes | CB31: 8-15 | CC31: NS | CD31: NS | CE31: 500-1500 | CF31: 10000-25000 | CG31: Acopiador | CH31: 1.2-3 | CI31: NA | CJ31: NA | CK31: NA | CL31: NA | CM31: NA | CN31: NA | CO31: NA | CP31: NA | CQ31: NA | CR31: NA | CS31: NA | CT31: NA | CU31: NA | CV31: Zona: Perico (700-200 millas fuera de Paita a Ilo); Pota (80-250 millas fuera de Pucusana a Ilo). | CW31: 954 191 597
A32: KD-PUCUSANA-031 | B32: Kelly Diaz | C32: 45888 | D32: Augusto Rodolfo Llanos Luyo | E32: 09526224 | F32: 36 | G32: 31 | H32: Pucusana | I32: Pucusana | J32: Pucusana, Marcona, Callao, Atico, Salaverry | K32: 25527 | L32: =DATEDIF(K32, DATE(2025,8,29), "Y") -> 55 | M32: M | N32: Soltero | O32: Secundaria | P32: si | Q32: No tiene | R32: Patrón | S32: no | T32: NA | U32: no | V32: NA | W32: NA | X32: NA | Y32: NA | Z32: NA | AA32: NA | AB32: no | AC32: NA | AD32: 4 | AE32: 4 | AF32: no | AG32: NA | AH32: no | AI32: NA | AJ32: no | AK32: La fuerza fisica natural no es la misma | AL32: no | AM32: tendria dificultad en rendir fisicamente como un hombre | AN32: 0 | AO32: no | AP32: CARLOS JOEL | AQ32: NS | AR32: no | AS32: no | AT32: si | AU32: 7 | AV32: NA | AW32: NA | AX32: NA | AY32: NA | AZ32: NA | BA32: NA | BB32: 80 | BC32: Cortina superficial | BD32: 4 | BE32: 30-50 | BF32: Peruana y Extranjera | BG32: Perico | BH32: no | BI32: Noviembre-Diciembre | BJ32: 4-5 | BK32: #paños: 10, cocada: 4 pulgadas, malla 6.75 x 4.5 m | BL32: 8-10 | BM32: 2-3 | BN32: 3-4 | BO32: 500-700 | BP32: 2000-5000 | BQ32: Acopiador | BR32: 4-5 | BS32: Espinel | BT32: 4 | BU32: 30-50 | BV32: Peruana y Extranjera | BW32: Perico | BX32: si, volador | BY32: Noviembre-Diciembre | BZ32: 4-5 | CA32: Linea madre: 13500 metros. #anzuelos: 1500. 1 anzuelo/linea. Calibre: 2 | CB32: 8-10 | CC32: 2-3 | CD32: 3-4 | CE32: 500-700 | CF32: 2000-5000 | CG32: Acopiador | CH32: 10-11 | CI32: Cortina Superficial | CJ32: Bonito | CK32: no | CL32: Septiembre-Abril | CM32: 35-40 | CN32: #paños: 10, cocada: 4 pulgadas, malla 6.75 x 4.5 m | CO32: 4 | CP32: 2 | CQ32: 3-4 | CR32: 200-400 | CS32: 4000-5000 | CT32: Acopiador | CU32: 1.5-4 | CV32: Zona: Perico (80-100 millas fuera de Callao y Marcona); Bonito (40-50 millas fuera de Pucusana). | CW32: 917 809 029
A33: KD-PUCUSANA-032 | B33: Kelly Diaz | C33: 45888 | D33: Yossimar Gonzales Peña | E33: 47606441 | F33: 21 | G33: 18 | H33: Pucusana | I33: Pucusana | J33: Pucusana, Callao | K33: 33109 | L33: =DATEDIF(K33, DATE(2025,8,29), "Y") -> 35 | M33: M | N33: Casado/Conviviente | O33: Secundaria | P33: si | Q33: si | R33: Armador | S33: no | T33: NA | U33: si | V33: Cortina costera | W33: pejerrey, jurel, caballa | X33: NA | Y33: NA | Z33: NA | AA33: NA | AB33: no | AC33: NA | AD33: 3 | AE33: 2 | AF33: si | AG33: Ama de casa | AH33: no | AI33: NA | AJ33: si | AK33: NA | AL33: si | AM33: NA | AN33: 1 | AO33: si | AP33: RIHANNA AILANI | AQ33: PS-18637-BM | AR33: no | AS33: no | AT33: si | AU33: 6 | AV33: NA | AW33: NA | AX33: NA | AY33: NA | AZ33: NA | BA33: NA | BB33: 8-24 | BC33: Cortina superficial | BD33: 4 | BE33: 30-40 | BF33: Peruana | BG33: Bonito | BH33: no | BI33: Septiembre-Abril | BJ33: 25-30 | BK33: #paños: 8-9, cocada: 4-4.5 pulgadas, malla 5 x 150 m | BL33: 7 | BM33: 2 | BN33: 3 | BO33: 200-1000 | BP33: 1000-2000 | BQ33: Acopiador | BR33: 1.5-2.1 | BS33: Trampa Ovas | BT33: 3 | BU33: 30-40 | BV33: Peruana | BW33: Ova | BX33: no | BY33: Septiembre-Diciembre | BZ33: 3 | CA33: Esteras y manta, con palmeras. Usa 12 trampas. Dimensiones de trampa 2x3 metros | CB33: 30-40 | CC33: 72 | CD33: 10-12 | CE33: 20-150 | CF33: 1000 | CG33: Acopiador | CH33: 30-40 | CI33: NA | CJ33: NA | CK33: NA | CL33: NA | CM33: NA | CN33: NA | CO33: NA | CP33: NA | CQ33: NA | CR33: NA | CS33: NA | CT33: NA | CU33: NA | CV33: Zona: Bonito (20-60 millas fuera de Pucusana); Ova (100 millas fuera de Marcona). Precio (kg) de ova con ojo: 5-10 soles. Por dia, botan al agua 3 trampas. La palmera dura 1 mes, la manguera dura 1 año; el zargazo dura 3 usos. Recientemente estan usando la maya anaranjada (que se usa en pistas), dura 1 solo uso. | CW33: 932 015 678 | CX33: apagado | CY33: Ova (100 millas fuera de Marcona)
A34: KD-PUCUSANA-033 | B34: Kelly Diaz | C34: 45888 | D34: Nestor Tanta Valdez | E34: 40790670 | F34: 28 | G34: 23 | H34: Paita | I34: Chimbote, Paita, Pucusana | J34: Pucusana | K34: 28291 | L34: =DATEDIF(K34, DATE(2025,8,29), "Y") -> 48 | M34: M | N34: Casado/Conviviente | O34: Secundaria | P34: si | Q34: si | R34: Armador, Patrón | S34: si | T34: Asociación Gremio de Pescadores de Paita | U34: no | V34: NA | W34: NA | X34: NA | Y34: NA | Z34: NA | AA34: NA | AB34: no | AC34: NA | AD34: 5 | AE34: 4 | AF34: si | AG34: Ama de casa | AH34: no | AI34: NA | AJ34: si | AK34: Pero capitania no les permite | AL34: si | AM34: NA | AN34: 2 | AO34: si | AP34: BROTHER | AQ34: PT-66150-CM | AR34: no | AS34: no | AT34: si | AU34: 32 | AV34: CORAZÓN DE JESÚS | AW34: PT-64567-CM | AX34: no | AY34: no | AZ34: si | BA34: 32 | BB34: 500 | BC34: Pinta Potera | BD34: 5-8 | BE34: 20-50 | BF34: Peruana | BG34: Pota | BH34: no | BI34: Enero-Diciembre | BJ34: 24-48 | BK34: 2-4 viajes/mes | BL34: 3-20 | BM34: NS | BN34: NS | BO34: 200-10000 | BP34: 12000 | BQ34: Acopiador (en el sur) y Directo a empresa (en el norte) | BR34: 1.2-1.3 | BS34: NA | BT34: NA | BU34: NA | BV34: NA | BW34: NA | BX34: NA | BY34: NA | BZ34: NA | CA34: NA | CB34: NA | CC34: NA | CD34: NA | CE34: NA | CF34: NA | CG34: NA | CH34: NA | CI34: NA | CJ34: NA | CK34: NA | CL34: NA | CM34: NA | CN34: NA | CO34: NA | CP34: NA | CQ34: NA | CR34: NA | CS34: NA | CT34: NA | CU34: NA | CV34: Zona: Pota (60-200 millas fuera de Pisco, Pucusana y Paita). Comenta incomodidad porque los pescadores artesanales no tienen la posibilidad de negociar el precio de la pota con las empresas | CW34: 944 448 148 | CX34: apagado
A35: KD-PUCUSANA-034 | B35: Kelly Diaz | C35: 45889 | D35: Percy Omar Rumiche Morales | E35: 44950588 | F35: 20 | G35: 15 | H35: Talara | I35: Pucusana | J35: Pucusana | K35: 32159 | L35: =DATEDIF(K35, DATE(2025,8,29), "Y") -> 37 | M35: M | N35: Casado/Conviviente | O35: Primaria | P35: si | Q35: si | R35: Patrón | S35: no | T35: NA | U35: si | V35: Cortina costera | W35: cabrilla, bonito | X35: Pinta | Y35: cabrilla, bonito | Z35: NA | AA35: NA | AB35: no | AC35: NA | AD35: 8 | AE35: 3 | AF35: si | AG35: Ama de casa | AH35: no | AI35: NA | AJ35: si | AK35: NA | AL35: si | AM35: NA | AN35: 0 | AO35: no | AP35: LUIS FERNANDO | AQ35: NS | AR35: no | AS35: no | AT35: si | AU35: 9 | AV35: NA | AW35: NA | AX35: NA | AY35: NA | AZ35: NA | BA35: NA | BB35: 80-140 | BC35: Pinta Potera | BD35: 4 | BE35: 30-40 | BF35: Peruana | BG35: Pota | BH35: no | BI35: Enero-Diciembre | BJ35: 36-48 | BK35: 3-4 viajes/mes | BL35: 3-7 | BM35: NS | BN35: NS | BO35: 100-1000 | BP35: 1000-3000 | BQ35: Acopiador | BR35: 1-3 | BS35: NA | BT35: NA | BU35: NA | BV35: NA | BW35: NA | BX35: NA | BY35: NA | BZ35: NA | CA35: NA | CB35: NA | CC35: NA | CD35: NA | CE35: NA | CF35: NA | CG35: NA | CH35: NA | CI35: NA | CJ35: NA | CK35: NA | CL35: NA | CM35: NA | CN35: NA | CO35: NA | CP35: NA | CQ35: NA | CR35: NA | CS35: NA | CT35: NA | CU35: NA | CV35: Zona: Pota (30-80 millas fuera de Ilo). | CW35: 981 248 489 | CX35: apagado
A36: KD-PUCUSANA-035 | B36: Kelly Diaz | C36: 45889 | D36: Miguel Angel Caceres Vargas | E36: 48436622 | F36: 21 | G36: 21 | H36: Pucusana | I36: Pucusana | J36: Pucusana, Marcona, Pisco, Callao, Cerro Azul | K36: 32530 | L36: =DATEDIF(K36, DATE(2025,8,29), "Y") -> 36 | M36: M | N36: Casado/Conviviente | O36: Primaria | P36: si | Q36: si | R36: Patrón | S36: si | T36: Asociación Gremio de Pescadores de Pucusana | U36: si | V36: Cortina costera | W36: pejerrey, caballa | X36: NA | Y36: NA | Z36: NA | AA36: NA | AB36: no | AC36: NA | AD36: 6 | AE36: 5 | AF36: si | AG36: Ama de casa | AH36: no | AI36: NA | AJ36: no | AK36: La fuerza fisica natural no es la misma (talvez en el bonito si puedan participar) | AL36: si | AM36: NA | AN36: 0 | AO36: no | AP36: ALISON Y THAIS | AQ36: TA-61458-BM | AR36: no | AS36: no | AT36: si | AU36: 8 | AV36: NA | AW36: NA | AX36: NA | AY36: NA | AZ36: NA | BA36: NA | BB36: 100 | BC36: Cortina superficial | BD36: 3 | BE36: 25-50 | BF36: Peruana y Extranjera | BG36: Bonito | BH36: no | BI36: Noviembre-Marzo | BJ36: 30-40 | BK36: #paños: 8, cocada: 3.25 y 4 pulgadas, malla 12 x 60 m | BL36: 2-6 | BM36: 1-2.5 | BN36: 8-20 | BO36: 100-3000 | BP36: 1500-5000 | BQ36: Acopiador | BR36: 3 | BS36: Pinta Potera | BT36: 3 | BU36: 25-50 | BV36: Peruana y Extranjera | BW36: Pota | BX36: no | BY36: Enero-Diciembre | BZ36: 36 | CA36: 3 viajes/mes | CB36: 7 | CC36: NS | CD36: NS | CE36: 500-1000 | CF36: 2000-6000 | CG36: Acopiador | CH36: 1.5-9 | CI36: NA | CJ36: NA | CK36: NA | CL36: NA | CM36: NA | CN36: NA | CO36: NA | CP36: NA | CQ36: NA | CR36: NA | CS36: NA | CT36: NA | CU36: NA | CV36: Zona: Bonito (5-100 millas fuera de Chancay y Marcona); Pota (5-100 millas fuera de Chancay y Marcona). | CW36: 972 258 161 | CX36: apagado
A37: KD-PUCUSANA-036 | B37: Kelly Diaz | C37: 45889 | D37: Dionisio Americo Aguayo Huayhua | E37: 09526945 | F37: 25 | G37: 20 | H37: Pucusana | I37: Pucusana | J37: Pucusana | K37: 22992 | L37: =DATEDIF(K37, DATE(2025,8,29), "Y") -> 62 | M37: M | N37: Casado/Conviviente | O37: Primaria | P37: si | Q37: No tiene | R37: Armador, Patrón | S37: si | T37: Asociación Gremio de Pescadores de Pucusana | U37: si | V37: Cortina costera | W37: pejerrey, jurel, bonito | X37: NA | Y37: NA | Z37: NA | AA37: NA | AB37: no | AC37: NA | AD37: 6 | AE37: 5 | AF37: si | AG37: Ama de casa | AH37: si | AI37: 1 hijo: tripulante; 1 hijo: patrón | AJ37: no | AK37: Pesca de altura es peligrosa | AL37: si | AM37: NA | AN37: 2 | AO37: si | AP37: BRIGITH II | AQ37: CO-37597-BM | AR37: no | AS37: no | AT37: si | AU37: 6 | AV37: BRIGITH III | AW37: CO-32594-BM | AX37: no | AY37: no | AZ37: si | BA37: 6 | BB37: 100-120 | BC37: Cortina superficial | BD37: 4 | BE37: 20-40 | BF37: Peruana | BG37: Bonito | BH37: no | BI37: Enero-Diciembre | BJ37: 36 | BK37: #paños: 7, cocada: 4 pulgadas, malla 7.5 x 180 m | BL37: 7 | BM37: 2-3 | BN37: 20-25 | BO37: 300-1000 | BP37: 2000-5000 | BQ37: Acopiador | BR37: 3-4 | BS37: NA | BT37: NA | BU37: NA | BV37: NA | BW37: NA | BX37: NA | BY37: NA | BZ37: NA | CA37: NA | CB37: NA | CC37: NA | CD37: NA | CE37: NA | CF37: NA | CG37: NA | CH37: NA | CI37: NA | CJ37: NA | CK37: NA | CL37: NA | CM37: NA | CN37: NA | CO37: NA | CP37: NA | CQ37: NA | CR37: NA | CS37: NA | CT37: NA | CU37: NA | CV37: Zona: Bonito (15-80 millas fuera de Pucusana).
A38: KD-PUCUSANA-037 | B38: Kelly Diaz | C38: 45889 | D38: Alexander Javier Moreno Villalta | E38: 47533671 | F38: 18 | G38: 18 | H38: Talara | I38: Pucusana | J38: Pucusana | K38: 33938 | L38: =DATEDIF(K38, DATE(2025,8,29), "Y") -> 32 | M38: M | N38: Casado/Conviviente | O38: Primaria | P38: si | Q38: si | R38: Patrón | S38: no | T38: NA | U38: si | V38: Cortina costera | W38: pejerrey | X38: Pinta | Y38: bonito | Z38: NA | AA38: NA | AB38: si | AC38: Mototaxi | AD38: 6 | AE38: 3 | AF38: si | AG38: Ama de casa | AH38: no | AI38: NA | AJ38: si | AK38: NA | AL38: si | AM38: NA | AN38: 0 | AO38: no | AP38: ABIGAIL BRIGIT | AQ38: MO-40881-BM | AR38: no | AS38: no | AT38: si | AU38: 10 | AV38: NA | AW38: NA | AX38: NA | AY38: NA | AZ38: NA | BA38: NA | BB38: 70-80 | BC38: Pinta Potera | BD38: 4 | BE38: 30-35 | BF38: Peruana y Extranjera | BG38: Pota | BH38: no | BI38: Enero-Diciembre | BJ38: 24-36 | BK38: 2-3 viajes/mes | BL38: 2-15 | BM38: NS | BN38: NS | BO38: 50-500 | BP38: 4000 | BQ38: Acopiador | BR38: 1.5-10 | BS38: NA | BT38: NA | BU38: NA | BV38: NA | BW38: NA | BX38: NA | BY38: NA | BZ38: NA | CA38: NA | CB38: NA | CC38: NA | CD38: NA | CE38: NA | CF38: NA | CG38: NA | CH38: NA | CI38: NA | CJ38: NA | CK38: NA | CL38: NA | CM38: NA | CN38: NA | CO38: NA | CP38: NA | CQ38: NA | CR38: NA | CS38: NA | CT38: NA | CU38: NA | CV38: Zona: Pota (30-100 millas fuera de Pucusana). | CW38: 932 681 144
A39: KD-PUCUSANA-038 | B39: Kelly Diaz | C39: 45890 | D39: Kevin Alfredo Colmenares Marrero | E39: 008852165 | F39: 5 | G39: 5 | H39: Pucusana | I39: Pucusana | J39: Pucusana | K39: 34822 | L39: =DATEDIF(K39, DATE(2025,8,29), "Y") -> 30 | M39: M | N39: Soltero | O39: Superior Universitario | P39: si | Q39: No tiene | R39: Tripulación | S39: no | T39: NA | U39: no | V39: NA | W39: NA | X39: NA | Y39: NA | Z39: NA | AA39: NA | AB39: si | AC39: Mototaxi | AD39: 2 | AE39: 2 | AF39: no | AG39: NA | AH39: no | AI39: NA | AJ39: no | AK39: La fuerza fisica natural no es la misma | AL39: si | AM39: NA | AN39: 0 | AO39: no | AP39: ANDREA | AQ39: CO-57959-BM | AR39: NS | AS39: NS | AT39: si | AU39: 10 | AV39: NA | AW39: NA | AX39: NA | AY39: NA | AZ39: NA | BA39: NA | BB39: 100-240 | BC39: Cortina superficial | BD39: 5 | BE39: 23-30 | BF39: Peruana y Extranjera | BG39: Bonito | BH39: no | BI39: Septiembre-Febrero | BJ39: 18-20 | BK39: #paños: 6-8, cocada: 3 pulgadas, malla 180 x 90-120 m | BL39: 4-7 | BM39: 1-3 | BN39: 12-20 | BO39: 200-2000 | BP39: 4000-5000 | BQ39: Acopiador | BR39: 1.4 | BS39: Pinta Potera | BT39: 5 | BU39: 23-30 | BV39: Peruana y Extranjera | BW39: Pota | BX39: no | BY39: Enero-Diciembre | BZ39: 12-24 | CA39: 1-2 viajes/mes | CB39: 10-20 | CC39: NS | CD39: NS | CE39: 200-2000 | CF39: 5000-10000 | CG39: Acopiador | CH39: 0.50-12 | CI39: NA | CJ39: NA | CK39: NA | CL39: NA | CM39: NA | CN39: NA | CO39: NA | CP39: NA | CQ39: NA | CR39: NA | CS39: NA | CT39: NA | CU39: NA | CV39: Zona: Pota (30-100 millas fuera de Pisco y Ancon); Bonito (40-50 millas fuera de Pisco y Pucusana). Solo les esta permitido ingresar 5 toneladas de pota por viaje. Pescador era Venezolano, el numero de DNI es el carnet de identidad. | CW39: 972 708 709
A40: KD-PUCUSANA-039 | B40: Kelly Diaz | C40: 45890 | D40: Jose Jacinto Sosa Chunga | E40: 42429929 | F40: 20 | G40: 20 | H40: Piura | I40: Pucusana | J40: Pucusana | K40: 30856 | L40: =DATEDIF(K40, DATE(2025,8,29), "Y") -> 41 | M40: M | N40: Casado/Conviviente | O40: Secundaria | P40: si | Q40: si | R40: Patrón | S40: si | T40: Sindicato de Pesca de Calamar Gigante y Pesca de Altura del puerto de Paita | U40: si | V40: Cortina costera | W40: bonito | X40: NA | Y40: NA | Z40: NA | AA40: NA | AB40: no | AC40: NA | AD40: 5 | AE40: 4 | AF40: si | AG40: Negocio | AH40: no | AI40: NA | AJ40: si | AK40: NA | AL40: si | AM40: NA | AN40: 0 | AO40: no | AP40: SIEMPRE VIRGINIA | AQ40: TA-57554-BM | AR40: no | AS40: no | AT40: si | AU40: 15 | AV40: NA | AW40: NA | AX40: NA | AY40: NA | AZ40: NA | BA40: NA | BB40: 800-1000 | BC40: Pinta Potera | BD40: 7 | BE40: 25-40 | BF40: Peruana | BG40: Pota | BH40: no | BI40: Enero-Diciembre | BJ40: 24 | BK40: 2 viajes/mes | BL40: 10 | BM40: NS | BN40: NS | BO40: 500-1500 | BP40: 5000-10000 | BQ40: Acopiador | BR40: 2-7 | BS40: Espinel | BT40: 7 | BU40: 25-40 | BV40: Peruana | BW40: Perico | BX40: si, pota | BY40: Octubre-Marzo | BZ40: 6 | CA40: Linea madre: 18000 metros. #anzuelos: 2000. 1 anzuelo/linea. Calibre: 5 | CB40: 15-20 | CC40: 3-4 | CD40: 12-18 | CE40: 800-1000 | CF40: 2000-15000 | CG40: Acopiador | CH40: 7-14 | CI40: NA | CJ40: NA | CK40: NA | CL40: NA | CM40: NA | CN40: NA | CO40: NA | CP40: NA | CQ40: NA | CR40: NA | CS40: NA | CT40: NA | CU40: NA | CV40: Zona: Pota (200-300 millas fuera de Pisco y Callao); Perico (200-300 millas fuera de Pisco y Callao). | CW40: 950 958 792
A41: KD-PUCUSANA-040 | B41: Kelly Diaz | C41: 45890 | D41: Olber Marcial Chanchari Manihuari | E41: 77416358 | F41: 4 | G41: 4 | H41: Pucusana | I41: Pucusana | J41: Pucusana, Ilo, etc | K41: 35109 | L41: =DATEDIF(K41, DATE(2025,8,29), "Y") -> 29 | M41: M | N41: Soltero | O41: Secundaria | P41: si | Q41: si | R41: Tripulación | S41: no | T41: NA | U41: no | V41: NA | W41: NA | X41: NA | Y41: NA | Z41: NA | AA41: NA | AB41: no | AC41: NA | AD41: 2 | AE41: 0 | AF41: no | AG41: NA | AH41: no | AI41: NA | AJ41: no | AK41: La fuerza fisica natural no es la misma; es peligroso | AL41: no | AM41: tendria dificultad en rendir fisicamente como un hombre | AN41: 0 | AO41: no | AP41: MARIJUAN | AQ41: IO-23102-BM | AR41: si | AS41: no | AT41: si | AU41: 12 | AV41: NA | AW41: NA | AX41: NA | AY41: NA | AZ41: NA | BA41: NA | BB41: 700 | BC41: Espinel | BD41: 4-5 | BE41: 25-30 | BF41: Peruana | BG41: Tollo | BH41: si, caballa | BI41: Enero-Diciembre | BJ41: 12 | BK41: Linea madre: 12000-14000 metros. #anzuelos: 1000-1200. 1 anzuelo/linea. Calibre: 3 | BL41: 25-28 | BM41: 3 | BN41: 20-25 | BO41: 150-3000 | BP41: 5000-12000 | BQ41: Acopiador | BR41: 2-6 | BS41: NA | BT41: NA | BU41: NA | BV41: NA | BW41: NA | BX41: NA | BY41: NA | BZ41: NA | CA41: NA | CB41: NA | CC41: NA | CD41: NA | CE41: NA | CF41: NA | CG41: NA | CH41: NA | CI41: NA | CJ41: NA | CK41: NA | CL41: NA | CM41: NA | CN41: NA | CO41: NA | CP41: NA | CQ41: NA | CR41: NA | CS41: NA | CT41: NA | CU41: NA | CV41: Zona: Tollo (300-400 millas fuera de Ilo y mas al sur). | CW41: 986 365 269
A42: KD-PUCUSANA-041 | B42: Kelly Diaz | C42: 45891 | D42: Marlo Juniors Chiquin Ramos | E42: 48022147 | F42: 18 | G42: 16 | H42: Pucusana | I42: Pucusana | J42: Pucusana | K42: 33898 | L42: =DATEDIF(K42, DATE(2025,8,29), "Y") -> 32 | M42: M | N42: Soltero | O42: Secundaria | P42: si | Q42: si | R42: Patrón | S42: si | T42: Asociación Gremio de Pescadores de Pucusana | U42: si | V42: Cortina costera | W42: pejerrey, chauchilla | X42: NA | Y42: NA | Z42: NA | AA42: NA | AB42: no | AC42: NA | AD42: 2 | AE42: 2 | AF42: no | AG42: NA | AH42: no | AI42: NA | AJ42: no | AK42: La fuerza fisica natural no es la misma; es peligroso | AL42: no | AM42: es mejor para la mujer trabajar en tierra | AN42: 0 | AO42: no | AP42: SIGLO XX | AQ42: PS-33223-BM | AR42: no | AS42: no | AT42: si | AU42: 6 | AV42: NA | AW42: NA | AX42: NA | AY42: NA | AZ42: NA | BA42: NA | BB42: 170-200 | BC42: Espinel | BD42: 5 | BE42: 29-50 | BF42: Peruana | BG42: Perico | BH42: si | BI42: Diciembre-Febrero | BJ42: 6-9 | BK42: Linea madre: 1200 metros. #anzuelos: 500-700. 3 anzuelo/linea. Calibre: 5 | BL42: 8-12 | BM42: 2-3 | BN42: 8-20 | BO42: 600-1000 | BP42: 3000-8000 | BQ42: Acopiador | BR42: 10 (espinel), 8 (red) | BS42: Cortina superficial | BT42: 5 | BU42: 29-50 | BV42: Peruana | BW42: Bonito | BX42: no | BY42: Diciembre-Febrero | BZ42: 9-12 | CA42: #paños: 10-12, cocada: 4 pulgadas, malla 10.5 x 180 m | CB42: 6-7 | CC42: 1-3 | CD42: 10-12 | CE42: 1000-5000 | CF42: 5000-8000 | CG42: Acopiador | CH42: 5 | CI42: Pinta Potera | CJ42: Pota | CK42: no | CL42: Enero-Diciembre | CM42: 36 | CN42: 3 viajes/mes | CO42: 7-8 | CP42: NS | CQ42: NS | CR42: 200-1500 | CS42: 6000-8000 | CT42: Acopiador | CU42: 1.5-3 | CV42: Zona: Bonito (20-50 millas fuera de Pucusana, Ancon y Pisco); Pota (50-100 millas fuera de Pucusana); Perico (100-150 millas fuera de Marcona). El palangre tiene 3 anzuelos cada 7-8 brazadas (10.5-12 m), cada 24 brazadas (36 m) hay una boya | CW42: 992 479 370
A43: CC-PUCUSANA-001 | B43: Cristel Cordero | C43: 45884 | D43: Jose Manuel Estrada | E43: 07897604 | F43: 62 | G43: 40 | H43: Pucusana | I43: Pucusana | J43: Pucusana | K43: 18946 | L43: =DATEDIF(K43, DATE(2025,8,29), "Y") -> 73 | M43: M | N43: Casado/Conviviente | O43: Primaria | P43: si | Q43: Privado | R43: Patrón | S43: si | T43: Asociación Gremio de Pescadores de Pucusana | U43: si | V43: Cortina costera | W43: pejerrey | X43: NA | Y43: NA | Z43: NA | AA43: NA | AB43: no | AC43: NA | AD43: 0 | AE43: 6 | AF43: si | AG43: Limpieza | AH43: no | AI43: NA | AJ43: si | AK43: NA | AL43: si | AM43: NA | AN43: 0 | AO43: no | AP43: LUIS MANUEL | AQ43: NS | AR43: si | AS43: si | AT43: si | AU43: 8 | AV43: NA | AW43: NA | AX43: NA | AY43: NA | AZ43: NA | BA43: NA | BB43: 600-700 | BC43: Espinel | BD43: 7 | BE43: 18-68 | BF43: Peruana | BG43: Perico | BH43: si, caballa, barrilete, pota | BI43: Septiembre-Febrero | BJ43: 1-2 | BK43: Linea madre: 240 metros. #anzuelos: 2000-2500. 1 anzuelo/linea. Calibre: 6 | BL43: 15-30 | BM43: 4 | BN43: 20-30 | BO43: 1000 | BP43: 5000-8000 | BQ43: Otro (dueño: mayorista y armador) | BR43: 8-11 | BS43: Cortina superficial | BT43: 7 | BU43: 18-68 | BV43: Peruana | BW43: Espada | BX43: no | BY43: Septiembre-Febrero | BZ43: 1-2 | CA43: #paños: 30, cocada: 18 pulgadas, malla 45 x 450 m | CB43: 20-25 | CC43: 10-12 | CD43: 20-25 | CE43: 500-1000 | CF43: 5000-8000 | CG43: Otro (dueño: mayorista y armador) | CH43: 8-11 | CI43: NA | CJ43: NA | CK43: NA | CL43: NA | CM43: NA | CN43: NA | CO43: NA | CP43: NA | CQ43: NA | CR43: NA | CS43: NA | CT43: NA | CU43: NA | CV43: En red de fondo puede caer tiburon azul, diamante, pez vela y lobos marinos. No sale a la huevera porque le aburre

Sheet Marcona
A1: Encuesta | B1: Nombre_Encuestador | C1: Fecha_Encuesta | D1: Nombre_Pescador | E1: DNI | F1: Años_Pesca | G1: Años_Altura | H1: Distrito_Vivienda | I1: Puerto_Zarpe | J1: Puerto_Arribo | K1: Fecha_Nacimiento | L1: Edad | M1: Sexo | N1: Estado_Civil | O1: Grado_Instruccion | P1: Alfabeto | Q1: Seguro_Salud | R1: Rol_Pescador | S1: OSPA | T1: Nombre_OSPA | U1: Otra_Pesca | V1: Arte_Costera1 | W1: Rec_Costero1 | X1: Arte_Costera2 | Y1: Rec_Costero2 | Z1: Arte_Costera3 | AA1: Rec_Costero3 | AB1: Alterna_Pesca | AC1: Actividad_Alterna | AD1: Personas_Dependientes | AE1: Numero_hijos | AF1: Pareja | AG1: Actividades_Pareja | AH1: FamiliaDirecta_Pesca | AI1: Rol_Familiares | AJ1: Genero_Opotunidades | AK1: GenOpor_No | AL1: Genero_Pago | AM1: GenPago_No | AN1: Num_Embarcaciones | AO1: Embarcacion_Propia | AP1: Nombre1_EmbarcacionAltura | AQ1: Matricula_1 | AR1: SISESAT_1 | AS1: Radiobaliza_1 | AT1: PTH_1 | AU1: TN_Bodega_1 | AV1: Nombre2_EmbarcacionAltura | AW1: Matricula_2 | AX1: SISESAT_2 | AY1: Radiobaliza_2 | AZ1: PTH_2 | BA1: TN_Bodega_2 | BB1: Galones_Combustible | BC1: Arte_1 | BD1: Num_Tripulantes1 | BE1: Edades_Tripulantes1 | BF1: Nacionalidad_Trip1 | BG1: Recurso_1 | BH1: Carnada1 | BI1: Temporada1 | BJ1: Viajes_Temporada1 | BK1: Detalles_Arte1 | BL1: Dias_Faena1 | BM1: Horas_Efectivas1 | BN1: Lances_Faena1 | BO1: Kg_Lance1 | BP1: Kg_Faena1 | BQ1: Venta_Recurso1 | BR1: Precio_Kg1 | BS1: Arte_2 | BT1: Num_Tripulantes2 | BU1: Edades_Tripulantes2 | BV1: Nacionalidad_Trip2 | BW1: Recurso_2 | BX1: Carnada2 | BY1: Temporada2 | BZ1: Viajes_Temporada2 | CA1: Detalles_Arte2 | CB1: Dias_Faena2 | CC1: Horas_Efectivas2 | CD1: Lances_Faena2 | CE1: Kg_Lance2 | CF1: Kg_Faena2 | CG1: Venta_Recurso2 | CH1: Precio_Kg2 | CI1: Arte_3 | CJ1: Recurso_3 | CK1: Carnada3 | CL1: Temporada3 | CM1: Viajes_Temporada3 | CN1: Detalles_Arte3 | CO1: Dias_Faena3 | CP1: Horas_Efectivas3 | CQ1: Lances_Faena3 | CR1: Captura_Lance3 | CS1: Captura_Faena3 | CT1: Venta_Recurso3 | CU1: Precio_Kg3 | CV1: Observaciones
A2: CC-MARCONA-001 | B2: Cristel Cordero | C2: 45775 | D2: Teodolfo Flores Rivero | E2: 22092289 | F2: 35 | G2: 30 | H2: Marcona | I2: Marcona | J2: Marcona | K2: 26839 | L2: =DATEDIF(K2, DATE(2025,8,29), "Y") -> 52 | M2: M | N2: Casado/Conviviente | O2: Primaria | P2: si | Q2: no | R2: Armador, Patrón | S2: si | T2: APROMAR | U2: si | V2: Buceo compresora | W2: mariscos | X2: Colecta de algas | Y2: algas | Z2: NA | AA2: NA | AB2: si | AC2: Albañil | AD2: 3 | AE2: 4 | AF2: si | AG2: Ama de casa | AH2: no | AI2: NA | AJ2: si | AK2: NA | AL2: si | AM2: NA | AN2: 1 | AO2: si | AP2: APURIMEÑO | AQ2: SN-29452-BM | AR2: si | AS2: si | AT2: si | AU2: 4 | AV2: NA | AW2: NA | AX2: NA | AY2: NA | AZ2: NA | BA2: NA | BB2: 120-130 | BC2: Trampa Ovas | BD2: 3 | BE2: 28-51 | BF2: Peruana | BG2: Ova | BH2: no | BI2: Octubre-Diciembre | BJ2: 3 | BK2: Usa esteras con manta y sargazo/palmeras | BL2: 30-40 | BM2: 72 | BN2: 10-12 | BO2: 10-100 | BP2: 350-1300 | BQ2: Acopiador | BR2: 22-38 | BS2: no | BT2: NA | BU2: NA | BV2: NA | BW2: NA | BX2: NA | BY2: NA | BZ2: NA | CA2: NA | CB2: NA | CC2: NA | CD2: NA | CE2: NA | CF2: NA | CG2: NA | CH2: NA | CI2: no | CJ2: NA | CK2: NA | CL2: NA | CM2: NA | CN2: NA | CO2: NA | CP2: NA | CQ2: NA | CR2: NA | CS2: NA | CT2: NA | CU2: NA | CV2: El zargazo proviene de la colecta de algas en orilla y las palmeras de las chacras de Nasca.
A3: CC-MARCONA-002 | B3: Cristel Cordero | C3: 45775 | D3: Pelagio Huamán Bacas | E3: 22089409 | F3: 38 | G3: 24 | H3: Marcona | I3: Marcona | J3: Marcona | K3: 23460 | L3: =DATEDIF(K3, DATE(2025,8,29), "Y") -> 61 | M3: M | N3: Casado/Conviviente | O3: Secundaria | P3: si | Q3: si | R3: Armador, Patrón | S3: si | T3: APROMAR | U3: si | V3: Colecta de algas | W3: algas | X3: Cortina costera | Y3: cabinza | Z3: Pinta | AA3: cabinza, jurel, cojinova, cabrilla | AB3: no | AC3: NA | AD3: 2 | AE3: 6 | AF3: si | AG3: Ama de casa | AH3: si | AI3: 1 hijo (recolección de algas) | AJ3: si | AK3: NA | AL3: si | AM3: NA | AN3: 2 | AO3: si | AP3: ALEX II | AQ3: NS | AR3: no | AS3: no | AT3: si | AU3: 3 | AV3: NA | AW3: NA | AX3: NA | AY3: NA | AZ3: NA | BA3: NA | BB3: 180 | BC3: Trampa Ovas | BD3: 3 | BE3: 35-61 | BF3: Peruana | BG3: Ova | BH3: no | BI3: Noviembre-Febrero | BJ3: 4 | BK3: Usa esteras y sargazo | BL3: 28-35 | BM3: 72 | BN3: 5-8 | BO3: 50-300 | BP3: 300-1000 | BQ3: Acopiador | BR3: 24-40 | BS3: no | BT3: NA | BU3: NA | BV3: NA | BW3: NA | BX3: NA | BY3: NA | BZ3: NA | CA3: NA | CB3: NA | CC3: NA | CD3: NA | CE3: NA | CF3: NA | CG3: NA | CH3: NA | CI3: no | CJ3: NA | CK3: NA | CL3: NA | CM3: NA | CN3: NA | CO3: NA | CP3: NA | CQ3: NA | CR3: NA | CS3: NA | CT3: NA | CU3: NA | CV3: Puertos que también salen a la ova: Chala, Atico, Planchada, Chimbote, Callao, Pucusana.
A4: CC-MARCONA-003 | B4: Cristel Cordero | C4: 45775 | D4: Julio Orihuela Cavero | E4: 22086318 | F4: 41 | G4: 20 | H4: Marcona | I4: Marcona | J4: Marcona | K4: 23586 | L4: =DATEDIF(K4, DATE(2025,8,29), "Y") -> 61 | M4: M | N4: Casado/Conviviente | O4: Secundaria | P4: si | Q4: si | R4: Armador, Patrón | S4: si | T4: APROMAR | U4: si | V4: Colecta de algas | W4: algas | X4: Buceo compresora | Y4: mariscos | Z4: Buceo pulmón | AA4: yuyo | AB4: no | AC4: NA | AD4: 0 | AE4: 1 | AF4: si | AG4: Negocio (alquiler de habitaciones) y Ama de casa | AH4: no | AI4: NA | AJ4: si | AK4: NA | AL4: si | AM4: NA | AN4: 1 | AO4: si | AP4: GENO Y KATTY II | AQ4: SN-59858-BM | AR4: no | AS4: si | AT4: si | AU4: 5 | AV4: NA | AW4: NA | AX4: NA | AY4: NA | AZ4: NA | BA4: NA | BB4: 136-204 | BC4: Trampa Ovas | BD4: 3 | BE4: 30-60 | BF4: Peruana y Venezolana | BG4: Ova | BH4: no | BI4: Octubre-Febrero | BJ4: 5-6 | BK4: Usa esteras con manta y sargazo/palmeras | BL4: 20-30 | BM4: 48-96 | BN4: 8-12 | BO4: 30-300 | BP4: 800-2000 | BQ4: Acopiador | BR4: 15-45 | BS4: no | BT4: NA | BU4: NA | BV4: NA | BW4: NA | BX4: NA | BY4: NA | BZ4: NA | CA4: NA | CB4: NA | CC4: NA | CD4: NA | CE4: NA | CF4: NA | CG4: NA | CH4: NA | CI4: no | CJ4: NA | CK4: NA | CL4: NA | CM4: NA | CN4: NA | CO4: NA | CP4: NA | CQ4: NA | CR4: NA | CS4: NA | CT4: NA | CU4: NA | CV4: Temperatura óptima para el pez volador: 17 °C. Ova con ojo (S/.10), el acopiador le descuenta. Indica que los pescadores quieren vender directo a la empresa.
A5: CC-MARCONA-004 | B5: Cristel Cordero | C5: 45775 | D5: Washington Espinoza Bolas | E5: 22086548 | F5: 50 | G5: 30 | H5: Marcona | I5: Marcona | J5: Marcona | K5: 22184 | L5: =DATEDIF(K5, DATE(2025,8,29), "Y") -> 64 | M5: M | N5: Casado/Conviviente | O5: Secundaria | P5: si | Q5: si | R5: Armador | S5: si | T5: APROMAR | U5: si | V5: Buceo compresora | W5: mariscos | X5: Buceo pulmón | Y5: mariscos | Z5: Trampa nasas | AA5: cangrejos | AB5: no | AC5: NA | AD5: 0 | AE5: 3 | AF5: si | AG5: Ama de casa | AH5: no | AI5: NA | AJ5: no | AK5: Prefiere que las mujeres participen en el procesamiento, considerando que Marcona no tiene plantas de procesamiento, pero falta oportunidades para su capacitación. | AL5: si | AM5: NA | AN5: 2 | AO5: si | AP5: YOSELYN I | AQ5: NS | AR5: no | AS5: no | AT5: si | AU5: 4 | AV5: YOSELIN II | AW5: NS | AX5: no | AY5: no | AZ5: si | BA5: 6 | BB5: 50-200 | BC5: Trampa Ovas | BD5: 4 | BE5: 18-50 | BF5: Peruana | BG5: Ova | BH5: no | BI5: Octubre-Enero | BJ5: 3 | BK5: Usa esteras con manta y sargazo/palmeras | BL5: 25 | BM5: 48-72 | BN5: 10 | BO5: 10-500 | BP5: 800-1000 | BQ5: Acopiador | BR5: 30-40 | BS5: Pinta potera | BT5: 4 | BU5: 18-50 | BV5: Peruana | BW5: Pota | BX5: no | BY5: Todo el año (cuota) | BZ5: 3/mes | CA5: NA | CB5: 3-5 | CC5: NA | CD5: NA | CE5: NA | CF5: 1000-5000 | CG5: Acopiador | CH5: 2-4 | CI5: Espinel superficial | CJ5: Perico | CK5: pota, pez volador | CL5: Enero-Marzo | CM5: 7 | CN5: Linea madre: 500 m, 40-60 lineas, #anzuelos/linea: 1, Calibre: 2 | CO5: 8 | CP5: 1 | CQ5: 80 | CR5: 300 | CS5: 1000-3000 | CT5: Acopiador | CU5: 5-14 | CV5: Ovas con ojo lo descartan al mar ya que su valor económico es mínimo. Para la pesca de pota son 4 pescaodres y cada uno trabaja con una muestra potera. Pesca de perico con espinel es complementaria a la pesca del pez volador.
A6: CC-MARCONA-005 | B6: Cristel Cordero | C6: 45775 | D6: Javier Alarcón | E6: 21859466 | F6: 30 | G6: 20 | H6: Marcona | I6: Marcona | J6: Marcona | K6: 25156 | L6: =DATEDIF(K6, DATE(2025,8,29), "Y") -> 56 | M6: M | N6: Casado/Conviviente | O6: Primaria | P6: si | Q6: si | R6: Armador, Patrón | S6: si | T6: Asociación de Armadores y Maricultores de la Bahía de San Juan de Marcona | U6: si | V6: Buceo compresora | W6: mariscos | X6: NA | Y6: NA | Z6: NA | AA6: NA | AB6: no | AC6: NA | AD6: 1 | AE6: 2 | AF6: si | AG6: Ama de casa | AH6: si | AI6: 1 hijo (tripulante) | AJ6: no | AK6: No, por la fuerza. | AL6: NS | AM6: NA | AN6: 1 | AO6: si | AP6: YAIR Y ARAEL | AQ6: NS | AR6: no | AS6: no | AT6: si | AU6: 5 | AV6: NA | AW6: NA | AX6: NA | AY6: NA | AZ6: NA | BA6: NA | BB6: 100-150 | BC6: Trampa Ovas | BD6: 3 | BE6: 30-50 | BF6: Peruana | BG6: Ova | BH6: no | BI6: Noviembre-Enero | BJ6: 3-4 | BK6: Usa esteras y sargazo | BL6: 20 | BM6: 3 | BN6: 3-4 | BO6: 40-200 | BP6: 500-1000 | BQ6: Acopiador | BR6: 30-38 | BS6: Pinta potera | BT6: 4 | BU6: 30-50 | BV6: Peruana | BW6: Pota | BX6: no | BY6: Diciembre-Abril | BZ6: 15-20 | CA6: NA | CB6: 4-5 | CC6: 4 | CD6: NA | CE6: NA | CF6: 200-1000 | CG6: Acopiador | CH6: 4 | CI6: no | CJ6: NA | CK6: NA | CL6: NA | CM6: NA | CN6: NA | CO6: NA | CP6: NA | CQ6: NA | CR6: NA | CS6: NA | CT6: NA | CU6: NA | CV6: Ovas con ojo lo descartan al mar ya que su valor económico es mínimo.
A7: CC-MARCONA-006 | B7: Cristel Cordero | C7: 45776 | D7: José Rojas Heredia | E7: 44825753 | F7: 13 | G7: 13 | H7: Marcona | I7: Marcona | J7: Marcona, El Chaco | K7: 31718 | L7: =DATEDIF(K7, DATE(2025,8,29), "Y") -> 38 | M7: M | N7: Casado/Conviviente | O7: Secundaria | P7: si | Q7: si | R7: Armador, Patrón | S7: si | T7: ASMASPEMAR | U7: si | V7: Colecta de algas | W7: algas | X7: NA | Y7: NA | Z7: NA | AA7: NA | AB7: no | AC7: NA | AD7: 4 | AE7: 3 | AF7: si | AG7: Ama de casa | AH7: no | AI7: NA | AJ7: no | AK7: El trabajo en la pesca es muy fuerte (fuerza física). Muy pocos hombres se embarcan con su pareja. | AL7: si | AM7: NA | AN7: 1 | AO7: si | AP7: ALEX STEFANO | AQ7: NS | AR7: NS | AS7: NS | AT7: NS | AU7: 3 | AV7: NA | AW7: NA | AX7: NA | AY7: NA | AZ7: NA | BA7: NA | BB7: 160-200 | BC7: Trampa Ovas | BD7: 3 | BE7: 20-65 | BF7: Peruana | BG7: Ova | BH7: no | BI7: Noviembre-Enero | BJ7: 3 | BK7: Usa esteras (6:3x2 m) con manta 8: 6x2 m) y sargazo/palmeras | BL7: 20-25 | BM7: 48-72 | BN7: 2-7 | BO7: 1-300 | BP7: 350-700 | BQ7: Acopiador | BR7: 22-45 | BS7: Cortina superficial | BT7: 4 | BU7: 20-65 | BV7: Peruana | BW7: Bonito | BX7: no | BY7: Noviembre-Enero | BZ7: 6-9 | CA7: #paños: 5, cocada: 5 pulgadas, malla 5x37 metros | CB7: 2-3 | CC7: 0.5-2 | CD7: 3-6 | CE7: 10-200 | CF7: 800-2000 | CG7: Acopiador | CH7: 1-3 | CI7: Pinta potera | CJ7: Pota | CK7: no | CL7: Todo el año (cuota) | CM7: 2-3/mes | CN7: NA | CO7: 2-3 | CP7: NA | CQ7: NA | CR7: 5-15 | CS7: 800-2000 | CT7: Acopiador | CU7: 3.5 | CV7: Menciona que algunas embarcaciones vienen de Piura (conocidas comunmente como Vikingos - embarcaciones grandes de 10 a 20 TN) vienen a pescar ovas, perico, pota y se llevan todo. Pesca de ovas: Noviembre y Diciembre (horas efectivas de pesca por lance: 3 días), Enero (horas efectivas de pesca por lance: 2 días). La ova con ojo lo descarta al mar ya que el acopiador no lo compra.
A8: CC-MARCONA-007 | B8: Cristel Cordero | C8: 45776 | D8: Juan Camacho Calderón | E8: 22284947 | F8: 58 | G8: 19 | H8: Marcona | I8: Marcona | J8: Marcona | K8: 20264 | L8: =DATEDIF(K8, DATE(2025,8,29), "Y") -> 70 | M8: M | N8: Soltero | O8: Primaria | P8: si | Q8: si | R8: Patrón | S8: si | T8: APROBENTO | U8: si | V8: Pinta | W8: bonito | X8: NA | Y8: NA | Z8: NA | AA8: NA | AB8: si | AC8: Albañil | AD8: 1 | AE8: 3 | AF8: no | AG8: NA | AH8: no | AI8: NA | AJ8: si | AK8: NA | AL8: no | AM8: Cuando no es familiar, se le paga un poco menos) | AN8: 0 | AO8: NA | AP8: DIOS ES AMOR I | AQ8: SN-41836-BM | AR8: no | AS8: no | AT8: si | AU8: 5 | AV8: NA | AW8: NA | AX8: NA | AY8: NA | AZ8: NA | BA8: NA | BB8: 240 | BC8: Trampa Ovas | BD8: 2 | BE8: 64-70 | BF8: Peruana | BG8: Ova | BH8: no | BI8: Septiembre-Febrero | BJ8: 5 | BK8: Usa manta (16: 6x2 m) y palmeras | BL8: 25-40 | BM8: 48-72 | BN8: 8 | BO8: 30-100 | BP8: 380-700 | BQ8: Acopiador | BR8: 23-42 | BS8: no | BT8: NA | BU8: NA | BV8: NA | BW8: NA | BX8: NA | BY8: NA | BZ8: NA | CA8: NA | CB8: NA | CC8: NA | CD8: NA | CE8: NA | CF8: NA | CG8: NA | CH8: NA | CI8: no | CJ8: NA | CK8: NA | CL8: NA | CM8: NA | CN8: NA | CO8: NA | CP8: NA | CQ8: NA | CR8: NA | CS8: NA | CT8: NA | CU8: NA | CV8: 18-19°C el pez volador desova (se recoge a los 3 días) y 21°C pez volador desova (se recoge a los 2 días). Ova con ojo (S/.12).
A9: CC-MARCONA-008 | B9: Cristel Cordero | C9: 45776 | D9: Marcos Rodriguez Mendoza | E9: 22092013 | F9: 40 | G9: 25 | H9: Marcona | I9: Marcona, Lomas, Atico | J9: Marcona, Lomas, Atico | K9: 26401 | L9: =DATEDIF(K9, DATE(2025,8,29), "Y") -> 53 | M9: M | N9: Soltero | O9: Secundaria | P9: si | Q9: si | R9: Patrón | S9: si | T9: APROBENTO | U9: si | V9: Pinta | W9: jurel, caballa, cabinza | X9: Buceo compresora | Y9: mariscos | Z9: NA | AA9: NA | AB9: si | AC9: Mototaxista, Auxiliar en mina | AD9: 1 | AE9: 1 | AF9: no | AG9: NA | AH9: no | AI9: NA | AJ9: si | AK9: NA | AL9: si | AM9: NA | AN9: 0 | AO9: NA | AP9: JESUCRISTO ES REY DE REYES | AQ9: PS-33229-BM | AR9: no | AS9: no | AT9: si | AU9: 6 | AV9: NA | AW9: NA | AX9: NA | AY9: NA | AZ9: NA | BA9: NA | BB9: 96 | BC9: Trampa Ovas | BD9: 3 | BE9: 20-60 | BF9: Peruana | BG9: Ova | BH9: no | BI9: Octubre-Febrero | BJ9: 5 | BK9: Usa esteras con manta y sargazo/palmeras/manguera | BL9: 30 | BM9: 48-72 | BN9: 10 | BO9: 20-150 | BP9: 800-1000 | BQ9: Acopiador | BR9: 32-45 | BS9: Espinel superficial | BT9: 4 | BU9: 20-60 | BV9: Peruana | BW9: Perico, Tiburón azul | BX9: Pota, Pez Volador | BY9: Diciembre-Febrero | BZ9: 5 | CA9: Linea madre: 40 m, #anzuelos/linea: 1, # anzuelos: 100-300, Calibre: NS | CB9: 15-20 | CC9: 2-3 | CD9: 30-45 | CE9: 100-200 | CF9: 2000-3000 | CG9: Acopiador | CH9: Perico (3.50-5), Azul (3) | CI9: no | CJ9: NA | CK9: NA | CL9: NA | CM9: NA | CN9: NA | CO9: NA | CP9: NA | CQ9: NA | CR9: NA | CS9: NA | CT9: NA | CU9: NA | CV9: Ova con ojo se lo guarda para él, como consumo en semana santa y ciertos platos), también lo descarta al mar para que continúe su ciclo.
A10: CC-MARCONA-009 | B10: Cristel Cordero | C10: 45776 | D10: José Ángel Bautista Gamboa | E10: 42663035 | F10: 25 | G10: 20 | H10: Marcona | I10: Marcona | J10: Marcona | K10: 30907 | L10: =DATEDIF(K10, DATE(2025,8,29), "Y") -> 41 | M10: M | N10: Soltero | O10: Secundaria | P10: si | Q10: si | R10: Armador, Patrón | S10: si | T10: APROMAR | U10: si | V10: Buceo compresora | W10: mariscos | X10: Colecta de algas | Y10: algas | Z10: NA | AA10: NA | AB10: no | AC10: NA | AD10: 2 | AE10: 2 | AF10: no | AG10: NA | AH10: no | AI10: NA | AJ10: si | AK10: NA | AL10: no | AM10: El pago se negocia, normalmente se le paga un poco menos a las mujeres | AN10: 1 | AO10: si | AP10: EL RETORNO DEL NAIHS | AQ10: SN-59909-BM | AR10: no | AS10: si | AT10: si | AU10: 4.5 | AV10: NA | AW10: NA | AX10: NA | AY10: NA | AZ10: NA | BA10: NA | BB10: 102-204 | BC10: Trampa Ovas | BD10: 3 | BE10: 25-38 | BF10: Peruana | BG10: Ova | BH10: no | BI10: Octubre-Febrero | BJ10: 4 | BK10: Usa esteras y manguera | BL10: 20-30 | BM10: 24-96 | BN10: 7 | BO10: 200 | BP10: 600-1000 | BQ10: Acopiador | BR10: 20-40 | BS10: Pinta potera | BT10: 4 | BU10: 25-38 | BV10: Peruana | BW10: Pota | BX10: no | BY10: Todo el año (cuota) | BZ10: 4/mes | CA10: NA | CB10: 2-4 | CC10: NA | CD10: NA | CE10: NA | CF10: 3000 | CG10: Acopiador | CH10: 3-4 | CI10: Cortina de superficie | CJ10: Bonito | CK10: no | CL10: Todo el año (cuota) | CM10: 2-3/mes | CN10: #paños: 6, cocada: 4 y 3 3/4 pulgadas, malla 13x60 m | CO10: 5-7 | CP10: 0.5-1 | CQ10: 2-10 | CR10: 500 | CS10: 2000-3000 | CT10: Comerciante | CU10: 1.5-6 | CV10: Ova pasa de ser una coloración blanquesina a negruzca (ova oscura ya no te compran).
A11: CC-MARCONA-010 | B11: Cristel Cordero | C11: 45777 | D11: Juan Jesús Carlos Medina | E11: 22285772 | F11: 55 | G11: 50 | H11: Marcona | I11: Marcona | J11: Marcona | K11: 21275 | L11: =DATEDIF(K11, DATE(2025,8,29), "Y") -> 67 | M11: M | N11: Casado/Conviviente | O11: Secundaria | P11: si | Q11: no | R11: Armador, Patrón | S11: si | T11: ASOCIACION DE BOLICHITOS ARTESANALES DE SAN JUAN DE MARCONA JUAN MARCIAL VALENZUELA | U11: si | V11: Cerco costero | W11: jurel, caballa | X11: NA | Y11: NA | Z11: NA | AA11: NA | AB11: si | AC11: Presidente de OSPA | AD11: 0 | AE11: 5 | AF11: si | AG11: Costurera | AH11: no | AI11: NA | AJ11: si | AK11: NA | AL11: si | AM11: NA | AN11: 2 | AO11: si | AP11: AKIMSHU | AQ11: PT-51299-BM | AR11: no | AS11: no | AT11: si | AU11: 15 | AV11: NA | AW11: NA | AX11: NA | AY11: NA | AZ11: NA | BA11: NA | BB11: 240 | BC11: Cerco | BD11: 4 | BE11: 25-64 | BF11: Peruana | BG11: Bonito | BH11: no | BI11: Diciembre-Febrero | BJ11: 10-15 | BK11: Cerco no mecanizado, cocada: 1.5 pulgadas | BL11: 2-3 | BM11: 3-4 | BN11: 3-7 | BO11: 20-30 | BP11: 12000 | BQ11: Acopiador | BR11: 4-7 | BS11: Espinel superficial | BT11: 7 | BU11: 25-64 | BV11: Peruana | BW11: Perico | BX11: Delfin | BY11: Diciembre-Febrero | BZ11: 1-2 | CA11: Linea madre: 4000 m, # anzuelos:1000, Calibre: 6 | CB11: 7-15 | CC11: 3-4 | CD11: 8-12 | CE11: 300-600 | CF11: 5000-10000 | CG11: Acopiador | CH11: 4 | CI11: Trampa ovas | CJ11: Ova | CK11: no | CL11: Octubre-Febrero | CM11: 3 | CN11: Usa mantas (15: 3x4 m) y palmera/manguera | CO11: 7-40 | CP11: 72 | CQ11: 2-15 | CR11: 10-200 | CS11: 300-1000 | CT11: Acopiador | CU11: 37-45 | CV11: Ova con ojo: S/8 a S/10 kg. Tiran su red cuando pasan delfines y el que cae capturado se filetea y se coloca como carnada.
A12: CC-MARCONA-011 | B12: Cristel Cordero | C12: 45777 | D12: Grimaldo Flores Rivero | E12: 43754263 | F12: 11 | G12: 11 | H12: Marcona | I12: Marcona | J12: Marcona | K12: 31684 | L12: =DATEDIF(K12, DATE(2025,8,29), "Y") -> 38 | M12: M | N12: Casado/Conviviente | O12: Secundaria | P12: si | Q12: si | R12: Armador, Patrón | S12: si | T12: APROMAR | U12: si | V12: Pinta | W12: jurel, caballa | X12: Colecta de algas | Y12: algas | Z12: NA | AA12: NA | AB12: si | AC12: Albañil | AD12: 3 | AE12: 2 | AF12: si | AG12: Ama de casa | AH12: no | AI12: NA | AJ12: si | AK12: NA | AL12: si | AM12: NA | AN12: 1 | AO12: si | AP12: APURIMEÑO II | AQ12: PS-17805-BM | AR12: no | AS12: si | AT12: si | AU12: 8 | AV12: NA | AW12: NA | AX12: NA | AY12: NA | AZ12: NA | BA12: NA | BB12: 204-238 | BC12: Trampa Ovas | BD12: 3 | BE12: 35-45 | BF12: Peruana | BG12: Ova | BH12: no | BI12: Noviembre-Enero | BJ12: 3-4 | BK12: Usa mantas (18: 3x1.5 m) y palmeras | BL12: 10-30 | BM12: 48-72 | BN12: 3-7 | BO12: 100-300 | BP12: 700-1000 | BQ12: Acopiador | BR12: 25-45 | BS12: no | BT12: NA | BU12: NA | BV12: NA | BW12: NA | BX12: NA | BY12: NA | BZ12: NA | CA12: NA | CB12: NA | CC12: NA | CD12: NA | CE12: NA | CF12: NA | CG12: NA | CH12: NA | CI12: no | CJ12: NA | CK12: NA | CL12: NA | CM12: NA | CN12: NA | CO12: NA | CP12: NA | CQ12: NA | CR12: NA | CS12: NA | CT12: NA | CU12: NA | CV12: Acopiadora de ovas Ana Candia. Precio de ova con ojo: S/. 4. Usan 10 a 12 sacos de sal para salar las ovas (1 saco = 50 kg). Temporada 2024-2025 no salió a la ova. La pota ha aparecido cerca a la costa (frente a Marcona y Lomas) ahora en 2025, no se veía eso desde el 2012.
A13: CC-MARCONA-012 | B13: Cristel Cordero | C13: 45804 | D13: Oscar Polanco García | E13: 43052807 | F13: 26 | G13: 20 | H13: Marcona | I13: Marcona | J13: Marcona | K13: 31178 | L13: =DATEDIF(K13, DATE(2025,8,29), "Y") -> 40 | M13: M | N13: Casado/Conviviente | O13: Superior Técnico | P13: si | Q13: no | R13: Armador, Patrón | S13: si | T13: APROBENTO | U13: si | V13: Buceo compresora | W13: mariscos, pulpo | X13: NA | Y13: NA | Z13: NA | AA13: NA | AB13: no | AC13: NA | AD13: 0 | AE13: 0 | AF13: si | AG13: Pequeño comercio (tienda en casa) y Armadora | AH13: si | AI13: Pareja (armadora) | AJ13: si | AK13: NA | AL13: no | AM13: Mujeres reciben un poco menos ya que no manejan la embarcación y no cargan mucho peso. | AN13: 1 | AO13: si | AP13: VIRGEN DE LAS NIEVES V | AQ13: TA-61627-BM | AR13: no | AS13: no | AT13: si | AU13: 13 | AV13: VIRGEN DE LAS NIEVES IV | AW13: SN-57548-BM | AX13: no | AY13: no | AZ13: si | BA13: 8 | BB13: 208 | BC13: Trampa Ovas | BD13: 4 | BE13: 35-75 | BF13: Peruana | BG13: Ova | BH13: no | BI13: Octubre-Enero | BJ13: 4 | BK13: Usa esteras con manta y sargazo/palmeras | BL13: 25-40 | BM13: 48-72 | BN13: 10 | BO13: 20-300 | BP13: 1200-2000 | BQ13: Acopiador | BR13: 25-45 | BS13: Cortina superficial | BT13: 4 | BU13: 35-75 | BV13: Peruana | BW13: Bonito | BX13: no | BY13: Octubre-Junio | BZ13: 18-27 | CA13: #paños: 10, cocada: 3 3/4 y 4 pulgadas, malla 15x60 metros | CB13: 3-5 | CC13: 0.5-1 | CD13: 9-15 | CE13: 100-1000 | CF13: 500-3000 | CG13: Acopiador | CH13: 1.5-4 | CI13: Cerco | CJ13: Jurel, Caballa, Bonito | CK13: no | CL13: Todo el año (cuota) | CM13: 3-5/mes | CN13: Cerco mecanizado, 1.5 pulgadas | CO13: 2-4 | CP13: 2-3 | CQ13: 4-5 | CR13: 100-6000 | CS13: 1000-10000 | CT13: Acopiador | CU13: Jurel: 1-5, Caballa: 0.80-3, Bonito: 1.5-4 | CV13: De 10 a 30 kg le sale ova con ojo del total de su faena (S/. 10). En la altura, todos los pescadores cuentan con GPS. Algunos armadores si llevan a su pareja a la altura.
A14: CC-MARCONA-013 | B14: Cristel Cordero | C14: 45804 | D14: Florentino Bustrón Mamani | E14: 22284452 | F14: 44 | G14: 44 | H14: Marcona | I14: Marcona | J14: Marcona | K14: 22212 | L14: =DATEDIF(K14, DATE(2025,8,29), "Y") -> 64 | M14: M | N14: Casado/Conviviente | O14: Primaria | P14: si | Q14: si | R14: Armador, Patrón | S14: si | T14: ASOCIACION DE MARICULTORES DE LOS HIJOS DE JACOB DE ESPECIES HIDROBIOLOGICAS – MARCONA | U14: si | V14: Buceo compresora | W14: mariscos | X14: NA | Y14: NA | Z14: NA | AA14: NA | AB14: no | AC14: NA | AD14: 1 | AE14: 6 | AF14: si | AG14: Ama de casa | AH14: si | AI14: 1 hijo (buzo embarcado) | AJ14: si | AK14: NA | AL14: si | AM14: NA | AN14: 1 | AO14: si | AP14: DIANA Y LUCERO IV | AQ14: PS-30225-BM | AR14: no | AS14: no | AT14: si | AU14: 6 | AV14: NA | AW14: NA | AX14: NA | AY14: NA | AZ14: NA | BA14: NA | BB14: 272 | BC14: Trampa Ovas | BD14: 3 | BE14: 22-64 | BF14: Peruana y Venezolana | BG14: Ova | BH14: no | BI14: Octubre-Febrero | BJ14: 4-5 | BK14: Usa esteras (15) con manta (15) y sargazo/palmeras | BL14: 15-20 | BM14: 48-96 | BN14: 3-5 | BO14: 500-1000 | BP14: 700-1000 | BQ14: Acopiador | BR14: 25-35 | BS14: Espinel superficial | BT14: 5 | BU14: 22-64 | BV14: Peruana y Venezolana | BW14: Perico | BX14: Pota, Caballa, Pez volador | BY14: Noviembre-Febrero | BZ14: 4 | CA14: Linea madre: 1000 m, #anzuelos/linea: 1, # anzuelos: 80, Calibre: 6 o 7 | CB14: 15-20 | CC14: 8-10 | CD14: 5 | CE14: 100-200 | CF14: 1000-1500 | CG14: Acopiador | CH14: 4 | CI14: no | CJ14: NA | CK14: NA | CL14: NA | CM14: NA | CN14: NA | CO14: NA | CP14: NA | CQ14: NA | CR14: NA | CS14: NA | CT14: NA | CU14: NA | CV14: En su OSPA son solo 4 integrantes que tienen embarcación para la altura. Precio de ova con ojo: S/.5.
A15: CC-MARCONA-014 | B15: Cristel Cordero | C15: 45805 | D15: Jimmy Soriano Ormeño | E15: 44939456 | F15: 24 | G15: 15 | H15: Marcona | I15: Marcona | J15: Marcona | K15: 30258 | L15: =DATEDIF(K15, DATE(2025,8,29), "Y") -> 42 | M15: M | N15: Casado/Conviviente | O15: Primaria | P15: si | Q15: no | R15: Armador, Patrón | S15: si | T15: Asociación de Armadores y Maricultores de la Bahía de San Juan de Marcona | U15: si | V15: Buceo compresora | W15: mariscos | X15: Cortina de fondo | Y15: lenguado, cabrilla, congrio | Z15: Pinta | AA15: jurel, cojinova, cabinza, caballa | AB15: no | AC15: NA | AD15: 3 | AE15: 2 | AF15: si | AG15: Ama de casa | AH15: no | AI15: NA | AJ15: si | AK15: NA | AL15: si | AM15: NA | AN15: 1 | AO15: si | AP15: JIMMY ANDERSON | AQ15: SN-03566-BM | AR15: no | AS15: no | AT15: si | AU15: 4 | AV15: NA | AW15: NA | AX15: NA | AY15: NA | AZ15: NA | BA15: NA | BB15: 192 | BC15: Trampa Ovas | BD15: 3-4 | BE15: 30-40 | BF15: Peruana | BG15: Ova | BH15: no | BI15: Octubre-Enero | BJ15: 4-5 | BK15: Usa mantas (15) y zargazo/palmeras | BL15: 20-25 | BM15: 72 | BN15: 6 | BO15: 50-200 | BP15: 700 | BQ15: Acopiador | BR15: 25-35 | BS15: Pinta potera | BT15: 3-4 | BU15: 30-40 | BV15: Peruana | BW15: Pota | BX15: no | BY15: Todo el año (cuota) | BZ15: 4/mes | CA15: NA | CB15: 4 | CC15: NA | CD15: NA | CE15: NA | CF15: 3000 | CG15: Acopiador | CH15: 1.5-4 | CI15: Espinel superficial | CJ15: Perico | CK15: pota, pez volador | CL15: Octubre-Febrero | CM15: 12-15 | CN15: Linea madre: 1280 m, 700 lineas #anzuelos/linea: 1, Calibre: 4 o 5 | CO15: 5-6 | CP15: 3-4 | CQ15: 5 | CR15: 500-700 | CS15: 1500-3000 | CT15: Acopiador | CU15: 4-7 | CV15: Considera que cada vez hay menos pesca ya que hay mucha presión pesquera industrial anchovetera. Asimismo, indica que ova con ojo no tiene valor económico por lo que a bordo prefiere regresarlo al mar.
A16: CC-MARCONA-016 | B16: Cristel Cordero | C16: 45805 | D16: Julio Loayza Aliaga | E16: 22283907 | F16: 40 | G16: 30 | H16: Marcona | I16: Marcona | J16: Marcona | K16: 23750 | L16: =DATEDIF(K16, DATE(2025,8,29), "Y") -> 60 | M16: M | N16: Casado/Conviviente | O16: Secundaria | P16: si | Q16: si | R16: Armador, Patrón | S16: si | T16: APROBENTO | U16: si | V16: Cortina de fondo | W16: corvina, lenguado | X16: Colecta de algas | Y16: algas | Z16: NA | AA16: NA | AB16: no | AC16: NA | AD16: 2 | AE16: 3 | AF16: si | AG16: Armadora, Ama de casa | AH16: si | AI16: Pareja (armadora), 1 hijo (tripulante) | AJ16: si | AK16: NA | AL16: si | AM16: NA | AN16: 1 | AO16: si | AP16: CALET Y MATEO | AQ16: SN-34964-BM | AR16: no | AS16: no | AT16: si | AU16: 8 | AV16: NA | AW16: NA | AX16: NA | AY16: NA | AZ16: NA | BA16: NA | BB16: 100 | BC16: Trampa Ovas | BD16: 3 | BE16: 30-40 | BF16: Peruana | BG16: Ova | BH16: no | BI16: Septiembre-Febrero | BJ16: 4-5 | BK16: Usa esteras (10) con manta (15) y sargazo/palmeras | BL16: 28-30 | BM16: 72 | BN16: 7-8 | BO16: 100 | BP16: 800-1000 | BQ16: Acopiador | BR16: 25-32 | BS16: no | BT16: NA | BU16: NA | BV16: NA | BW16: NA | BX16: NA | BY16: NA | BZ16: NA | CA16: NA | CB16: NA | CC16: NA | CD16: NA | CE16: NA | CF16: NA | CG16: NA | CH16: NA | CI16: no | CJ16: NA | CK16: NA | CL16: NA | CM16: NA | CN16: NA | CO16: NA | CP16: NA | CQ16: NA | CR16: NA | CS16: NA | CT16: NA | CU16: NA | CV16: No le alcanza el dinero para comprar radiobaliza, aunque considera que si es de suma importancia para la seguridad de los tripulantes. Para la primera salida para la ova se gasta un total de 15,000 soles (8,000 combustible + 3500 mantas y esteras + 600 zargazo + 2400 palmeras + 700 otras herramientas como palos y cabos)
A17: CC-MARCONA-017 | B17: Cristel Cordero | C17: 45805 | D17: Abel Quispe Calle | E17: 46281470 | F17: 15 | G17: 15 | H17: Marcona | I17: Marcona | J17: Marcona, San Andrés, El Chaco | K17: 33329 | L17: =DATEDIF(K17, DATE(2025,8,29), "Y") -> 34 | M17: M | N17: Casado/Conviviente | O17: Secundaria | P17: si | Q17: si | R17: Patrón | S17: si | T17: APROBENTO, ASOCIACION DE MARICULTORES SAN PEDRO DEL PUERTO SAN JUAN DE MARCONA | U17: si | V17: Buceo compresora | W17: mariscos, lenguado, pintadilla | X17: Buceo pulmón | Y17: mariscos, lenguado, pintadilla | Z17: Cortina de fondo | AA17: corvina | AB17: no | AC17: NA | AD17: 2 | AE17: 2 | AF17: si | AG17: Lava pescado, Ama de casa | AH17: si | AI17: Pareja (lava pescado), 1 hijo (tripulante) | AJ17: si | AK17: NA | AL17: si | AM17: NA | AN17: 0 | AO17: NA | AP17: MIS TRES AMORES | AQ17: SN-03568-BM | AR17: no | AS17: no | AT17: si | AU17: 6 | AV17: NA | AW17: NA | AX17: NA | AY17: NA | AZ17: NA | BA17: NA | BB17: 208 | BC17: Trampa Ovas | BD17: 3 | BE17: 34-50 | BF17: Peruana | BG17: Ova | BH17: no | BI17: Octubre-Febrero | BJ17: 4 | BK17: Usa esteras con manta y sargazo | BL17: 30 | BM17: 72 | BN17: 6 | BO17: 100-500 | BP17: 800-1000 | BQ17: Acopiador | BR17: 22-35 | BS17: Pinta potera | BT17: 4 | BU17: 34-50 | BV17: Peruana | BW17: Pota | BX17: no | BY17: Diciembre-Febrero | BZ17: 5-6 | CA17: NA | CB17: 3-4 | CC17: NA | CD17: NA | CE17: NA | CF17: 3000-4000 | CG17: Acopiador | CH17: 1.5-3.5 | CI17: no | CJ17: NA | CK17: NA | CL17: NA | CM17: NA | CN17: NA | CO17: NA | CP17: NA | CQ17: NA | CR17: NA | CS17: NA | CT17: NA | CU17: NA | CV17: Indica que de 1 a 2 horas demora desde tirar la muestra, esperar que la pota se enganche y calar la muestra. Trabaja con acopiador Efrain y Debora, tanto para ova y pota, y este no le paga por ova con ojo.
A18: CC-MARCONA-018 | B18: Cristel Cordero | C18: 45806 | D18: Maximo Napa Castro | E18: 22285378 | F18: 48 | G18: 30 | H18: Marcona | I18: Marcona | J18: Marcona, Pisco | K18: 23423 | L18: =DATEDIF(K18, DATE(2025,8,29), "Y") -> 61 | M18: M | N18: Divorciado | O18: Primaria | P18: si | Q18: no | R18: Armador, Patrón | S18: si | T18: APROBENTO | U18: si | V18: Buceo compresora | W18: cabrilla, lenguado, pintadilla | X18: NA | Y18: NA | Z18: NA | AA18: NA | AB18: no | AC18: NA | AD18: 0 | AE18: 7 | AF18: no | AG18: NA | AH18: si | AI18: 2 hijos (patrón) | AJ18: si | AK18: NA | AL18: si | AM18: NA | AN18: 2 | AO18: si | AP18: GATÓN II | AQ18: no | AR18: no | AS18: no | AT18: no | AU18: 5 | AV18: NA | AW18: NA | AX18: NA | AY18: NA | AZ18: NA | BA18: NA | BB18: 128 | BC18: Trampa Ovas | BD18: 1 | BE18: 61 | BF18: Peruana | BG18: Ova | BH18: no | BI18: Octubre-Febrero | BJ18: 5 | BK18: Usa esteras con manta y sargazo/palmeras | BL18: 30-40 | BM18: 72 | BN18: 15 | BO18: 100-150 | BP18: 700-2000 | BQ18: Acopiador | BR18: 32-45 | BS18: no | BT18: NA | BU18: NA | BV18: NA | BW18: NA | BX18: NA | BY18: NA | BZ18: NA | CA18: NA | CB18: NA | CC18: NA | CD18: NA | CE18: NA | CF18: NA | CG18: NA | CH18: NA | CI18: no | CJ18: NA | CK18: NA | CL18: NA | CM18: NA | CN18: NA | CO18: NA | CP18: NA | CQ18: NA | CR18: NA | CS18: NA | CT18: NA | CU18: NA | CV18: Acopiador: Ana Candia. Fue un pescador sobreviviente de altura ya que suele salir solo a la ova de pez volador y en la ultima temporada 2024-2025 su motor se malogró en altamar y se perdió por 3 meses, apareciendo por las Islas Galápagos rescatado desde un helicóptero.
A19: CC-MARCONA-019 | B19: Cristel Cordero | C19: 45811 | D19: Roberto Mendoza Soriano | E19: 73458556 | F19: 20 | G19: 16 | H19: Marcona | I19: Marcona | J19: Marcona | K19: 34655 | L19: =DATEDIF(K19, DATE(2025,8,29), "Y") -> 30 | M19: M | N19: Casado/Conviviente | O19: Sin Instrucción | P19: si | Q19: no | R19: Patrón | S19: si | T19: APROBENTO | U19: si | V19: Buceo compresora | W19: mariscos, pulpo | X19: Colecta de algas | Y19: algas | Z19: NA | AA19: NA | AB19: no | AC19: NA | AD19: 4 | AE19: 3 | AF19: si | AG19: Ama de casa | AH19: no | AI19: NA | AJ19: si | AK19: NA | AL19: si | AM19: NA | AN19: 0 | AO19: NA | AP19: VALENTINA Y MIGUEL I | AQ19: CE-55929-BM | AR19: no | AS19: no | AT19: si | AU19: 6 | AV19: NA | AW19: NA | AX19: NA | AY19: NA | AZ19: NA | BA19: NA | BB19: 224 | BC19: Trampa Ovas | BD19: 3 | BE19: 30-45 | BF19: Peruana y Venezolana | BG19: Ova | BH19: no | BI19: Octubre-Febrero | BJ19: 4 | BK19: Usa mantas (20: 2x3.5 m) y sargazo/palmeras | BL19: 28 | BM19: 48-96 | BN19: 8 | BO19: 30-100 | BP19: 1000-1400 | BQ19: Acopiador | BR19: 35-40 | BS19: Espinel superficial | BT19: 4 | BU19: 30-45 | BV19: Peruana y Venezolana | BW19: Perico | BX19: pota | BY19: Diciembre-Febrero | BZ19: 4 | CA19: Linea madre: 500 m, #anzuelos/linea: 1, # anzuelos: 100, Calibre: NS | CB19: 15 | CC19: 3-4 | CD19: 6 | CE19: 20 | CF19: 500 | CG19: Comerciante | CH19: 15 | CI19: no | CJ19: NA | CK19: NA | CL19: NA | CM19: NA | CN19: NA | CO19: NA | CP19: NA | CQ19: NA | CR19: NA | CS19: NA | CT19: NA | CU19: NA | CV19: Menciona que hay muchas discrepancias entre los pescadores de altura relacionado a su pesca. El zargazo húmedo lo compran a S/. 500 la 1/2 TN a los que barretean zargazo con un fierro (barreta). En Marcona casi no hay acopiadores de perico. Menciona que el bonito con boliche va hasta las 50 mn.
A20: CC-MARCONA-020 | B20: Cristel Cordero | C20: 45814 | D20: Juan Asuero Humaní | E20: 22085259 | F20: 40 | G20: 10 | H20: Marcona | I20: Marcona | J20: Marcona | K20: 22306 | L20: =DATEDIF(K20, DATE(2025,8,29), "Y") -> 64 | M20: M | N20: Casado/Conviviente | O20: Secundaria | P20: si | Q20: si | R20: Armador, Patrón | S20: si | T20: APROMAR | U20: si | V20: Colecta de algas | W20: algas | X20: NA | Y20: NA | Z20: NA | AA20: NA | AB20: no | AC20: NA | AD20: 0 | AE20: 3 | AF20: si | AG20: Comerciante de pescado | AH20: si | AI20: Pareja (comerciante de pescado) | AJ20: no | AK20: Considera que está prohibido que las mujeres se embarquen | AL20: si | AM20: NA | AN20: 1 | AO20: si | AP20: RAYMUNDO | AQ20: TS-23279-BM | AR20: no | AS20: no | AT20: si | AU20: 4 | AV20: NA | AW20: NA | AX20: NA | AY20: NA | AZ20: NA | BA20: NA | BB20: 136 | BC20: Trampa Ovas | BD20: 3 | BE20: 30-64 | BF20: Peruana | BG20: Ova | BH20: no | BI20: Noviembre-Enero | BJ20: 6 | BK20: Usa esteras (10: 2.20 x 3 m) y sargazo | BL20: 15-20 | BM20: 72 | BN20: 4 | BO20: 100-200 | BP20: 500-700 | BQ20: Acopiador | BR20: 25-40 | BS20: Cortina superficial | BT20: 4 | BU20: 30-64 | BV20: Peruana | BW20: Bonito | BX20: no | BY20: Todo el año (cuota) | BZ20: 3-5/mes | CA20: #paños: 2, cocada: 3 3/4 pulgadas, malla 6x100 metros | CB20: 2-3 | CC20: 0.5-1 | CD20: 1 | CE20: 200 | CF20: 200 | CG20: Comerciante | CH20: 1-5 | CI20: no | CJ20: NA | CK20: NA | CL20: NA | CM20: NA | CN20: NA | CO20: NA | CP20: NA | CQ20: NA | CR20: NA | CS20: NA | CT20: NA | CU20: NA | CV20: Pesca bonito 8 meses al año aprox. (1 mes de veda y 2 meses de pesca), lleva redes boniteras cuando sale a la ova para aprovechar. Considera que la población de peces voladores se ha reducido, encontrándose más machos que hembras. Asimismo, el número de embarcaciones que van a la ova han aumentado. Recomienda que se cree una cuota de captura por embarcación para el volador.
A21: CC-MARCONA-021 | B21: Cristel Cordero | C21: 45814 | D21: Jorge Anchayhua | E21: 45773391 | F21: 18 | G21: 10 | H21: Marcona | I21: Marcona | J21: Marcona, San Andrés, Pucusana | K21: 32681 | L21: =DATEDIF(K21, DATE(2025,8,29), "Y") -> 36 | M21: M | N21: Casado/Conviviente | O21: Secundaria | P21: si | Q21: no | R21: Armador, Patrón | S21: si | T21: APROBENTO | U21: si | V21: Buceo compresora | W21: mariscos, pulpo, lenguado, congrio, pintadilla | X21: NA | Y21: NA | Z21: NA | AA21: NA | AB21: no | AC21: NA | AD21: 2 | AE21: 1 | AF21: si | AG21: Ama de casa | AH21: no | AI21: NA | AJ21: si | AK21: NA | AL21: si | AM21: NA | AN21: 0 | AO21: NA | AP21: MI SARITA | AQ21: PT-31218-BM | AR21: no | AS21: no | AT21: si | AU21: 4 | AV21: NA | AW21: NA | AX21: NA | AY21: NA | AZ21: NA | BA21: NA | BB21: 192 | BC21: Trampa Ovas | BD21: 4 | BE21: 25-40 | BF21: Peruana | BG21: Ova | BH21: no | BI21: Octubre-Febrero | BJ21: 4-5 | BK21: Usa esteras (10: 2x3.5 m) con manta (10: 2x6 m) y sargazo/palmeras/mangueras | BL21: 25 | BM21: 48-72 | BN21: 8-10 | BO21: 100-500 | BP21: 400-1000 | BQ21: Acopiador | BR21: 20-35 | BS21: Cortina superficial | BT21: 4 | BU21: 25-40 | BV21: Peruana | BW21: Bonito | BX21: no | BY21: Enero-Febrero | BZ21: 2 | CA21: #paños: 10, cocada: 3.5 o 4 pulgadas, malla 16x30 metros | CB21: 2-3 | CC21: 1-2 | CD21: 3-4 | CE21: 200 | CF21: 500-1500 | CG21: Comerciante | CH21: 1.5-4 | CI21: no | CJ21: NA | CK21: NA | CL21: NA | CM21: NA | CN21: NA | CO21: NA | CP21: NA | CQ21: NA | CR21: NA | CS21: NA | CT21: NA | CU21: NA | CV21: Lleva redes boniteras cuando sale a la ova para aprovechar.
A22: FV-MARCONA-001 | B22: Florinda Ventura | C22: 45775 | D22: Jorge Calvera Rojas | E22: 22087712 | F22: 40 | G22: 40 | H22: Marcona | I22: Marcona | J22: Marcona, Chala, San Andrés | K22: 21612 | L22: =DATEDIF(K22, DATE(2025,8,29), "Y") -> 66 | M22: M | N22: Casado/Conviviente | O22: Secundaria | P22: si | Q22: si | R22: Armador | S22: si | T22: ASMASPEMAR | U22: si | V22: Colecta de algas | W22: algas | X22: NA | Y22: NA | Z22: NA | AA22: NA | AB22: no | AC22: NA | AD22: 1 | AE22: 1 | AF22: si | AG22: Ama de casa | AH22: no | AI22: NA | AJ22: si | AK22: NA | AL22: si | AM22: NA | AN22: 2 | AO22: si | AP22: VIRGENCITA DE CHAPI | AQ22: SN-52701-BM | AR22: no | AS22: no | AT22: si | AU22: 6 | AV22: VIRGENCITA DE YAUCA | AW22: NS | AX22: no | AY22: no | AZ22: si | BA22: 3 | BB22: 140 | BC22: Trampa Ovas | BD22: 3 | BE22: 25-40 | BF22: Peruana | BG22: Ova | BH22: no | BI22: Noviembre-Enero | BJ22: 4 | BK22: Usa esteras con manta y sargazo/palmeras/manguera | BL22: 30 | BM22: 72-96 | BN22: 4-6 | BO22: 100-150 | BP22: 600-800 | BQ22: Acopiador | BR22: 25-42 | BS22: Pinta potera | BT22: 4 | BU22: 25-40 | BV22: Peruana | BW22: Pota | BX22: no | BY22: Todo el año (cuota) | BZ22: 2/mes | CA22: NA | CB22: 4 | CC22: NA | CD22: NA | CE22: NA | CF22: 4000-5000 | CG22: Acopiador | CH22: 3.5 | CI22: Cortina superficie | CJ22: Bonito | CK22: no | CL22: Todo el año (cuota) | CM22: 4 | CN22: #paños: 7, cocada: 4 pulgadas, malla 10x82 m | CO22: 2 | CP22: 1-2 | CQ22: 1-2 | CR22: 1000 | CS22: 2000-4000 | CT22: Acopiador | CU22: 1-5 | CV22: Aprovecha su salida a la ova para pescar perico con espinel de superficie y usa de carnada pez volador vivo.
A23: FV-MARCONA-002 | B23: Florinda Ventura | C23: 45775 | D23: Walter De la Cruz Peña | E23: 22299143 | F23: 32 | G23: 25 | H23: Marcona | I23: Marcona | J23: Marcona | K23: 27147 | L23: =DATEDIF(K23, DATE(2025,8,29), "Y") -> 51 | M23: M | N23: Casado/Conviviente | O23: Secundaria | P23: si | Q23: si | R23: Armador, Patrón | S23: si | T23: APROBENTO | U23: si | V23: Buceo compresora | W23: mariscos | X23: NA | Y23: NA | Z23: NA | AA23: NA | AB23: no | AC23: NA | AD23: 6 | AE23: 5 | AF23: si | AG23: Ama de casa | AH23: no | AI23: no | AJ23: no | AK23: A las mujeres no les gusta embarcarse a la altura | AL23: si | AM23: NA | AN23: 1 | AO23: si | AP23: MI PAPA NICO | AQ23: SN-55592-BM | AR23: no | AS23: no | AT23: si | AU23: 6 | AV23: NA | AW23: NA | AX23: NA | AY23: NA | AZ23: NA | BA23: NA | BB23: 140 | BC23: Trampa Ovas | BD23: 3 | BE23: 45-55 | BF23: Peruana | BG23: Ova | BH23: no | BI23: Octubre-Enero | BJ23: 8-10 | BK23: Usa esteras y sargazo | BL23: 15-20 | BM23: 72-96 | BN23: 3-4 | BO23: 100 | BP23: 500 | BQ23: Acopiador | BR23: 30 | BS23: no | BT23: NA | BU23: NA | BV23: NA | BW23: NA | BX23: NA | BY23: NA | BZ23: NA | CA23: NA | CB23: NA | CC23: NA | CD23: NA | CE23: NA | CF23: NA | CG23: NA | CH23: NA | CI23: no | CJ23: NA | CK23: NA | CL23: NA | CM23: NA | CN23: NA | CO23: NA | CP23: NA | CQ23: NA | CR23: NA | CS23: NA | CT23: NA | CU23: NA | CV23: Indica que en APROBENTO son 40 socios embarcados.
A24: FV-MARCONA-003 | B24: Florinda Ventura | C24: 45775 | D24: Aldo Ramirez López | E24: 03474634 | F24: 35 | G24: 25 | H24: Marcona | I24: Marcona | J24: Marcona | K24: 25493 | L24: =DATEDIF(K24, DATE(2025,8,29), "Y") -> 55 | M24: M | N24: Soltero | O24: Primaria | P24: si | Q24: si | R24: Tripulación | S24: si | T24: Asociación de Armadores y Maricultores de la Bahía de San Juan de Marcona | U24: si | V24: Buceo compresora | W24: mariscos, pulpo | X24: NA | Y24: NA | Z24: NA | AA24: NA | AB24: si | AC24: Varar botes | AD24: 1 | AE24: 3 | AF24: no | AG24: NA | AH24: no | AI24: NA | AJ24: si | AK24: NA | AL24: si | AM24: NA | AN24: 0 | AO24: NA | AP24: LOS TIPIS | AQ24: SN-03572-BM | AR24: no | AS24: no | AT24: si | AU24: 8 | AV24: NA | AW24: NA | AX24: NA | AY24: NA | AZ24: NA | BA24: NA | BB24: 200 | BC24: Trampa Ovas | BD24: 3 | BE24: 30-50 | BF24: Peruana | BG24: Ova | BH24: no | BI24: Octubre-Enero | BJ24: 6 | BK24: Usa esteras con manta y sargazo/palmeras | BL24: 15-20 | BM24: 48-72 | BN24: 3 | BO24: 150 | BP24: 600 | BQ24: Acopiador | BR24: 25-40 | BS24: Cortina superficial | BT24: 4 | BU24: 30-50 | BV24: Peruana | BW24: Bonito | BX24: no | BY24: Noviembre-Febrero | BZ24: 6 | CA24: #paños: 7, cocada: 4 pulgadas, malla 7x64 m | CB24: 15-20 | CC24: 0.5-1 | CD24: 2 | CE24: 1000 | CF24: 2000 | CG24: Comerciante | CH24: 4-6 | CI24: no | CJ24: NA | CK24: NA | CL24: NA | CM24: NA | CN24: NA | CO24: NA | CP24: NA | CQ24: NA | CR24: NA | CS24: NA | CT24: NA | CU24: NA | CV24: Aprovecha su salida a la ova para pescar bonito con cortina de superficie.
A25: FV-MARCONA-004 | B25: Florinda Ventura | C25: 45776 | D25: Pedro Roman Levano | E25: 21530211 | F25: 26 | G25: 26 | H25: Marcona | I25: Marcona | J25: Marcona | K25: 24810 | L25: =DATEDIF(K25, DATE(2025,8,29), "Y") -> 57 | M25: M | N25: Casado/Conviviente | O25: Secundaria | P25: si | Q25: si | R25: Patrón | S25: si | T25: APROBENTO | U25: si | V25: Buceo compresora | W25: mariscos, pulpo | X25: NA | Y25: NA | Z25: NA | AA25: NA | AB25: si | AC25: Presidente de OSPA | AD25: 3 | AE25: 3 | AF25: si | AG25: Acopiadora | AH25: si | AI25: Pareja (acopiadora) | AJ25: si | AK25: NA | AL25: si | AM25: NA | AN25: 0 | AO25: NA | AP25: PAPILON IV | AQ25: SN-29038-BM | AR25: no | AS25: no | AT25: si | AU25: 3 | AV25: NA | AW25: NA | AX25: NA | AY25: NA | AZ25: NA | BA25: NA | BB25: 192 | BC25: Trampa Ovas | BD25: 3 | BE25: 30-55 | BF25: Peruana | BG25: Ova | BH25: no | BI25: Octubre-Febrero | BJ25: 6 | BK25: Usa esteras con manta y sargazo/palmera | BL25: 20-30 | BM25: 48-72 | BN25: 6-8 | BO25: 150 | BP25: 700 | BQ25: Acopiador | BR25: 25 | BS25: no | BT25: NA | BU25: NA | BV25: NA | BW25: NA | BX25: NA | BY25: NA | BZ25: NA | CA25: NA | CB25: NA | CC25: NA | CD25: NA | CE25: NA | CF25: NA | CG25: NA | CH25: NA | CI25: no | CJ25: NA | CK25: NA | CL25: NA | CM25: NA | CN25: NA | CO25: NA | CP25: NA | CQ25: NA | CR25: NA | CS25: NA | CT25: NA | CU25: NA | CV25: Aprovecha su salida a la ova para pescar perico con espinel de superficie usa de carnada pez volador vivo, pero es solo para consumo a bordo.
A26: HM-MARCONA-001 | B26: Heidy Mejia | C26: 45776 | D26: Alberto Palomino | E26: 08009113 | F26: 30 | G26: 30 | H26: Marcona | I26: Marcona | J26: Marcona, Pucusana, Atico, San Andres | K26: 28261 | L26: =DATEDIF(K26, DATE(2025,8,29), "Y") -> 48 | M26: M | N26: Casado/Conviviente | O26: Primaria | P26: si | Q26: si | R26: Armador, Patrón | S26: si | T26: NS | U26: no | V26: NA | W26: NA | X26: NA | Y26: NA | Z26: NA | AA26: NA | AB26: si | AC26: Mototaxista | AD26: 3 | AE26: 3 | AF26: si | AG26: Fileteadora | AH26: si | AI26: Pareja (fileteadora) | AJ26: si | AK26: NA | AL26: no | AM26: Depende del trabajo (esfuerzo físico) que haga | AN26: 1 | AO26: si | AP26: MI CHUELON | AQ26: NS | AR26: no | AS26: no | AT26: si | AU26: 5 | AV26: NA | AW26: NA | AX26: NA | AY26: NA | AZ26: NA | BA26: NA | BB26: 160-240 | BC26: Trampa Ovas | BD26: 4 | BE26: 24-40 | BF26: Peruana | BG26: Ova | BH26: no | BI26: Septiembre-Enero | BJ26: 4 | BK26: Usa esteras con manta y sargazo/palmeras | BL26: 30 | BM26: 72 | BN26: 8-9 | BO26: 50-100 | BP26: 800-1000 | BQ26: Acopiador | BR26: 40 | BS26: Pinta potera | BT26: 4 | BU26: 24-40 | BV26: Peruana | BW26: Pota | BX26: no | BY26: Febrero-Junio | BZ26: 15 | CA26: NA | CB26: 3 | CC26: NA | CD26: NA | CE26: NA | CF26: 1000-5000 | CG26: Acopiador | CH26: 3-4 | CI26: Espinel superficial | CJ26: Perico | CK26: pota, pez volador | CL26: Octubre-Diciembre | CM26: 6 | CN26: 700 anzuelos | CO26: 10 | CP26: 3 | CQ26: 10-15 | CR26: 300 | CS26: 5000 | CT26: Acopiador | CU26: 10
A27: HM-MARCONA-002 | B27: Heidy Mejia | C27: 45776 | D27: Alex Tipamana Avendaño | E27: 42168056 | F27: 20 | G27: 20 | H27: Marcona | I27: Marcona | J27: Marcona, San Andrés, El Chaco | K27: 30018 | L27: =DATEDIF(K27, DATE(2025,8,29), "Y") -> 43 | M27: M | N27: Soltero | O27: Secundaria | P27: si | Q27: si | R27: Armador | S27: si | T27: APROBENTO | U27: si | V27: Colecta de algas | W27: algas | X27: NA | Y27: NA | Z27: NA | AA27: NA | AB27: si | AC27: Pintor | AD27: 2 | AE27: 0 | AF27: si | AG27: Ama de casa | AH27: no | AI27: NA | AJ27: no | AK27: NS | AL27: si | AM27: NA | AN27: 1 | AO27: si | AP27: ANDERSON | AQ27: PS-01651-BM | AR27: no | AS27: no | AT27: si | AU27: 4 | AV27: NA | AW27: NA | AX27: NA | AY27: NA | AZ27: NA | BA27: NA | BB27: 120-240 | BC27: Trampa Ovas | BD27: 4 | BE27: 30-50 | BF27: Peruana | BG27: Ova | BH27: no | BI27: Octubre-Marzo | BJ27: 3-5 | BK27: Usa esteras con manta y sargazo/palmeras/manguera | BL27: 40-60 | BM27: 72 | BN27: 8-10 | BO27: 50 | BP27: 300-1000 | BQ27: Acopiador | BR27: 20-35 | BS27: Pinta potera | BT27: 4 | BU27: 30-50 | BV27: Peruana | BW27: Pota | BX27: no | BY27: Todo el año (cuota) | BZ27: 3-4/mes | CA27: NA | CB27: 7 | CC27: NA | CD27: NA | CE27: NA | CF27: 2000-4000 | CG27: Acopiador | CH27: 3-4 | CI27: no | CJ27: NA | CK27: NA | CL27: NA | CM27: NA | CN27: NA | CO27: NA | CP27: NA | CQ27: NA | CR27: NA | CS27: NA | CT27: NA | CU27: NA | CV27: Acopiador de ova: Ana Candia, acopiador de pota: Efrain
A28: HM-MARCONA-003 | B28: Heidy Mejia | C28: 45776 | D28: Jorge Álvarez Ramirez | E28: 40242680 | F28: 30 | G28: 30 | H28: Marcona | I28: Marcona | J28: Marcona, Chala | K28: 28867 | L28: =DATEDIF(K28, DATE(2025,8,29), "Y") -> 46 | M28: M | N28: Casado/Conviviente | O28: Secundaria | P28: si | Q28: si | R28: Armador, Patrón | S28: si | T28: APROBENTO | U28: si | V28: Buceo compresora | W28: mariscos | X28: Colecta de algas | Y28: algas | Z28: NA | AA28: NA | AB28: no | AC28: NA | AD28: 3 | AE28: 2 | AF28: si | AG28: Ama de casa | AH28: no | AI28: NA | AJ28: si | AK28: NA | AL28: si | AM28: NA | AN28: 1 | AO28: si | AP28: DON GILBERTO I | AQ28: SN-20132-BM | AR28: no | AS28: no | AT28: si | AU28: 3 | AV28: NA | AW28: NA | AX28: NA | AY28: NA | AZ28: NA | BA28: NA | BB28: 120 | BC28: Trampa Ovas | BD28: 4 | BE28: 20-50 | BF28: Peruana | BG28: Ova | BH28: no | BI28: Octubre-Marzo | BJ28: 4-5 | BK28: Usa esteras con manta y sargazo/palmera | BL28: 15-40 | BM28: 48-72 | BN28: 8-10 | BO28: 100 | BP28: 1000-1500 | BQ28: Acopiador | BR28: 20-35 | BS28: Cortina superficial | BT28: 4 | BU28: 20-50 | BV28: Peruana | BW28: Bonito | BX28: no | BY28: Todo el año (cuota) | BZ28: 3-4/mes | CA28: #paños: 6, cocada: 4 pulgadas, malla 36x220 metros | CB28: 7 | CC28: 2-3 | CD28: 10-15 | CE28: 50-80 | CF28: 1000 | CG28: Acopiador | CH28: 0.50-3 | CI28: Pinta potera | CJ28: Pota | CK28: no | CL28: Octubre-Marzo | CM28: Todo el año (cuota) | CN28: NA | CO28: 7 | CP28: NA | CQ28: NA | CR28: NA | CS28: 3000 | CT28: Acopiador | CU28: 3 | CV28: Acopiador de ova: Ana Candia y Efrain, acopiador de pota y bonito: Efrain
A29: HM-MARCONA-004 | B29: Heidy Mejia | C29: 45777 | D29: Martin Velez Paz | E29: 22084954 | F29: 50 | G29: 42 | H29: Marcona | I29: Marcona | J29: Marcona | K29: 23200 | L29: =DATEDIF(K29, DATE(2025,8,29), "Y") -> 62 | M29: M | N29: Casado/Conviviente | O29: Secundaria | P29: si | Q29: si | R29: Armador, Patrón | S29: si | T29: APROMAR | U29: si | V29: Buceo compresora | W29: mariscos | X29: Colecta de algas | Y29: algas | Z29: NA | AA29: NA | AB29: no | AC29: NA | AD29: 1 | AE29: 3 | AF29: si | AG29: Ama de casa | AH29: no | AI29: NA | AJ29: si | AK29: NA | AL29: si | AM29: NA | AN29: 1 | AO29: si | AP29: LOS NIKITAS | AQ29: PT-57021-BM | AR29: no | AS29: si | AT29: si | AU29: 6 | AV29: NA | AW29: NA | AX29: NA | AY29: NA | AZ29: NA | BA29: NA | BB29: 100-120 | BC29: Trampa Ovas | BD29: 3 | BE29: 40-60 | BF29: Peruana | BG29: Ova | BH29: no | BI29: Octubre-Febrero | BJ29: 4-5 | BK29: Usa esteras con manta y sargazo/palmera | BL29: 15-25 | BM29: 48-72 | BN29: 6-12 | BO29: 15-700 | BP29: 500-2000 | BQ29: Acopiador | BR29: 30-35 | BS29: Pinta potera | BT29: 4 | BU29: 40-60 | BV29: Peruana | BW29: Pota | BX29: no | BY29: Todo el año (cuota) | BZ29: 3-5/mes | CA29: NA | CB29: 7 | CC29: NA | CD29: NA | CE29: NA | CF29: 3000 | CG29: Acopiador | CH29: 4-6 | CI29: no | CJ29: NA | CK29: NA | CL29: NA | CM29: NA | CN29: NA | CO29: NA | CP29: NA | CQ29: NA | CR29: NA | CS29: NA | CT29: NA | CU29: NA | CV29: Acopiador de ova: Ana Cesar Rocha, acopiador de pota: Efrain
A30: HM-MARCONA-005 | B30: Heidy Mejia | C30: 45777 | D30: Luis Jimenez Lupe | E30: 22287705 | F30: 16 | G30: 8 | H30: Marcona | I30: Marcona | J30: Marcona, Chala, San Andrés, Atico | K30: 25487 | L30: =DATEDIF(K30, DATE(2025,8,29), "Y") -> 55 | M30: M | N30: Casado/Conviviente | O30: Primaria | P30: si | Q30: si | R30: Armador | S30: si | T30: ASOCIACION DE BOLICHITOS ARTESANALES DE SAN JUAN DE MARCONA JUAN MARCIAL VALENZUELA | U30: si | V30: Buceo compresora | W30: mariscos | X30: NA | Y30: NA | Z30: NA | AA30: NA | AB30: no | AC30: NA | AD30: 5 | AE30: 4 | AF30: si | AG30: Ama de casa | AH30: no | AI30: NA | AJ30: no | AK30: NS | AL30: no | AM30: NS | AN30: 1 | AO30: si | AP30: FABIANO Y ESTEFANO I | AQ30: SN-53991-BM | AR30: no | AS30: no | AT30: si | AU30: 6 | AV30: NA | AW30: NA | AX30: NA | AY30: NA | AZ30: NA | BA30: NA | BB30: 34-42 | BC30: Cerco | BD30: 7 | BE30: 30-56 | BF30: Peruana | BG30: Bonito, Caballa, Jurel | BH30: no | BI30: Diciembre-Abril | BJ30: 2/mes | BK30: Cerco no mecanizado, cocada: 2.5 pulgadas | BL30: 10 | BM30: 1 | BN30: 1-5 | BO30: 500-1000 | BP30: 3000 | BQ30: Acopiador | BR30: Bonito y Caballa: S/. 2, Jurel: S/. 3 | BS30: Trampa ovas | BT30: 3 | BU30: 30-56 | BV30: Peruana | BW30: Ova | BX30: no | BY30: Noviembre-Marzo | BZ30: 4 | CA30: Usa esteras con manta y sargazo/palmeras/manguera | CB30: 20 | CC30: 24-48 | CD30: 4 | CE30: 100 | CF30: 500-600 | CG30: Acopiador | CH30: 30 | CI30: no | CJ30: NA | CK30: NA | CL30: NA | CM30: NA | CN30: NA | CO30: NA | CP30: NA | CQ30: NA | CR30: NA | CS30: NA | CT30: NA | CU30: NA
A31: HM-MARCONA-006 | B31: Heidy Mejia | C31: 45777 | D31: Cristopher Lecarnaque Paiva | E31: 46947012 | F31: 18 | G31: 16 | H31: Marcona | I31: Marcona | J31: Marcona | K31: 33349 | L31: =DATEDIF(K31, DATE(2025,8,29), "Y") -> 34 | M31: M | N31: Casado/Conviviente | O31: Secundaria | P31: si | Q31: si | R31: Patrón | S31: si | T31: APROBENTO | U31: si | V31: Buceo compresora | W31: cabrilla, corvina | X31: NA | Y31: NA | Z31: NA | AA31: NA | AB31: no | AC31: NA | AD31: 3 | AE31: 2 | AF31: si | AG31: Ama de casa | AH31: no | AI31: NA | AJ31: si | AK31: NA | AL31: no | AM31: Hacen menos trabajo (esfuerzo físico) que los hombres. | AN31: 1 | AO31: si | AP31: CORAZON VALIENTE | AQ31: NS | AR31: no | AS31: no | AT31: no | AU31: 4 | AV31: NA | AW31: NA | AX31: NA | AY31: NA | AZ31: NA | BA31: NA | BB31: 80-204 | BC31: Trampa Ovas | BD31: 3 | BE31: 20-50 | BF31: Peruana | BG31: Ova | BH31: no | BI31: Noviembre-Febrero | BJ31: 5-6 | BK31: Usa manta y sargazo/palmera | BL31: 15-20 | BM31: 24-48 | BN31: 5 | BO31: 50-300 | BP31: 600-800 | BQ31: Acopiador | BR31: 30-42 | BS31: Pinta potera | BT31: 4 | BU31: 20-50 | BV31: Peruana | BW31: Pota | BX31: no | BY31: Enero-Mayo | BZ31: 20 | CA31: NA | CB31: 2-3 | CC31: NA | CD31: NA | CE31: NA | CF31: 3000-4500 | CG31: Acopiador | CH31: 1.5-5.5 | CI31: Cortina superficie | CJ31: Bonito | CK31: no | CL31: Noviembre-Febrero | CN31: # paños: 5, cocada: 4 pulgadas | CO31: 3-4 | CP31: NA | CQ31: NA | CR31: NA | CS31: 2000-3000 | CT31: Acopiador | CU31: 2 | CV31: Acopiador de pota y bonito: Efrain
A32: HM-MARCONA-007 | B32: Heidy Mejia | C32: 45777 | D32: Jorge Antezana Villegas | E32: 45954224 | F32: 20 | G32: 20 | H32: Marcona | I32: Marcona | J32: Marcona | K32: 29194 | L32: =DATEDIF(K32, DATE(2025,8,29), "Y") -> 45 | M32: M | N32: Soltero | O32: Secundaria | P32: si | Q32: si | R32: Patrón | S32: no | T32: NA | U32: si | V32: Colecta de algas | W32: algas | X32: NA | Y32: NA | Z32: NA | AA32: NA | AB32: si | AC32: Construcción civil | AD32: 2 | AE32: 2 | AF32: no | AG32: NA | AH32: no | AI32: NA | AJ32: si | AK32: NA | AL32: no | AM32: No, por el machismo de la mujer en la pesca se le paga menos | AN32: 0 | AO32: NA | AP32: JAIR ARAEL | AQ32: NS | AR32: no | AS32: no | AT32: si | AU32: 10 | AV32: NA | AW32: NA | AX32: NA | AY32: NA | AZ32: NA | BA32: NA | BB32: 128-192 | BC32: Trampa Ovas | BD32: 3 | BE32: 20-35 | BF32: Peruana | BG32: Ova | BH32: no | BI32: Octubre-Marzo | BJ32: 4-5 | BK32: Usa esteras con manta y sargazo/palmeras/manguera | BL32: 20-30 | BM32: 72 | BN32: 3-4 | BO32: 300-500 | BP32: 1000-2000 | BQ32: Acopiador | BR32: 22-45 | BS32: Cerco | BT32: 6 | BU32: 20-35 | BV32: Peruana | BW32: Bonito | BX32: no | BY32: Todo el año (cuota) | BZ32: 7-8 | CA32: Cerco mecanizado, cocada: 4 pulgadas | CB32: 2-4 | CC32: 1 | CD32: 2-3 | CE32: 5000-7000 | CF32: 15000 | CG32: Acopiador | CH32: 4-5 | CI32: Espinel superficial | CJ32: Perico | CK32: pota, pez volador | CL32: Octubre-Marzo | CM32: 4-5 | CN32: Linea madre: 150 m, Calibre: 4 | CO32: 20-30 | CP32: 3-4 | CQ32: 4 | CR32: 300-500 | CS32: 1000-2000 | CT32: Acopiador | CU32: 15-20 | CV32: Acopiador de ova: Ana Cesar Rocha, acopiador de bonito y perico: Efrain
A33: HM-MARCONA-008 | B33: Heidy Mejia | C33: 45777 | D33: Mackensi Contreras Ramos | E33: 43547174 | F33: 15 | G33: 15 | H33: Marcona | I33: Marcona | J33: Marcona | K33: 31115 | L33: =DATEDIF(K33, DATE(2025,8,29), "Y") -> 40 | M33: M | N33: Casado/Conviviente | O33: Superior Técnico | P33: si | Q33: si | R33: Armador, Patrón | S33: si | T33: APROBENTO | U33: si | V33: Buceo compresora | W33: mariscos | X33: NA | Y33: NA | Z33: NA | AA33: NA | AB33: no | AC33: NA | AD33: 2 | AE33: 2 | AF33: si | AG33: Administradora | AH33: no | AI33: NA | AJ33: si | AK33: NA | AL33: si | AM33: NA | AN33: 1 | AO33: si | AP33: TERESA | AQ33: SN-52598-BM | AR33: no | AS33: no | AT33: si | AU33: 5 | AV33: NA | AW33: NA | AX33: NA | AY33: NA | AZ33: NA | BA33: NA | BB33: 238 | BC33: Trampa Ovas | BD33: 4 | BE33: 30-40 | BF33: Peruana | BG33: Ova | BH33: no | BI33: Octubre-Febrero | BJ33: 3-4 | BK33: Usa manta y sargazo/palmera/manguera | BL33: 25 | BM33: 72 | BN33: 8 | BO33: 200 | BP33: 1500 | BQ33: Acopiador | BR33: 23-25 | BS33: Pinta potera | BT33: 4 | BU33: 30-40 | BV33: Peruana | BW33: Pota | BX33: no | BY33: Todo el año (cuota) | BZ33: 4-6 | CA33: NA | CB33: 3 | CC33: NA | CD33: NA | CE33: NA | CF33: 3000 | CG33: Acopiador | CH33: 1.5-4.5 | CI33: Cortina de superficie | CJ33: Bonito | CK33: no | CL33: Febrero-Julio | CM33: 3-5/mes | CN33: #paños: 5, cocada: 4 pulgadas, malla 4x100 m | CO33: 5 | CP33: 1-2 | CQ33: 3 | CR33: 500 | CS33: 1500 | CT33: Acopiador | CU33: 4 | CV33: Acopiador de ova: Ana Candia, acopiador de pota y bonito: Efrain
A34: NV-MARCONA-001 | B34: Nicol Vásquez | C34: 45814 | D34: Edgar Polanco García | E34: 80318890 | F34: 29 | G34: 20 | H34: Marcona | I34: Marcona | J34: Marcona | K34: 28858 | L34: =DATEDIF(K34, DATE(2025,8,29), "Y") -> 46 | M34: M | N34: Casado/Conviviente | O34: Superior Técnico | P34: si | Q34: no | R34: Patrón | S34: si | T34: APROBENTO | U34: no | V34: NA | W34: NA | X34: NA | Y34: NA | Z34: NA | AA34: NA | AB34: no | AC34: NA | AD34: 4 | AE34: 3 | AF34: si | AG34: Comerciante | AH34: no | AI34: NA | AJ34: si | AK34: NA | AL34: si | AM34: NA | AN34: 0 | AO34: NA | AP34: VIRGEN DE LAS NIEVES III | AQ34: SN-52599-BM | AR34: no | AS34: no | AT34: si | AU34: 8 | AV34: NA | AW34: NA | AX34: NA | AY34: NA | AZ34: NA | BA34: NA | BB34: 240 | BC34: Trampa Ovas | BD34: 4 | BE34: 45-50 | BF34: Peruana | BG34: Ova | BH34: no | BI34: Octubre-Diciembre | BJ34: 3 | BK34: Usa manta y sargazo/palmera | BL34: 30 | BM34: 24-72 | BN34: 7-8 | BO34: 150-500 | BP34: 1000-1500 | BQ34: Acopiador | BR34: 32-35 | BS34: Pinta potera | BT34: 4 | BU34: 45-50 | BV34: Peruana | BW34: Pota | BX34: no | BY34: Todo el año (cuota) | BZ34: 2-3/mes | CA34: NA | CB34: 4 | CC34: NA | CD34: NA | CE34: NA | CF34: 2000-3500 | CG34: Acopiador | CH34: 2-3 | CI34: Cortina superficie | CJ34: Bonito | CK34: no | CL34: Noviembre-Marzo | CM34: 4-5 | CN34: #paños: 8, cocada: 4 pulgadas | CO34: 2-3 | CP34: 1-2 | CQ34: 1-4 | CR34: 1000-4000 | CS34: 3000-4000 | CT34: Acopiador | CU34: 2

Sheet Andres
A1: Encuesta | B1: Nombre_Encuestador | C1: Fecha_Encuesta | D1: Nombre_Pescador | E1: DNI | F1: Años_Pesca | G1: Años_Altura | H1: Distrito_Vivienda | I1: Puerto_Zarpe | J1: Puerto_Arribo | K1: Fecha_Nacimiento | L1: Edad | M1: Sexo | N1: Estado_Civil | O1: Grado_Instruccion | P1: Alfabeto | Q1: Seguro_Salud | R1: Rol_Pescador | S1: OSPA | T1: Nombre_OSPA | U1: Otra_Pesca | V1: Arte_Costera1 | W1: Rec_Costero1 | X1: Arte_Costera2 | Y1: Rec_Costero2 | Z1: Arte_Costera3 | AA1: Rec_Costero3 | AB1: Alterna_Pesca | AC1: Actividad_Alterna | AD1: Personas_Dependientes | AE1: Numero_hijos | AF1: Pareja | AG1: Actividades_Pareja | AH1: FamiliaDirecta_Pesca | AI1: Rol_Familiares | AJ1: Genero_Opotunidades | AK1: GenOpor_No | AL1: Genero_Pago | AM1: GenPago_No | AN1: Num_Embarcaciones | AO1: Embarcacion_Propia | AP1: Nombre1_EmbarcacionAltura | AQ1: Matricula_1 | AR1: SISESAT_1 | AS1: Radiobaliza_1 | AT1: PTH_1 | AU1: TN_Bodega_1 | AV1: Nombre2_EmbarcacionAltura | AW1: Matricula_2 | AX1: SISESAT_2 | AY1: Radiobaliza_2 | AZ1: PTH_2 | BA1: TN_Bodega_2 | BB1: Galones_Combustible | BC1: Arte_1 | BD1: Num_Tripulantes1 | BE1: Edades_Tripulantes1 | BF1: Nacionalidad_Trip1 | BG1: Recurso_1 | BH1: Carnada1 | BI1: Temporada1 | BJ1: Viajes_Temporada1 | BK1: Detalles_Arte1 | BL1: Dias_Faena1 | BM1: Horas_Efectivas1 | BN1: Lances_Faena1 | BO1: Kg_Lance1 | BP1: Kg_Faena1 | BQ1: Venta_Recurso1 | BR1: Precio_Kg1 | BS1: Arte_2 | BT1: Num_Tripulantes2 | BU1: Edades_Tripulantes2 | BV1: Nacionalidad_Trip2 | BW1: Recurso_2 | BX1: Carnada2 | BY1: Temporada2 | BZ1: Viajes_Temporada2 | CA1: Detalles_Arte2 | CB1: Dias_Faena2 | CC1: Horas_Efectivas2 | CD1: Lances_Faena2 | CE1: Kg_Lance2 | CF1: Kg_Faena2 | CG1: Venta_Recurso2 | CH1: Precio_Kg2 | CI1: Arte_3 | CJ1: Recurso_3 | CK1: Carnada3 | CL1: Temporada3 | CM1: Viajes_Temporada3 | CN1: Detalles_Arte3 | CO1: Dias_Faena3 | CP1: Horas_Efectivas3 | CQ1: Lances_Faena3 | CR1: Captura_Lance3 | CS1: Captura_Faena3 | CT1: Venta_Recurso3 | CU1: Precio_Kg3 | CV1: Observaciones
A2: CC-SAN ANDRES-001 | B2: Cristel Cordero | C2: 45758 | D2: Juan de Dios Magan Arroyo | E2: 25453400 | F2: 20 | G2: 10 | H2: San Andrés | I2: San Andrés | J2: San Andrés, Marcona, Chala, Lomas | K2: 23182 | L2: =DATEDIF(K2, DATE(2025,8,29), "Y") -> 62 | M2: M | N2: Casado/Conviviente | O2: Secundaria | P2: si | Q2: si | R2: Armador, Patrón | S2: si | T2: ASPADSA | U2: no | V2: NA | W2: NA | X2: NA | Y2: NA | Z2: NA | AA2: NA | AB2: si | AC2: Mecánico | AD2: 2 | AE2: 2 | AF2: si | AG2: Pequeño comercio (tienda en casa) y Ama de casa | AH2: si | AI2: 1 hijo (tripulante) | AJ2: si | AK2: NA | AL2: si | AM2: NA | AN2: 2 | AO2: si | AP2: FISHERMAN II | AQ2: PS-17886-BM | AR2: no | AS2: si | AT2: no | AU2: 5 | AV2: NA | AW2: NA | AX2: NA | AY2: NA | AZ2: NA | BA2: NA | BB2: 220 | BC2: Trampa Ovas | BD2: 3 | BE2: 35-60 | BF2: Peruana | BG2: Ova | BH2: no | BI2: Octubre-Marzo | BJ2: 4-5 | BK2: Usa solo manta | BL2: 30 | BM2: 48-72 | BN2: 12-15 | BO2: 50-250 | BP2: 600-1000 | BQ2: Acopiador | BR2: 32-44 | BS2: Espinel superficial | BT2: 7 | BU2: 35-60 | BV2: Peruana | BW2: Perico | BX2: Pota, Pez Volador | BY2: Enero-Marzo | BZ2: 4-5 | CA2: Linea madre: 3218 m, #anzuelos/linea: 1, # anzuelos: 25-40, Calibre: 4 | CB2: 30 | CC2: 2 | CD2: 1-2 | CE2: 200 | CF2: 500 | CG2: Comerciante | CH2: 5 | CI2: Palangre | CJ2: Bacalao | CK2: anchoveta, jurel, caballa, pota | CL2: Cuota anual | CM2: 10-12 | CN2: Linea madre: 27359 m, 2 lineas, #anzuelos/linea: 800-1000, Calibre: 4 | CO2: 15-20 | CP2: 8 | CQ2: 15-30 | CR2: 360-400 | CS2: 2500-3000 | CT2: Trato con el armador | CU2: 4 | CV2: Él es armador y patrón en la embarcación de ovas y perico. Precio (kg) de ova con ojo: 5-6 soles, representa el 1% de su pesca total. En la embarcación de bacalao es tripulante y se pesca a 1500 m de profundidad.Precio de bacalao es de 4000 soles la TN. Cambio climático provoca más vientos, cambios en las corrientes, y cambios bruscos de temperatura.
A3: CC-SAN ANDRES-002 | B3: Cristel Cordero | C3: 34504 | D3: Anderson Jayo Villanueva | E3: 76561618 | F3: 9 | G3: 9 | H3: San Andrés | I3: San Andrés | J3: San Andrés | K3: 34504 | L3: =DATEDIF(K3, DATE(2025,8,29), "Y") -> 31 | M3: M | N3: Soltero | O3: Superior Técnico | P3: si | Q3: si | R3: Tripulación | S3: si | T3: AFREMARPA | U3: si | V3: Buceo compresora | W3: mariscos | X3: Pinta | Y3: bonito | Z3: NA | AA3: NA | AB3: no | AC3: NA | AD3: 0 | AE3: 0 | AF3: no | AG3: NA | AH3: NA | AI3: NA | AJ3: si | AK3: NA | AL3: NS | AM3: NA | AN3: 0 | AO3: no | AP3: HEINZEN Y XIOMARA | AQ3: TA-60305-BM | AR3: no | AS3: si | AT3: si | AU3: 11 | AV3: NA | AW3: NA | AX3: NA | AY3: NA | AZ3: NA | BA3: NA | BB3: 216 | BC3: Trampa Ovas | BD3: 4 | BE3: 30-60 | BF3: Peruana | BG3: Ova | BH3: no | BI3: Octubre-Diciembre | BJ3: 3 | BK3: Usa esteras (6: 4x3m) con manta(6: 6x3m y sargazo/palmeras | BL3: 12-30 | BM3: 48-96 | BN3: 4 | BO3: 200 | BP3: 500-1000 | BQ3: Acopiador | BR3: 40-50 | BS3: Cortina superficial | BT3: 4 | BU3: 30-60 | BV3: Peruana | BW3: Bonito | BX3: no | BY3: Octubre-Abril | BZ3: 4-5 | CA3: #paños: 16, cocada: 4 pulgadas, malla 10x20 metros | CB3: 2-6 | CC3: 0.5-1 | CD3: 1-5 | CE3: 200-800 | CF3: 400-1200 | CG3: Comerciante | CH3: 3.30-12 | CI3: no | CJ3: NA | CK3: NA | CL3: NA | CM3: NA | CN3: NA | CO3: NA | CP3: NA | CQ3: NA | CR3: NA | CS3: NA | CT3: NA | CU3: NA | CV3: Su papá es el dueño de la embarcación. Pescador menciona que el boliche abarata el precio del bonito (bolicheros no respetan el pacto de cuota de bonito que tienen con los cortineros). Asimismo, pescador paga a acopiador una comisión de 2 soles por kg de ova. Él negocia con acopiador para que le cubra la gasolina y esteras con palmeras. Ovas con ojo son devueltas al mar. 1 bidón de gasolina son 18 galones, 1 bidón está 280 a 300 soles y recorre aprox. 50 millas.
A4: CC-SAN ANDRES-003 | B4: Cristel Cordero | C4: 45758 | D4: Santiago Martinez Ronceros | E4: 22243503 | F4: 45 | G4: 25 | H4: Pisco | I4: El Chaco | J4: El Chaco | K4: 24080 | L4: =DATEDIF(K4, DATE(2025,8,29), "Y") -> 59 | M4: M | N4: Casado/Conviviente | O4: Primaria | P4: si | Q4: no | R4: Patrón | S4: si | T4: ASOCIACION DE PESCADORES ARTESANALES Y EXTRACTORES DE MARISCOS ALMIRANTE MIGUEL GRAU SAN ANDRES | U4: si | V4: Trampa nasas | W4: cangrejos | X4: Buceo compresora | Y4: mariscos | Z4: NA | AA4: NA | AB4: si | AC4: Cocinero | AD4: 1 | AE4: 1 | AF4: si | AG4: Profesora | AH4: no | AI4: NA | AJ4: si | AK4: NA | AL4: si | AM4: NA | AN4: 0 | AO4: no | AP4: MARIA AUXILIADORA DE LOS CRISTIANOS | AQ4: PS-42470-BM | AR4: no | AS4: si | AT4: si | AU4: 4.5 | AV4: NA | AW4: NA | AX4: NA | AY4: NA | AZ4: NA | BA4: NA | BB4: 110 | BC4: Trampa Ovas | BD4: 3 | BE4: 24-59 | BF4: Peruana | BG4: Ova | BH4: no | BI4: Noviembre-Enero | BJ4: 4-5 | BK4: Usa solo manta (12: 3x2m) con sargazo/manguera | BL4: 12-19 | BM4: 48-72 | BN4: 3 | BO4: 300-800 | BP4: 550-1100 | BQ4: Acopiador | BR4: 26-44 | BS4: Palangre de fondo | BT4: 7 | BU4: 24-59 | BV4: Peruana | BW4: Bacalao | BX4: Tamboril, Jurel, Caballa | BY4: Cuota anual | BZ4: NS | CA4: NS | CB4: 12 | CC4: 8 | CD4: 12-24 | CE4: 250-500 | CF4: 3000-7000 | CG4: Trato con el armador | CH4: 4 | CI4: no | CJ4: NA | CK4: NA | CL4: NA | CM4: NA | CN4: NA | CO4: NA | CP4: NA | CQ4: NA | CR4: NA | CS4: NA | CT4: NA | CU4: NA | CV4: Precio (kg) de ova con ojo: 9 soles. Esta se vende en la sierra (Arequipa y Puno), plato típico: Caldito de Viernes. Menciona que a los pescadores Venezolanos les pagan menos. Bacalao lo pescan entre los 1800-2500 metros de profundidad.
A5: CC-SAN ANDRES-004 | B5: Cristel Cordero | C5: 45762 | D5: Javier De la Cruz | E5: 40691053 | F5: 26 | G5: 20 | H5: San Andrés | I5: San Andrés | J5: San Andrés, Lagunillas | K5: 28605 | L5: =DATEDIF(K5, DATE(2025,8,29), "Y") -> 47 | M5: M | N5: Casado/Conviviente | O5: Secundaria | P5: si | Q5: si | R5: Armador | S5: si | T5: ASPAMACHIBSA | U5: si | V5: Buceo compresora | W5: mariscos | X5: NA | Y5: NA | Z5: NA | AA5: NA | AB5: no | AC5: NA | AD5: 3 | AE5: 4 | AF5: si | AG5: Ama de casa | AH5: no | AI5: NA | AJ5: si | AK5: NA | AL5: no | AM5: Mujeres se encargan principalmente de ayudar a jalar, limpiar y cocinar en la embarcación; no realiza el trabajo pesado por lo que se le recibe un poco menos. | AN5: 1 | AO5: si | AP5: JAIR Y AARON | AQ5: PS-29013-BM | AR5: no | AS5: no | AT5: si | AU5: 4 | AV5: NA | AW5: NA | AX5: NA | AY5: NA | AZ5: NA | BA5: NA | BB5: 180 | BC5: Trampa Ovas | BD5: 3 | BE5: 30-50 | BF5: Peruana | BG5: Ova | BH5: no | BI5: Noviembre-Febrero | BJ5: 4-5 | BK5: Usa esteras con manta y sargazo/palmeras | BL5: 20-30 | BM5: 72-96 | BN5: 5-6 | BO5: 100-250 | BP5: 150-10000 | BQ5: Acopiador | BR5: 30-45 | BS5: Cortina superficial | BT5: 4 | BU5: 20-50 | BV5: Peruana | BW5: Bonito | BX5: no | BY5: Octubre-Diciembre | BZ5: 12 | CA5: #paños: 18, cocada: 4 pulgadas, malla 10x100 metros | CB5: 3-6 | CC5: 0.5 | CD5: 6-12 | CE5: 100-500 | CF5: 300-3000 | CG5: Comerciante | CH5: 1-5 | CI5: no | CJ5: NA | CK5: NA | CL5: NA | CM5: NA | CN5: NA | CO5: NA | CP5: NA | CQ5: NA | CR5: NA | CS5: NA | CT5: NA | CU5: NA | CV5: Precio (kg) de ova con ojo: 5 soles. Destino de la ova: no sabe.
A6: CC-SAN ANDRES-005 | B6: Cristel Cordero | C6: 45762 | D6: Darío Aquije Galvez | E6: 42043898 | F6: 25 | G6: 10 | H6: San Andrés | I6: San Andrés | J6: San Andrés | K6: 29842 | L6: =DATEDIF(K6, DATE(2025,8,29), "Y") -> 43 | M6: M | N6: Casado/Conviviente | O6: Secundaria | P6: si | Q6: no | R6: Armador | S6: si | T6: ASPAMACHIBSA | U6: si | V6: Buceo compresora | W6: mariscos | X6: NA | Y6: NA | Z6: NA | AA6: NA | AB6: no | AC6: NA | AD6: 2 | AE6: 2 | AF6: si | AG6: Ama de casa | AH6: no | AI6: NA | AJ6: si | AK6: NA | AL6: NS | AM6: NA | AN6: 1 | AO6: si | AP6: NAYELI VALERIA I | AQ6: PS-39761-BM | AR6: no | AS6: no | AT6: si | AU6: 4 | AV6: NA | AW6: NA | AX6: NA | AY6: NA | AZ6: NA | BA6: NA | BB6: 180 | BC6: Trampa Ovas | BD6: 2-3 | BE6: 28-42 | BF6: Peruana | BG6: Ova | BH6: no | BI6: Noviembre-Febrero | BJ6: 5 | BK6: Usa esteras con manta y palmeras | BL6: 25-30 | BM6: 72 | BN6: 8 | BO6: 80-200 | BP6: 500-800 | BQ6: Comerciante | BR6: 30-42 | BS6: no | BT6: NA | BU6: NA | BV6: NA | BW6: NA | BX6: NA | BY6: NA | BZ6: NA | CA6: NA | CB6: NA | CC6: NA | CD6: NA | CE6: NA | CF6: NA | CG6: NA | CH6: NA | CI6: no | CJ6: NA | CK6: NA | CL6: NA | CM6: NA | CN6: NA | CO6: NA | CP6: NA | CQ6: NA | CR6: NA | CS6: NA | CT6: NA | CU6: NA | CV6: Precio (kg) de ova con ojo: 5 soles. Pescador previene para que no salga ova con ojo, esta representa menos del 1% del total de su pesca. Pescador vende al comerciante que paga mejor y este vende a la empresa.
A7: CC-SAN ANDRES-006 | B7: Cristel Cordero | C7: 45772 | D7: Edy Carrizales Valenzuela | E7: 10332720 | F7: 40 | G7: 20 | H7: San Andrés | I7: San Andrés | J7: San Andrés, Pucusana, Marcona | K7: 24136 | L7: =DATEDIF(K7, DATE(2025,8,29), "Y") -> 59 | M7: M | N7: Divorciado | O7: Secundaria | P7: si | Q7: si | R7: Armador, Patrón | S7: no | T7: NA | U7: si | V7: Pinta | W7: pejerrey | X7: NA | Y7: NA | Z7: NA | AA7: NA | AB7: no | AC7: NA | AD7: 6 | AE7: 6 | AF7: no | AG7: NA | AH7: no | AI7: NA | AJ7: si | AK7: NA | AL7: si | AM7: NA | AN7: 1 | AO7: si | AP7: YAYO | AQ7: PT-27127-BM | AR7: no | AS7: no | AT7: no | AU7: 6 | AV7: NA | AW7: NA | AX7: NA | AY7: NA | AZ7: NA | BA7: NA | BB7: 120-250 | BC7: Trampa Ovas | BD7: 3 | BE7: 17-59 | BF7: Peruana | BG7: Ova | BH7: no | BI7: Octubre-Marzo | BJ7: 6-10 | BK7: Usa esteras con manta y sargazo/palmeras/manguera | BL7: 15-30 | BM7: 24-72 | BN7: 3-4 | BO7: 100-400 | BP7: 1000-1500 | BQ7: Acopiador | BR7: 40-48 | BS7: Cortina superficial | BT7: 4 | BU7: 17-59 | BV7: Peruana | BW7: Bonito | BX7: no | BY7: Noviembre-Abril | BZ7: 20 | CA7: #paños: 5, cocada: 4 pulgadas, malla 15x150 metros | CB7: 5 | CC7: 0.5-1 | CD7: 12 | CE7: 125-2000 | CF7: 4000-6000 | CG7: Comerciante | CH7: 2-4 | CI7: no | CJ7: NA | CK7: NA | CL7: NA | CM7: NA | CN7: NA | CO7: NA | CP7: NA | CQ7: NA | CR7: NA | CS7: NA | CT7: NA | CU7: NA | CV7: Ova con ojo se descarta ya que no tiene valor económico.
A8: CC-SAN ANDRES-007 | B8: Cristel Cordero | C8: 45778 | D8: Frank García Ríos | E8: 45594397 | F8: 30 | G8: 20 | H8: Pisco | I8: San Andrés, Marcona | J8: Callao, Chimbote, Salaverry, Marcona, Lomas | K8: 29342 | L8: =DATEDIF(K8, DATE(2025,8,29), "Y") -> 45 | M8: M | N8: Soltero | O8: Secundaria | P8: si | Q8: si | R8: Patrón | S8: no | T8: NA | U8: no | V8: NA | W8: NA | X8: NA | Y8: NA | Z8: NA | AA8: NA | AB8: no | AC8: NA | AD8: 0 | AE8: 0 | AF8: no | AG8: NA | AH8: no | AI8: NA | AJ8: si | AK8: NA | AL8: si | AM8: NA | AN8: 0 | AO8: no | AP8: MAR Y CIELO | AQ8: NS | AR8: no | AS8: no | AT8: si | AU8: 20 | AV8: NA | AW8: NA | AX8: NA | AY8: NA | AZ8: NA | BA8: NA | BB8: 200-300 | BC8: Trampa Ovas | BD8: 3 | BE8: 35-60 | BF8: Peruana | BG8: Ova | BH8: no | BI8: Septiembre-Febrero | BJ8: 5 | BK8: Usa mantas y pameras/manguera | BL8: 30 | BM8: 72 | BN8: 4-5 | BO8: 50-500 | BP8: 1000 | BQ8: Acopiador | BR8: 40-50 | BS8: Cortina superficial | BT8: 6 | BU8: 35-60 | BV8: Peruana | BW8: Tiburones (azul, diamante, zorro) | BX8: no | BY8: Septiembre-Febrero | BZ8: 7-8 | CA8: #paños: 30-35, cocada: 9 pulgadas, malla 22x110 metros | CB8: 7-8 | CC8: 24 | CD8: 6-7 | CE8: 3000 | CF8: 8000 | CG8: Acopiador | CH8: Azul (1-3), Zorro (7-10) y Diamante (15-20) | CI8: Cortina de fondo | CJ8: Bacalao | CK8: no | CL8: Diciembre-Marzo | CM8: NA | CN8: #paños: 30-40, cocada: 6 pulgadas, malla 16x64 metros | CO8: 30-45 | CP8: 10-12 | CQ8: 20-25 | CR8: 500-600 | CS8: 12000-2000 | CT8: Directo a empresa | CU8: 20-25 | CV8: Durante faena ova con ojo se descarta al mar, manta y manguera se amarran para simular al zargazo. Acopiador de ovas en Pisco (Embarcación: Astrid Carolina). Pesca de tiburones: >120 mn desde la costa frente a Lomas. Pesca bacalao 3000m de profundicdad con cortina de fondo.
A9: CC-SAN ANDRES-008 | B9: Cristel Cordero | C9: 45807 | D9: Felix Flores Anchante | E9: 22308700 | F9: 20 | G9: 15 | H9: Pisco | I9: San Andrés, El Chaco | J9: San Andrés, El Chaco | K9: 26873 | L9: =DATEDIF(K9, DATE(2025,8,29), "Y") -> 52 | M9: M | N9: Casado/Conviviente | O9: Superior Técnico | P9: si | Q9: si | R9: Armador, Patrón | S9: si | T9: AFREMARPA | U9: si | V9: Buceo compresora | W9: mariscos | X9: Cortina costera | Y9: pejerrey | Z9: NA | AA9: NA | AB9: si | AC9: Técnico de mantenimiento en empresa industrial | AD9: 4 | AE9: 3 | AF9: si | AG9: Ama de casa | AH9: si | AI9: 1 hijo (tripulante) | AJ9: si | AK9: NA | AL9: si | AM9: NA | AN9: 1 | AO9: si | AP9: JESUS ES MI GUÍA | AQ9: PS-61764-BM | AR9: no | AS9: si | AT9: si | AU9: 6 | AV9: NA | AW9: NA | AX9: NA | AY9: NA | AZ9: NA | BA9: NA | BB9: 150 | BC9: Trampa Ovas | BD9: 3 | BE9: 26-52 | BF9: Peruana | BG9: Ova | BH9: no | BI9: Octubre-Febrero | BJ9: 3-4 | BK9: Usa esteras (3: 2x3 metros) con manta (2: 5x2 m) y manguera/zargazo | BL9: 15-30 | BM9: 48-96 | BN9: 4-7 | BO9: 60-300 | BP9: 600-1200 | BQ9: Acopiador | BR9: 28-45 | BS9: no | BT9: NA | BU9: NA | BV9: NA | BW9: NA | BX9: NA | BY9: NA | BZ9: NA | CA9: NA | CB9: NA | CC9: NA | CD9: NA | CE9: NA | CF9: NA | CG9: NA | CH9: NA | CI9: no | CJ9: NA | CK9: NA | CL9: NA | CM9: NA | CN9: NA | CO9: NA | CP9: NA | CQ9: NA | CR9: NA | CS9: NA | CT9: NA | CU9: NA | CV9: S/. 15 a 19 precio de 1 galón de combustible. Acopiador no quiere comprar ova con ojo. 3 esteras (2x3 metros) con cabo/manguera/zargazo y 2 mantas (5x2 metros) con corcho o botellas plásticas, mantas van debajo de las esteras. Los extremos se refuerzan con palos de eucalipto.
A10: CC-SAN ANDRES-009 | B10: Cristel Cordero | C10: 45827 | D10: Luis Cabezudo Diaz | E10: 22283675 | F10: 50 | G10: 30 | H10: San Andrés | I10: San Andrés, Marcona, Lomas | J10: San Andrés, Marcona, Lomas | K10: 22249 | L10: =DATEDIF(K10, DATE(2025,8,29), "Y") -> 64 | M10: M | N10: Casado/Conviviente | O10: Primaria | P10: si | Q10: no | R10: Armador, Patrón | S10: si | T10: ASOCIACION DE PESCADORES ARTESANALES Y EXTRACTORES DE MARISCOS ALMIRANTE MIGUEL GRAU SAN ANDRES | U10: si | V10: Buceo compresora | W10: mariscos, tramboyo, pintadilla, lenguado | X10: NA | Y10: NA | Z10: NA | AA10: NA | AB10: no | AC10: NA | AD10: 1 | AE10: 3 | AF10: si | AG10: Ama de casa | AH10: si | AI10: 1 hijo (tripulante) | AJ10: no | AK10: No es apropiado, requiere mucha fuerza física y en altamar no hay privacidad | AL10: si | AM10: NA | AN10: 1 | AO10: si | AP10: STEFANNY Y SHEYLA | AQ10: PS-30630-BM | AR10: no | AS10: si | AT10: si | AU10: 6 | AV10: NA | AW10: NA | AX10: NA | AY10: NA | AZ10: NA | BA10: NA | BB10: 190-200 | BC10: Trampa Ovas | BD10: 3 | BE10: 25-65 | BF10: Peruana | BG10: Ova | BH10: no | BI10: Octubre-Enero | BJ10: 4-5 | BK10: Usa esteras con manta y sargazo/palmeras/manguera | BL10: 15-25 | BM10: 24-72 | BN10: 7-15 | BO10: 50-150 | BP10: 600-800 | BQ10: Acopiador | BR10: 35-44 | BS10: Pinta potera | BT10: 4 | BU10: 25-65 | BV10: Peruana | BW10: Pota | BX10: no | BY10: Todo el año (cuota) | BZ10: 4/mes | CA10: NA | CB10: 5 | CC10: NA | CD10: NA | CE10: NA | CF10: 600-800 | CG10: Acopiador | CH10: 35-44 | CI10: Cortina superficial | CJ10: Bonito | CK10: NA | CL10: Todo el año (cuota) | CM10: 2/mes | CN10: #paños: 8, cocada: 4 pulgadas, malla 7x128 metros | CO10: 5 | CP10: 0.5-1 | CQ10: 3-10 | CR10: 440-1100 | CS10: 3000-4000 | CT10: Acopiador | CU10: 2-4 | CV10: Pesca de pota principalmente entre mayo a agosto, fuera de las 40 mn. Inidica que en altamar se pelean entre pescadores por el recurso. Precio de ova con ojo: S/.8 (1 kg del total de la faena de ova). Indica que desde hace 3 años la abundancia de ova de pez volador se ha reducido.
A11: CC-EL CHACO-001 | B11: Cristel Cordero | C11: 45827 | D11: Walter Torres Escate | E11: 22299095 | F11: 30 | G11: 5 | H11: El Chaco | I11: El Chaco | J11: El Chaco, Pucusana, Marcona | K11: 26490 | L11: =DATEDIF(K11, DATE(2025,8,29), "Y") -> 53 | M11: M | N11: Casado/Conviviente | O11: Primaria | P11: si | Q11: si | R11: Armador, Patrón | S11: si | T11: ASPADSA, ASOCIACION DE PESCADORES,MARICULTORES Y ARMADORES ARTESANALES DEL CHACO - PARACAS | U11: si | V11: Cortina costera | W11: Lisa | X11: NA | Y11: NA | Z11: NA | AA11: NA | AB11: no | AC11: NA | AD11: 2 | AE11: 4 | AF11: si | AG11: Ama de casa | AH11: no | AI11: NA | AJ11: no | AK11: La mujer no tiene mucha fuerza física para pescar y maniobrar la embarcación. | AL11: NS | AM11: NA | AN11: 2 | AO11: si | AP11: VIRGENCITA DE CHAPI | AQ11: PS-19707-BM, PS-52182-BM | AR11: no | AS11: si | AT11: si | AU11: 4 | AV11: VIRGEN DE YAUCA | AW11: PS-52182-BM | AX11: no | AY11: no | AZ11: no | BA11: 3 | BB11: 255 | BC11: Trampa Ovas | BD11: 3 | BE11: 30-50 | BF11: Peruana | BG11: Ova | BH11: no | BI11: Octubre-Enero | BJ11: 3 | BK11: Usa esteras con manta y manguera | BL11: 30-40 | BM11: 48-72 | BN11: 10-15 | BO11: 10-50 | BP11: 350-650 | BQ11: Acopiador | BR11: 25-35 | BS11: no | BT11: NA | BU11: NA | BV11: NA | BW11: NA | BX11: NA | BY11: NA | BZ11: NA | CA11: NA | CB11: NA | CC11: NA | CD11: NA | CE11: NA | CF11: NA | CG11: NA | CH11: NA | CI11: NA | CJ11: NA | CK11: NA | CL11: NA | CM11: NA | CN11: NA | CO11: NA | CP11: NA | CQ11: NA | CR11: NA | CS11: NA | CT11: NA | CU11: NA | CV11: Ova con ojo se descarta ya que vale muy poco (S/. 5-7) Hace 3 años había más ova. Indica que palmera está muy caro, zargazo es dificil de conseguir (recogen las que flotan a la deriva en el mar o a veces le compran a los recolectores de algas).
A12: VT-SAN ANDRES-001 | B12: Valeria Torres | C12: 45807 | D12: Romel Huerta Mendoza | E12: 41349147 | F12: 33 | G12: 20 | H12: San Andrés | I12: San Andrés, Lagunillas, El Chaco, Laguna Grande | K12: 29400 | L12: =DATEDIF(K12, DATE(2025,8,29), "Y") -> 45 | M12: M | N12: Casado/Conviviente | O12: Secundaria | P12: si | Q12: si | R12: Armador | S12: si | T12: AFREMARPA, ASPADSA | U12: si | V12: Buceo compresora | W12: mariscos | X12: NA | Y12: NA | Z12: NA | AA12: NA | AB12: si | AC12: Agricultura (en el norte) | AD12: 4 | AE12: 2 | AF12: si | AG12: Ama de casa | AH12: no | AI12: NA | AJ12: si | AK12: NA | AL12: si | AM12: NA | AN12: 1 | AO12: si | AP12: HERMANOS HUERTA I | AQ12: PS-29167-BM | AR12: no | AS12: si | AT12: si | AU12: 5 | AV12: NA | AW12: NA | AX12: NA | AY12: NA | AZ12: NA | BA12: NA | BB12: 270 | BC12: Trampa Ovas | BD12: 3 | BE12: 27-45 | BF12: Peruana | BG12: Ova | BH12: no | BI12: Noviembre-Febrero | BJ12: 3-4 | BK12: Usa esteras (6-7: 2x3m) con manta(4:3x6m) y sargazo/palmeras/manguera | BL12: 18-25 | BM12: 48-72 | BN12: 3-5 | BO12: 500-1800 | BP12: 800-1200 | BQ12: Acopiador | BR12: 28-38 | BS12: Cerco | BT12: 4 | BU12: 27-45 | BV12: Peruana | BW12: Bonito | BX12: no | BY12: Noviembre-Enero | BZ12: 2-3/mes | CA12: Cerco no mecanizado, cocada: 4 pulgadas | CB12: 2-3 | CC12: 0.5-1 | CD12: 2-3 | CE12: 200-400 | CF12: 300-800 | CG12: Acopiador | CH12: 2-4 | CI12: no | CJ12: NA | CK12: NA | CL12: NA | CM12: NA | CN12: NA | CO12: NA | CP12: NA | CQ12: NA | CR12: NA | CS12: NA | CT12: NA | CU12: NA | CV12: Pesca bonito con cerco hasta las 90 mn. Zona de pesca de altura: Lomas a Pucusana, principalmente frente a Chincha. Precio de ova con ojo: S/.7. Durante la faena, analiza el comportamiento del pez volador ya que cuando solo son machos busca en otro sitio hasta encontrar ova.
A13: VT-EL CHACO-001 | B13: Valeria Torres | C13: 45807 | D13: David Martinez Valladares | E13: 22263898 | F13: 20 | G13: 10 | H13: Pisco | I13: El Chaco | J13: El Chaco | K13: 22521 | L13: =DATEDIF(K13, DATE(2025,8,29), "Y") -> 64 | M13: M | N13: Casado/Conviviente | O13: Secundaria | P13: si | Q13: no | R13: Patrón | S13: si | T13: AFREMARPA | U13: si | V13: Buceo compresora | W13: mariscos | X13: NA | Y13: NA | Z13: NA | AA13: NA | AB13: no | AC13: NA | AD13: 4 | AE13: 4 | AF13: si | AG13: Ama de casa | AH13: si | AI13: 1 hijo (tripulante) | AJ13: si | AK13: NA | AL13: si | AM13: NA | AN13: 1 | AO13: si | AP13: ANTONY GIANCARLO I | AQ13: PS-13810-BM | AR13: no | AS13: no | AT13: si | AU13: 3 | AV13: NA | AW13: NA | AX13: NA | AY13: NA | AZ13: NA | BA13: NA | BB13: 170 | BC13: Trampa Ovas | BD13: 4 | BE13: 25-45 | BF13: Peruana | BG13: Ova | BH13: no | BI13: Octubre-Febrero | BJ13: 8 | BK13: Usa esteras con manta y sargazo | BL13: 15 | BM13: 20-72 | BN13: 3 | BO13: 600 | BP13: 1500 | BQ13: Acopiador | BR13: 40-45 | BS13: no | BT13: NA | BU13: NA | BV13: NA | BW13: NA | BX13: NA | BY13: NA | BZ13: NA | CA13: NA | CB13: NA | CC13: NA | CD13: NA | CE13: NA | CF13: NA | CG13: NA | CH13: NA | CI13: no | CJ13: NA | CK13: NA | CL13: NA | CM13: NA | CN13: NA | CO13: NA | CP13: NA | CQ13: NA | CR13: NA | CS13: NA | CT13: NA | CU13: NA | CV13: Precio de ova con ojo: S/.5.
A14: FV-SAN ANDRES-001 | B14: Flor Ventura | C14: 45807 | D14: Jorge Anchante Chavez | E14: 22242605 | F14: 43 | G14: 13 | H14: San Andrés | I14: San Andrés, Marcona | J14: San Andrés, El Chaco, Marcona | K14: 24208 | L14: =DATEDIF(K14, DATE(2025,8,29), "Y") -> 59 | M14: M | N14: Casado/Conviviente | O14: Secundaria | P14: si | Q14: si | R14: Armador, Patrón | S14: si | T14: AFREMARPA | U14: si | V14: Buceo compresora | W14: mariscos | X14: NA | Y14: NA | Z14: NA | AA14: NA | AB14: no | AC14: NA | AD14: 3 | AE14: 2 | AF14: si | AG14: Comerciante de mariscos | AH14: si | AI14: Pareja (armadora, comerciante de mariscos) | AJ14: si | AK14: NA | AL14: si | AM14: NA | AN14: 1 | AO14: si | AP14: MANUELA DEL PILAR | AQ14: PS-56758-BM | AR14: no | AS14: si | AT14: si | AU14: 5 | AV14: NA | AW14: NA | AX14: NA | AY14: NA | AZ14: NA | BA14: NA | BB14: 119-136 | BC14: Trampa Ovas | BD14: 4 | BE14: 30-60 | BF14: Peruana | BG14: Ova | BH14: no | BI14: Noviembre-Febrero | BJ14: 4 | BK14: Usa esteras con manta y sargazo/palmeras/manguera | BL14: 15-20 | BM14: 72-96 | BN14: 4-5 | BO14: 20-300 | BP14: 130-1800 | BQ14: Acopiador | BR14: 20-45 | BS14: no | BT14: NA | BU14: NA | BV14: NA | BW14: NA | BX14: NA | BY14: NA | BZ14: NA | CA14: NA | CB14: NA | CC14: NA | CD14: NA | CE14: NA | CF14: NA | CG14: NA | CH14: NA | CI14: no | CJ14: NA | CK14: NA | CL14: NA | CM14: NA | CN14: NA | CO14: NA | CP14: NA | CQ14: NA | CR14: NA | CS14: NA | CT14: NA | CU14: NA | CV14: Durante la faena de ova de pez volador el pescador aprovecha en pescar con cordel (tiburón y perico) y con pinta potera (pota) para su consumo. A veces puede traer a tierra (tiburón lo preserva con sal). Embarcación está a nombre de su esposa.
A15: CZ-SAN ANDRES-001 | B15: Cesar Zamora | C15: 45772 | D15: Manuel Barrientos Valenzuela | E15: 22285186 | F15: 40 | G15: 15 | H15: San Andrés | I15: San Andrés | J15: San Andrés, El Chaco, Marcona, Pucusana | K15: 20540 | L15: =DATEDIF(K15, DATE(2025,8,29), "Y") -> 69 | M15: M | N15: Casado/Conviviente | O15: Superior Universitario | P15: si | Q15: si | R15: Armador | S15: si | T15: ASPADSA | U15: si | V15: Cerco costero | W15: anchoveta | X15: cortina costera | Y15: NA | Z15: NA | AA15: NA | AB15: no | AC15: NA | AD15: 2 | AE15: 0 | AF15: si | AG15: Ama de casa | AH15: no | AI15: NA | AJ15: si | AK15: NA | AL15: si | AM15: NA | AN15: 1 | AO15: si | AP15: TRIPITA | AQ15: PS-23141-BM | AR15: no | AS15: no | AT15: si | AU15: 10 | AV15: NA | AW15: NA | AX15: NA | AY15: NA | AZ15: NA | BA15: NA | BB15: 200 | BC15: Trampa Ovas | BD15: 4 | BE15: 20-60 | BF15: Peruana | BG15: Ova | BH15: no | BI15: Enero-Marzo | BJ15: 6 | BK15: Usa esteras y sargazo/palmeras | BL15: 15-60 | BM15: 24-48 | BN15: 3 | BO15: 200-500 | BP15: 1000-1500 | BQ15: Directo a empresa | BR15: 25-30 | BS15: Pinta potera | BT15: 4 | BU15: 20-60 | BV15: Peruana | BW15: Pota | BX15: no | BY15: Enero-Marzo | BZ15: 6 | CA15: NA | CB15: 5 | CC15: NA | CD15: NA | CE15: NA | CF15: 4000-5000 | CG15: Comerciante | CH15: 6 | CI15: Espinel superficial | CJ15: Perico | CK15: pota, caballa | CL15: Noviembre-Marzo | CM15: 8 | CN15: Linea madre: 500 m, 250 lineas #anzuelos/linea: 1, Calibre: 4 o 5 | CO15: 5 | CP15: 3-5 | CQ15: 3-5 | CR15: 1000 | CS15: 2000 | CT15: Comerciante | CU15: NS | CV15: Hace 1 año no pesca.
A16: CC-SAN ANDRES-010 | B16: Cristel Cordero | C16: 45805 | D16: Fabian Tibilmana | E16: 22300490 | F16: 34 | G16: 25 | H16: Pisco | I16: San Andrés, Marcona | J16: Pisco, Marcona | K16: 27166 | L16: =DATEDIF(K16, DATE(2025,8,29), "Y") -> 51 | M16: M | N16: Soltero | O16: Secundaria | P16: si | Q16: si | R16: Tripulación | S16: si | T16: ASOCIACION DE PESCADORES ARTESANALES Y EXTRACTORES DE MARISCOS ALMIRANTE MIGUEL GRAU SAN ANDRES | U16: si | V16: Buceo compresora | W16: mariscos | X16: NA | Y16: NA | Z16: NA | AA16: NA | AB16: no | AC16: NA | AD16: 0 | AE16: 3 | AF16: no | AG16: NA | AH16: no | AI16: NA | AJ16: si | AK16: NA | AL16: NS | AM16: NA | AN16: 0 | AO16: NA | AP16: LOS TIPIS | AQ16: SN-02572-BM | AR16: no | AS16: no | AT16: si | AU16: 2.5 | AV16: NA | AW16: NA | AX16: NA | AY16: NA | AZ16: NA | BA16: NA | BB16: 192-240 | BC16: Trampa Ovas | BD16: 4 | BE16: 16-70 | BF16: Peruana y Venezolana | BG16: Ova | BH16: no | BI16: Octubre-Febrero | BJ16: 5 | BK16: Usa esteras (6) con manta (15) y sargazo/palmeras/manguera | BL16: 20-25 | BM16: 72 | BN16: 7-9 | BO16: 50-500 | BP16: 600-1200 | BQ16: Acopiador | BR16: 18-35 | BS16: no | BT16: NA | BU16: NA | BV16: NA | BW16: NA | BX16: NA | BY16: NA | BZ16: NA | CA16: NA | CB16: NA | CC16: NA | CD16: NA | CE16: NA | CF16: NA | CG16: NA | CH16: NA | CI16: no | CJ16: NA | CK16: NA | CL16: NA | CM16: NA | CN16: NA | CO16: NA | CP16: NA | CQ16: NA | CR16: NA | CS16: NA | CT16: NA | CU16: NA | CV16: Pescador menciona que la ova con ojo es descartado por el acopiador.
A17: CC-SAN ANDRES-011 | B17: Cristel Cordero | C17: 45889 | D17: Eloy García Pizarro | E17: 22286836 | F17: 45 | G17: 12 | H17: San Andrés | I17: San Andrés | J17: San Andrés, Marcona | K17: 24239 | L17: =DATEDIF(K17, DATE(2025,8,29), "Y") -> 59 | M17: M | N17: Casado/Conviviente | O17: Sin Instrucción | P17: si | Q17: si | R17: Armador | S17: si | T17: ASPADSA | U17: si | V17: Buceo compresora | W17: mariscos, pulpo | X17: NA | Y17: NA | Z17: NA | AA17: NA | AB17: no | AC17: NA | AD17: 1 | AE17: 3 | AF17: si | AG17: Ama de casa | AH17: no | AI17: NA | AJ17: no | AK17: Hay mucho viento en Pisco por lo que el oleaje es muy bravo y es peligroso para las mujeres | AL17: si | AM17: NA | AN17: 1 | AO17: si | AP17: BEATITA MELCHORITA | AQ17: PS-28871-BM | AR17: no | AS17: si | AT17: si | AU17: 4.5 | AV17: NA | AW17: NA | AX17: NA | AY17: NA | AZ17: NA | BA17: NA | BB17: 128-160 | BC17: Trampa Ovas | BD17: 3-4 | BE17: 40-45 | BF17: Peruana | BG17: Ova | BH17: no | BI17: Noviembre-Enero | BJ17: 3 | BK17: Usa esteras (10: 1.5x3m) con manta (20: 1.5x3m) y sargazo/palmeras/manguera | BL17: 15 | BM17: 48-96 | BN17: 3-8 | BO17: 100-150 | BP17: 500-700 | BQ17: Acopiador | BR17: 25-45 | BS17: no | BT17: NA | BU17: NA | BV17: NA | BW17: NA | BX17: NA | BY17: NA | BZ17: NA | CA17: NA | CB17: NA | CC17: NA | CD17: NA | CE17: NA | CF17: NA | CG17: NA | CH17: NA | CI17: no | CJ17: NA | CK17: NA | CL17: NA | CM17: NA | CN17: NA | CO17: NA | CP17: NA | CQ17: NA | CR17: NA | CS17: NA | CT17: NA | CU17: NA | CV17: Gasta en la primera salida alrededor de S/.6000. Ova con ojo, el acopiador ya no le paga pero se lo queda. Él ha escuchado que lo secan y lo llevan a la sierra para preparar un plato llamado cau-cau.
A18: CC-SAN ANDRES-012 | B18: Cristel Cordero | C18: 45889 | D18: Luis Canelo Acasiete | E18: 22285867 | F18: 55 | G18: 55 | H18: San Andrés | I18: San Andrés, Quilca | J18: San Andrés | K18: 20503 | L18: =DATEDIF(K18, DATE(2025,8,29), "Y") -> 69 | M18: M | N18: Casado/Conviviente | O18: Superior Universitario | P18: si | Q18: si | R18: Armador | S18: si | T18: ASOCIACION DE PESCADORES ARTESANALES DE BOLICHITOS DE SAN ANDRES VICTOR PEÑA ORMEÑO | U18: si | V18: Cerco costero | W18: anchoveta | X18: NA | Y18: NA | Z18: NA | AA18: NA | AB18: si | AC18: Gerente de Servicio al Ciudadano de la Municipalidad de San Andrés | AD18: 0 | AE18: 3 | AF18: si | AG18: Bahía de embarcaciones | AH18: si | AI18: Pareja (bahía de embarcaciones) | AJ18: si | AK18: NA | AL18: si | AM18: NA | AN18: 2 | AO18: si | AP18: MARIQUITA II | AQ18: PS-29591-BM | AR18: no | AS18: no | AT18: si | AU18: 7.8 | AV18: KIKI Y DELIA | AW18: PS-00563-BM | AX18: no | AY18: no | AZ18: si | BA18: 5.8 | BB18: 204 | BC18: Cerco | BD18: 6 | BE18: 18-60 | BF18: Peruana y Venezolana | BG18: Bonito, Caballa, Jurel | BH18: no | BI18: Octubre-Abril | BJ18: 2-3/mes | BK18: Cerco mecanizado, cocada: 1 pulgada | BL18: 7 | BM18: 2 | BN18: 1-4 | BO18: 1000-5000 | BP18: 5000 | BQ18: Acopiador | BR18: Bonito: S/. 3-4, Caballa y Jurel: S/.1- 2 | BS18: Trampa ovas | BT18: 5 | BU18: 18-60 | BV18: Peruana y Venezolana | BW18: Ova | BX18: no | BY18: Noviembre-Febrero | BZ18: 3-4 | CA18: Usa esteras con manta y sargazo/palmeras | CB18: 25-30 | CC18: 48-72 | CD18: 10-12 | CE18: 50-150 | CF18: 600-800 | CG18: Acopiador | CH18: 25-32 | CI18: no | CJ18: NA | CK18: NA | CL18: NA | CM18: NA | CN18: NA | CO18: NA | CP18: NA | CQ18: NA | CR18: NA | CS18: NA | CT18: NA | CU18: NA | CV18: Tiene 2 embarcaciones bolicheras y ambas salen a la altura. Ahora sus tripulantes están pescando anchoveta para harina y venderlo a las empresas industriales (pesca ilegal).
A19: CC-SAN ANDRES-013 | B19: Cristel Cordero | C19: 45889 | D19: Pedro Donayre | E19: 22290522 | F19: 51 | G19: 16 | H19: Pisco | I19: San Andrés | J19: San Andrés, Lagunilla, Laguna Grande | K19: 20809 | L19: =DATEDIF(K19, DATE(2025,8,29), "Y") -> 68 | M19: M | N19: Viudo | O19: Superior Técnico | P19: si | Q19: si | R19: Armador, Patrón | S19: si | T19: COTSCOPEMAR | U19: no | V19: NA | W19: NA | X19: NA | Y19: NA | Z19: NA | AA19: NA | AB19: si | AC19: Maricultur (crianza de concha de abanico en la zona de amortiguamiento de Paracas) y Presidente de la OSPA | AD19: 3 | AE19: 5 | AF19: no | AG19: NA | AH19: si | AI19: 3 hijo (tripulante) | AJ19: si | AK19: NA | AL19: si | AM19: NA | AN19: 1 | AO19: si | AP19: DOÑA PETA | AQ19: PS-42425-BM | AR19: NS | AS19: si | AT19: si | AU19: 4 | AV19: NA | AW19: NA | AX19: NA | AY19: NA | AZ19: NA | BA19: NA | BB19: 192 | BC19: Trampa Ovas | BD19: 4 | BE19: 27-69 | BF19: Peruana | BG19: Ova | BH19: no | BI19: Octubre-Enero | BJ19: 5-6 | BK19: Usa mantas (20:5x4m) y pameras/manguera | BL19: 15 | BM19: 48-72 | BN19: 3-5 | BO19: 50-150 | BP19: 450-600 | BQ19: Acopiador | BR19: 26-50 | BS19: no | BT19: NA | BU19: NA | BV19: NA | BW19: NA | BX19: NA | BY19: NA | BZ19: NA | CA19: NA | CB19: NA | CC19: NA | CD19: NA | CE19: NA | CF19: NA | CG19: NA | CH19: NA | CI19: no | CJ19: NA | CK19: NA | CL19: NA | CM19: NA | CN19: NA | CO19: NA | CP19: NA | CQ19: NA | CR19: NA | CS19: NA | CT19: NA | CU19: NA | CV19: Hace 15 años él pescaba centolla con nasas (trampas) a más de 1800 de profundidad. Acopiador le descuenta S/. 1.50 por kg porque ya le dio para sus gastos para iniciar la primera salida.
A20: CC-SAN ANDRES-014 | B20: Cristel Cordero | C20: 45888 | D20: Victor Salazar Matias | E20: 22287358 | F20: 40 | G20: 30 | H20: San Andrés | I20: San Andrés | J20: El Chaco, Lagunillas | K20: 24810 | L20: =DATEDIF(K20, DATE(2025,8,29), "Y") -> 57 | M20: M | N20: Casado/Conviviente | O20: Primaria | P20: si | Q20: si | R20: Armador, Patrón | S20: si | T20: AFREMARPA | U20: si | V20: Buceo compresora | W20: mariscos | X20: NA | Y20: NA | Z20: NA | AA20: NA | AB20: no | AC20: NA | AD20: 1 | AE20: 4 | AF20: si | AG20: Ama de casa | AH20: si | AI20: 2 hijo (tripulante) | AJ20: no | AK20: En San Andrés hay mucho viento y las mujeres se marean fácilmente, en cambio en el sur es más tranquilo por lo que salen en pareja. | AL20: no | AM20: Cuando salen en pareja, el hombre se queda con el dinero ya que el ingreso es familiar. | AN20: 1 | AO20: si | AP20: LA MECHONA | AQ20: PS-00675-BM | AR20: no | AS20: si | AT20: si | AU20: 4 | AV20: NA | AW20: NA | AX20: NA | AY20: NA | AZ20: NA | BA20: NA | BB20: 120-160 | BC20: Trampa Ovas | BD20: 3 | BE20: 20-50 | BF20: Peruana | BG20: Ova | BH20: no | BI20: Octubre-Febrero | BJ20: 2-4 | BK20: Usa esteras (12: 2x1.5m) con manta (12:3x2m) y sargazo/palmeras | BL20: 20 | BM20: 24-72 | BN20: 5-8 | BO20: 100-300 | BP20: 700-800 | BQ20: Acopiador | BR20: 35-50 | BS20: no | BT20: NA | BU20: NA | BV20: NA | BW20: NA | BX20: NA | BY20: NA | BZ20: NA | CA20: NA | CB20: NA | CC20: NA | CD20: NA | CE20: NA | CF20: NA | CG20: NA | CH20: NA | CI20: no | CJ20: NA | CK20: NA | CL20: NA | CM20: NA | CN20: NA | CO20: NA | CP20: NA | CQ20: NA | CR20: NA | CS20: NA | CT20: NA | CU20: NA | CV20: Pesca de perico con espinel es complementaria a la pesca del pez volador (solo para consumo a bordo y lo sala para traerlo a tierra para su familia). Zona de pesca de ova: >30 mn frente a Lomas y llega hasta Pucusana. El pescador indica que es muy cuidadoso con su producto por lo que no le sale ova con ojito. Menciona que algunos pescadores que van a la ova en San Andrés usan la manguera para reemplazar la palmera o zargazo cuando no hay (Él ha usado pero no le gustó). Una cala de ova en verano dura solo 24h.
A21: CC-SAN ANDRES-015 | B21: Cristel Cordero | C21: 45888 | D21: Martin Cueto Cortez | E21: 22287811 | F21: 35 | G21: 20 | H21: San Andrés | I21: San Andrés | J21: San Andrés, Pucusana, Marcona | K21: 25572 | L21: =DATEDIF(K21, DATE(2025,8,29), "Y") -> 55 | M21: M | N21: Casado/Conviviente | O21: Secundaria | P21: si | Q21: no | R21: Armador | S21: si | T21: ASPADSA | U21: si | V21: Cortina costera | W21: cojinova, cachema | X21: NA | Y21: NA | Z21: NA | AA21: NA | AB21: no | AC21: NA | AD21: 2 | AE21: 3 | AF21: si | AG21: Ama de casa | AH21: no | AI21: NA | AJ21: si | AK21: NA | AL21: si | AM21: NA | AN21: 1 | AO21: si | AP21: TIO NACO II | AQ21: PS-52459-BM | AR21: no | AS21: si | AT21: si | AU21: 6 | AV21: NA | AW21: NA | AX21: NA | AY21: NA | AZ21: NA | BA21: NA | BB21: 70-200 | BC21: Trampa Ovas | BD21: 3 | BE21: 30-50 | BF21: Peruana | BG21: Ova | BH21: no | BI21: Octubre-Diciembre | BJ21: 3 | BK21: Usa esteras con manta y sargazo/palmeras/manguera | BL21: 15-20 | BM21: 48-96 | BN21: 5-7 | BO21: 20-80 | BP21: 800-1000 | BQ21: Acopiador | BR21: 23-35 | BS21: Cortina superficial | BT21: 4 | BU21: 30-50 | BV21: Peruana | BW21: Perico | BX21: no | BY21: Noviembre-Enero | BZ21: 9 | CA21: #paños: 25, cocada: 6 pulgadas, malla 5x50 metros | CB21: 7 | CC21: 1-2 | CD21: 4-5 | CE21: 300-500 | CF21: 3000-4000 | CG21: Comerciante | CH21: 5-10 | CI21: Cortina superficial | CJ21: Bonito | CK21: no | CL21: Septiembre-Mayo | CM21: 5/mes | CN21: #paños: 10, cocada: 4 pulgadas, malla 9x128 metros | CO21: 3-4 | CP21: 2 | CQ21: 9-12 | CR21: 1000-2000 | CS21: 5000 | CT21: Comerciante | CU21: 1.5-5 | CV21: Gasta en la primera salida alrededor de S/.15000. Pez volador deposita sus huevos a los 17-18°C. Zona de pesca en la altura: >30 mn frente a Marcona y llega hasta Pucusana.
A22: CC-SAN ANDRES-016 | B22: Cristel Cordero | C22: 45888 | D22: Luis Carhuaz Rosales | E22: 22265880 | F22: 50 | G22: 10 | H22: Pisco | I22: San Andrés | J22: San Andrés | K22: 21763 | L22: =DATEDIF(K22, DATE(2025,8,29), "Y") -> 66 | M22: M | N22: Soltero | O22: Primaria | P22: si | Q22: si | R22: Armador, Patrón | S22: si | T22: AFREMARPA | U22: si | V22: Buceo compresora | W22: mariscos | X22: NA | Y22: NA | Z22: NA | AA22: NA | AB22: no | AC22: NA | AD22: 0 | AE22: 3 | AF22: no | AG22: NA | AH22: si | AI22: 1 hijo (tripulante) | AJ22: NS | AK22: NA | AL22: NS | AM22: NA | AN22: 1 | AO22: si | AP22: DELIA MILAGROS | AQ22: PS-31525-BM | AR22: no | AS22: si | AT22: si | AU22: 4 | AV22: NA | AW22: NA | AX22: NA | AY22: NA | AZ22: NA | BA22: NA | BB22: 170 | BC22: Trampa Ovas | BD22: 3-4 | BE22: 60-70 | BF22: Peruana | BG22: Ova | BH22: no | BI22: Octubre-Enero | BJ22: 3-4 | BK22: Usa esteras (15:3x2m) con manta (15:3x2m) y sargazo/palmeras/manguera | BL22: 15-25 | BM22: 48-72 | BN22: 5-7 | BO22: 100-150 | BP22: 800-1000 | BQ22: Acopiador | BR22: 27-33 | BS22: no | BT22: NA | BU22: NA | BV22: NA | BW22: NA | BX22: NA | BY22: NA | BZ22: NA | CA22: NA | CB22: NA | CC22: NA | CD22: NA | CE22: NA | CF22: NA | CG22: NA | CH22: NA | CI22: no | CJ22: NA | CK22: NA | CL22: NA | CM22: NA | CN22: NA | CO22: NA | CP22: NA | CQ22: NA | CR22: NA | CS22: NA | CT22: NA | CU22: NA | CV22: En Pisco hay 2 acopiadores locales de ova: Chino Fernando (Fernando Kon) y Ruth Montoro. 1 saco es 100 kg
A23: CC-EL CHACO-002 | B23: Cristel Cordero | C23: 45887 | D23: Elmer Cotrina | E23: 45243453 | F23: 20 | G23: 10 | H23: Chincha | I23: El Chaco, Atenas | J23: El Chaco, Atenas | K23: 30793 | L23: =DATEDIF(K23, DATE(2025,8,29), "Y") -> 41 | M23: M | N23: Casado/Conviviente | O23: Secundaria | P23: si | Q23: si | R23: Armador, Patrón | S23: si | T23: AFREMARPA | U23: si | V23: Buceo compresora | W23: mariscos, cabrilla, lenguado, congrio, cherlo, tramboyo | X23: NA | Y23: NA | Z23: NA | AA23: NA | AB23: si | AC23: Maricultur (crianza de concha de abanico en la zona de amortiguamiento de Paracas) | AD23: 4 | AE23: 3 | AF23: si | AG23: Ama de casa | AH23: no | AI23: NA | AJ23: si | AK23: NA | AL23: NS | AM23: NA | AN23: 1 | AO23: si | AP23: MARIA VICTORIA | AQ23: PS-55515-BM | AR23: no | AS23: si | AT23: si | AU23: 4 | AV23: NA | AW23: NA | AX23: NA | AY23: NA | AZ23: NA | BA23: NA | BB23: 90-108 | BC23: Trampa Ovas | BD23: 3-4 | BE23: 30-50 | BF23: Peruana | BG23: Ova | BH23: no | BI23: Octubre-Enero | BJ23: 4-5 | BK23: Usa esteras con manta y palmeras | BL23: 12-18 | BM23: 24 | BN23: 10-20 | BO23: 30-40 | BP23: 350-800 | BQ23: Comerciante | BR23: 38-43 | BS23: no | BT23: NA | BU23: NA | BV23: NA | BW23: NA | BX23: NA | BY23: NA | BZ23: NA | CA23: NA | CB23: NA | CC23: NA | CD23: NA | CE23: NA | CF23: NA | CG23: NA | CH23: NA | CI23: no | CJ23: NA | CK23: NA | CL23: NA | CM23: NA | CN23: NA | CO23: NA | CP23: NA | CQ23: NA | CR23: NA | CS23: NA | CT23: NA | CU23: NA | CV23: Gasta en la primera salida alrededor de S/.10000. Ova con ojo lo descarta a bordo ya que usualmente los compradores de ovas no lo compran. Antes se usaba solo estera y sargazo, ahora se usa palmeras y hasta manguera de regadío. Cuando el perico se empieza a comer al pez volador, lo captura con cortina para el consumo de los tripulantes a bordo. Trampa de ova: primero va la manta (hace sombra), luego la estera y luego la palmera.
A24: CC-EL CHACO-003 | B24: Cristel Cordero | C24: 45889 | D24: Angel Miguel Echevarria Salguero | E24: 22309838 | F24: 49 | G24: 20 | H24: El Chaco | I24: El Chaco | J24: El Chaco | K24: 24305 | L24: =DATEDIF(K24, DATE(2025,8,29), "Y") -> 59 | M24: M | N24: Casado/Conviviente | O24: Sin Instrucción | P24: no | Q24: si | R24: Armador, Patrón | S24: si | T24: ASOCIACION DE PESCADORES,MARICULTORES Y ARMADORES ARTESANALES DEL CHACO - PARACAS | U24: si | V24: Pinta | W24: bonito | X24: Cortina costera | Y24: pejerrey | Z24: NA | AA24: NA | AB24: si | AC24: Alquiler de vela y moto acuática | AD24: 0 | AE24: 3 | AF24: si | AG24: Limpieza de playas | AH24: si | AI24: 1 hijo (tripulante) | AJ24: si | AK24: NA | AL24: si | AM24: NA | AN24: 1 | AO24: si | AP24: EL TOYO I | AQ24: PS-42693-BM | AR24: no | AS24: no | AT24: si | AU24: 6 | AV24: NA | AW24: NA | AX24: NA | AY24: NA | AZ24: NA | BA24: NA | BB24: 180 | BC24: Trampa Ovas | BD24: 3-4 | BE24: 30-59 | BF24: Peruana | BG24: Ova | BH24: no | BI24: Octubre-Diciembre | BJ24: 3-4 | BK24: Usa esteras (12:1.5x2m) con manta (12:1.5x2m) y sargazo/palmeras | BL24: 15-28 | BM24: 48-96 | BN24: 3-5 | BO24: 150-300 | BP24: 600-1500 | BQ24: Comerciante | BR24: 27-38 | BS24: no | BT24: NA | BU24: NA | BV24: NA | BW24: NA | BX24: NA | BY24: NA | BZ24: NA | CA24: NA | CB24: NA | CC24: NA | CD24: NA | CE24: NA | CF24: NA | CG24: NA | CH24: NA | CI24: no | CJ24: NA | CK24: NA | CL24: NA | CM24: NA | CN24: NA | CO24: NA | CP24: NA | CQ24: NA | CR24: NA | CS24: NA | CT24: NA | CU24: NA | CV24: Gasta en la primera salida alrededor de S/. 9000. Hay planta de procesamiento para ova en San Andrés. Pez volador nada en una corriente de agua celeste de 18 a 28°C. Ova con ojo: s/ 3. Trampa de ova: primero va la manta (hace sombra), luego la estera (en los lados zargazo para atraer al volador) y luego la palmera. Pez volador deja su huevera en la palmera y el zargazo.

Sheet Lomas
A1: Encuesta | B1: Nombre_Encuestador | C1: Fecha_Encuesta | D1: Nombre_Pescador | E1: DNI | F1: Años_Pesca | G1: Años_Altura | H1: Distrito_Vivienda | I1: Puerto_Zarpe | J1: Puerto_Arribo | K1: Fecha_Nacimiento | L1: Edad | M1: Sexo | N1: Estado_Civil | O1: Grado_Instruccion | P1: Alfabeto | Q1: Seguro_Salud | R1: Rol_Pescador | S1: OSPA | T1: Nombre_OSPA | U1: Otra_Pesca | V1: Arte_Costera1 | W1: Rec_Costero1 | X1: Arte_Costera2 | Y1: Rec_Costero2 | Z1: Arte_Costera3 | AA1: Rec_Costero3 | AB1: Alterna_Pesca | AC1: Actividad_Alterna | AD1: Personas_Dependientes | AE1: Numero_hijos | AF1: Pareja | AG1: Actividades_Pareja | AH1: FamiliaDirecta_Pesca | AI1: Rol_Familiares | AJ1: Genero_Opotunidades | AK1: GenOpor_No | AL1: Genero_Pago | AM1: GenPago_No | AN1: Num_Embarcaciones | AO1: Embarcacion_Propia | AP1: Nombre1_EmbarcacionAltura | AQ1: Matricula_1 | AR1: SISESAT_1 | AS1: Radiobaliza_1 | AT1: PTH_1 | AU1: TN_Bodega_1 | AV1: Nombre2_EmbarcacionAltura | AW1: Matricula_2 | AX1: SISESAT_2 | AY1: Radiobaliza_2 | AZ1: PTH_2 | BA1: TN_Bodega_2 | BB1: Galones_Combustible | BC1: Arte_1 | BD1: Num_Tripulantes1 | BE1: Edades_Tripulantes1 | BF1: Nacionalidad_Trip1 | BG1: Recurso_1 | BH1: Carnada1 | BI1: Temporada1 | BJ1: Viajes_Temporada1 | BK1: Detalles_Arte1 | BL1: Dias_Faena1 | BM1: Horas_Efectivas1 | BN1: Lances_Faena1 | BO1: Kg_Lance1 | BP1: Kg_Faena1 | BQ1: Venta_Recurso1 | BR1: Precio_Kg1 | BS1: Arte_2 | BT1: Num_Tripulantes2 | BU1: Edades_Tripulantes2 | BV1: Nacionalidad_Trip2 | BW1: Recurso_2 | BX1: Carnada2 | BY1: Temporada2 | BZ1: Viajes_Temporada2 | CA1: Detalles_Arte2 | CB1: Dias_Faena2 | CC1: Horas_Efectivas2 | CD1: Lances_Faena2 | CE1: Kg_Lance2 | CF1: Kg_Faena2 | CG1: Venta_Recurso2 | CH1: Precio_Kg2 | CI1: Arte_3 | CJ1: Recurso_3 | CK1: Carnada3 | CL1: Temporada3 | CM1: Viajes_Temporada3 | CN1: Detalles_Arte3 | CO1: Dias_Faena3 | CP1: Horas_Efectivas3 | CQ1: Lances_Faena3 | CR1: Captura_Lance3 | CS1: Captura_Faena3 | CT1: Venta_Recurso3 | CU1: Precio_Kg3 | CV1: Observaciones
A2: CC-LOMAS-001 | B2: Cristel Cordero | C2: 45825 | D2: Aldo Álvarez | E2: 41928103 | F2: 30 | G2: 20 | H2: Lomas | I2: Lomas | J2: Lomas, Matarani, Pucusana | K2: 30460 | L2: =DATEDIF(K2, DATE(2025,8,29), "Y") -> 42 | M2: M | N2: Casado/Conviviente | O2: Secundaria | P2: si | Q2: si | R2: Tripulación | S2: si | T2: APARVALM | U2: si | V2: Colecta de algas | W2: algas | X2: Buceo pulmón | Y2: mariscos, pulpo, barquillo, chanque | Z2: NA | AA2: NA | AB2: si | AC2: Presidente de OSPA, Proveedor de la Municipalidad | AD2: 3 | AE2: 3 | AF2: si | AG2: Docente | AH2: no | AI2: NA | AJ2: si | AK2: NA | AL2: si | AM2: NA | AN2: 0 | AO2: NA | AP2: KEVIN JOSE | AQ2: NS | AR2: no | AS2: no | AT2: si | AU2: 6 | AV2: NA | AW2: NA | AX2: NA | AY2: NA | AZ2: NA | BA2: NA | BB2: 136 | BC2: Trampa Ovas | BD2: 3 | BE2: 25-45 | BF2: Peruana | BG2: Ova | BH2: no | BI2: Octubre-Diciembre | BJ2: 8 | BK2: Usa esteras y sargazo | BL2: 7-10 | BM2: 48-96 | BN2: 2-3 | BO2: 300-400 | BP2: 900-1200 | BQ2: Acopiador | BR2: NS | BS2: NA | BT2: NA | BU2: NA | BV2: NA | BW2: NA | BX2: NA | BY2: NA | BZ2: NA | CA2: NA | CB2: NA | CC2: NA | CD2: NA | CE2: NA | CF2: NA | CG2: NA | CH2: NA | CI2: NA | CJ2: NA | CK2: NA | CL2: NA | CM2: NA | CN2: NA | CO2: NA | CP2: NA | CQ2: NA | CR2: NA | CS2: NA | CT2: NA | CU2: NA | CV2: Desde el 2016 sale a la ova de pez volador.
A3: CC-LOMAS-002 | B3: Cristel Cordero | C3: 45825 | D3: Walter Calle Ticona | E3: 00517446 | F3: 22 | G3: 22 | H3: Lomas | I3: Lomas | J3: Lomas | K3: 28485 | L3: =DATEDIF(K3, DATE(2025,8,29), "Y") -> 47 | M3: M | N3: Casado/Conviviente | O3: Secundaria | P3: si | Q3: si | R3: Patrón | S3: si | T3: GREMIO DE PESCADORES ARTESANALES Y EXTRACTORES DE MARISCOS | U3: si | V3: Colecta de algas | W3: algas | X3: Cortina de fondo | Y3: corvina, lorna, chita, lenguado, cabrilla | Z3: NA | AA3: NA | AB3: si | AC3: Presidente de OSPA, Construcción | AD3: 2 | AE3: 2 | AF3: si | AG3: Colecta de algas | AH3: si | AI3: Pareja (colecta de algas) | AJ3: si | AK3: NA | AL3: si | AM3: NA | AN3: 0 | AO3: NA | AP3: ASTRID JEREMY | AQ3: NS | AR3: no | AS3: no | AT3: si | AU3: 10 | AV3: NA | AW3: NA | AX3: NA | AY3: NA | AZ3: NA | BA3: NA | BB3: 250-300 | BC3: Trampa Ovas | BD3: 3 | BE3: 30-40 | BF3: Peruana | BG3: Ova | BH3: no | BI3: Noviembre-Enero | BJ3: 3 | BK3: Usa esteras (5:1.5x2.5 m) con manta (10:2x8 m) y sargazo/palmeras | BL3: 30-45 | BM3: 48_72 | BN3: 7-10 | BO3: 10-100 | BP3: 800-1500 | BQ3: Acopiador | BR3: 22-28 | BS3: Espinel superficial | BT3: 4 | BU3: 30-40 | BV3: Peruana | BW3: Perico | BX3: pez volador, pota | BY3: Enero-Febrero | BZ3: 3 | CA3: Linea madre: 5600 m, #anzuelos/linea: 1, # anzuelos: 500, Calibre: 5 | CB3: 6-10 | CC3: 6-8 | CD3: 10-12 | CE3: 300-1000 | CF3: 2500 | CG3: Acopiador | CH3: 10 | CI3: Pinta potera | CJ3: Pota | CK3: no | CL3: Abril-Junio | CM3: 2-3 | CN3: NA | CO3: 3-5 | CP3: NA | CQ3: NA | CR3: NA | CS3: 5000-8000 | CT3: Acopiador | CU3: 2.5-5 | CV3: Pesca de ova de pez volador: 3 días por cala (noviembre), 2 días (diciembre y enero). Considera que el número de pescadores y embarcaciones para la ova ha aumentado, por lo que ahora hay menos huevera. Para la primera salida para la ova se gasta un total de 14,000 soles (8,000 combustible + 3000 mantas y esteras + 500 zargazo+ 2400 palmeras + 3000 viveres). Dato: cada palmera cuesta 6 a 7 soles (compran 400). En Lomas hay 5 acopiadores en total.
A4: CC-LOMAS-003 | B4: Cristel Cordero | C4: 45826 | D4: Justo Antayhua Valdiviezo | E4: 10455364 | F4: 10 | G4: 2 | H4: Lomas | I4: Lomas | J4: Lomas | K4: 26526 | L4: =DATEDIF(K4, DATE(2025,8,29), "Y") -> 53 | M4: M | N4: Casado/Conviviente | O4: Superior Técnico | P4: si | Q4: no | R4: Tripulación | S4: si | T4: ASOCIACIÓN DE PESCADORES ARTESANALES DE PINTA, CORDEL Y CAÑA DEFENSORES DE LOS BANCOS NATURALES DE LENGUADOS, CORVINAS Y MACHAS DEL PUERTO DE LOMAS (ASPAEL) | U4: si | V4: Espinel de orilla | W4: corvina, lenguado | X4: Pinta | Y4: bonito | Z4: NA | AA4: NA | AB4: no | AC4: NA | AD4: 1 | AE4: 3 | AF4: si | AG4: Colecta de algas, Presidenta de asociación APA MIRAMAR | AH4: si | AI4: Pareja (colecta de algas) | AJ4: si | AK4: NA | AL4: si | AM4: NA | AN4: 0 | AO4: NA | AP4: EIMAR | AQ4: TA-22651-BM | AR4: no | AS4: no | AT4: si | AU4: 12 | AV4: NA | AW4: NA | AX4: NA | AY4: NA | AZ4: NA | BA4: NA | BB4: 230-270 | BC4: Trampa Ovas | BD4: 3-4 | BE4: 21-60 | BF4: Peruana y Venezolana | BG4: Ova | BH4: no | BI4: Octubre-Enero | BJ4: 4 | BK4: Usa esteras (5:2.8x1.2 m)con manta (2: 3.8x2.2 m) y sargazo/palmeras | BL4: 25-35 | BM4: 24-48 | BN4: 6 | BO4: 50-200 | BP4: 800-2000 | BQ4: Acopiador | BR4: 25-42 | BS4: NA | BT4: NA | BU4: NA | BV4: NA | BW4: NA | BX4: NA | BY4: NA | BZ4: NA | CA4: NA | CB4: NA | CC4: NA | CD4: NA | CE4: NA | CF4: NA | CG4: NA | CH4: NA | CI4: NA | CJ4: NA | CK4: NA | CL4: NA | CM4: NA | CN4: NA | CO4: NA | CP4: NA | CQ4: NA | CR4: NA | CS4: NA | CT4: NA | CU4: NA | CV4: Actualmente usan más palmeras que zargazo ya que es más dificil de conseguir y se pudre fácilmente. Este zargazo se saca con barreteo. Precio de ova con ojo: S/ 5 a 10. El mismo se encarga de vender a compradores que tienen ese negocio de cau-cau para la sierra.
A5: CC-LOMAS-004 | B5: Cristel Cordero | C5: 45826 | D5: Miguel Lima | E5: 80281933 | F5: 30 | G5: 30 | H5: Lomas | I5: Lomas | J5: Lomas, Matarani | K5: 23283 | L5: =DATEDIF(K5, DATE(2025,8,29), "Y") -> 61 | M5: M | N5: Viudo | O5: Primaria | P5: si | Q5: si | R5: Armador, Patrón | S5: si | T5: APA MIRAMAR | U5: si | V5: Espinel de orilla | W5: corvina, lenguado | X5: NA | Y5: NA | Z5: NA | AA5: NA | AB5: no | AC5: NA | AD5: 1 | AE5: 4 | AF5: no | AG5: NA | AH5: si | AI5: 1 hijo (tripulante), 1 hijo (armador) | AJ5: si | AK5: NA | AL5: si | AM5: NA | AN5: 1 | AO5: si | AP5: TANIA FABIANA | AQ5: SN-54060-BM | AR5: no | AS5: no | AT5: si | AU5: 6 | AV5: NA | AW5: NA | AX5: NA | AY5: NA | AZ5: NA | BA5: NA | BB5: 153-238 | BC5: Trampa Ovas | BD5: 3 | BE5: 18-60 | BF5: Peruana | BG5: Ova | BH5: no | BI5: Noviembre-Febrero | BJ5: 3-4 | BK5: Usa esteras y sargazo/palmeras | BL5: 20-35 | BM5: 72 | BN5: 3-7 | BO5: 100-500 | BP5: 800-1800 | BQ5: Acopiador | BR5: 15-45 | BS5: Espinel superficial | BT5: 4 | BU5: 18-60 | BV5: Peruana y Venezolana | BW5: Perico | BX5: pota | BY5: Enero-Febrero | BZ5: 6 | CA5: Linea madre: 8200 m, #anzuelos/linea: 1, # anzuelos: 500-600, Calibre: 8 | CB5: 7-12 | CC5: 2-3 | CD5: 2-3 | CE5: 500-1000 | CF5: 2000-4000 | CG5: Acopiador | CH5: 5-7 | CI5: Pinta potera | CJ5: Pota | CK5: no | CL5: Todo el año (cuota) | CM5: 2-3/mes | CN5: NA | CO5: 10-15 | CP5: NA | CQ5: NA | CR5: NA | CS5: 1000-2000 | CT5: Acopiador | CU5: 6 | CV5: Ova con ojo trata de regresarlo al mar. Pesca de perico (1 cala dura 7h: 30 min botar el espinel al agua + 2a3h que espera que el perico enganche + 3h en recoger todo el espinel). Acopiador de ova, perico y pota: Duber
A6: CC-LOMAS-005 | B6: Cristel Cordero | C6: 45826 | D6: Luz Aurora Guerrero Fernandez | E6: 80276520 | F6: 13 | G6: 4 | H6: Lomas | I6: Lomas | J6: Lomas, Pucusana | K6: 26836 | L6: =DATEDIF(K6, DATE(2025,8,29), "Y") -> 52 | M6: F | N6: Casado/Conviviente | O6: Primaria | P6: si | Q6: si | R6: Tripulación | S6: no | T6: NA | U6: si | V6: Cortina costera | W6: pejerrey | X6: Pinta | Y6: pota | Z6: NA | AA6: NA | AB6: si | AC6: Ama de casa | AD6: 2 | AE6: 5 | AF6: si | AG6: Armador y patrón | AH6: si | AI6: Pareja (armador), 1 hijo (tripulante), 1 hijo (armador) | AJ6: si | AK6: Principalmente para la ova | AL6: si | AM6: NA | AN6: 0 | AO6: NA | AP6: SANTA ROSA II | AQ6: MO-38424-BM | AR6: no | AS6: no | AT6: si | AU6: 6 | AV6: NA | AW6: NA | AX6: NA | AY6: NA | AZ6: NA | BA6: NA | BB6: =15*17 -> 255 | BC6: Trampa Ovas | BD6: 3 | BE6: 47-49 | BF6: Peruana | BG6: Ova | BH6: no | BI6: Octubre-Febrero | BJ6: 3 | BK6: Usa manta y palmera/manguera | BL6: 30 | BM6: 48 | BN6: 10-15 | BO6: 20-100 | BP6: 1500 | BQ6: Acopiador | BR6: 37-41 | BS6: NA | BT6: NA | BU6: NA | BV6: NA | BW6: NA | BX6: NA | BY6: NA | BZ6: NA | CA6: NA | CB6: NA | CC6: NA | CD6: NA | CE6: NA | CF6: NA | CG6: NA | CH6: NA | CI6: NA | CJ6: NA | CK6: NA | CL6: NA | CM6: NA | CN6: NA | CO6: NA | CP6: NA | CQ6: NA | CR6: NA | CS6: NA | CT6: NA | CU6: NA | CV6: Durante su faena a la ova en la altura, ha visto ballenas jorobadas y delfines. Precio de ova con ojo: S/. 10 a 15 (le vende a acopiador que compra cau-cau)
A7: CC-LOMAS-006 | B7: Cristel Cordero | C7: 45826 | D7: Juan Carlos Ochoa Taype | E7: 41485241 | F7: 28 | G7: 17 | H7: Lomas | I7: Lomas | J7: Lomas | K7: 30029 | L7: =DATEDIF(K7, DATE(2025,8,29), "Y") -> 43 | M7: M | N7: Casado/Conviviente | O7: Secundaria | P7: si | Q7: si | R7: Armador, Patrón | S7: si | T7: APARVALM | U7: si | V7: Colecta de algas | W7: algas | X7: NA | Y7: NA | Z7: NA | AA7: NA | AB7: no | AC7: NA | AD7: 1 | AE7: 1 | AF7: si | AG7: Cajera de los botes en el muelle | AH7: si | AI7: Pareja (cajera de botes) | AJ7: si | AK7: NA | AL7: si | AM7: NA | AN7: 1 | AO7: si | AP7: GINO Y ANGIE | AQ7: SN-42496-BM | AR7: no | AS7: no | AT7: si | AU7: 5 | AV7: NA | AW7: NA | AX7: NA | AY7: NA | AZ7: NA | BA7: NA | BB7: 170 | BC7: Trampa Ovas | BD7: 3 | BE7: 35-45 | BF7: Peruana | BG7: Ova | BH7: no | BI7: Octubre-Enero | BJ7: 2-3 | BK7: Usa esteras con manta y sargazo/palmeras/manguera | BL7: 25-30 | BM7: 72-96 | BN7: 5-7 | BO7: 50-100 | BP7: 1000-1400 | BQ7: Acopiador | BR7: 28-40 | BS7: Espinel superficial | BT7: 4 | BU7: 35-45 | BV7: Peruana | BW7: Perico | BX7: pez volador, pota | BY7: Diciembre-Febrero | BZ7: 3 | CA7: Linea madre: 4300 m, #anzuelos/linea: 1, # anzuelos: 300, Calibre: 5 | CB7: 7-10 | CC7: 2-4 | CD7: 8 | CE7: 200-500 | CF7: 2000-3000 | CG7: Acopiador | CH7: 7-10 | CI7: Pinta potera | CJ7: Pota | CK7: no | CL7: 72-144 | CM7: 4-5/mes | CN7: NA | CO7: 3-7 | CP7: NA | CQ7: NA | CR7: NA | CS7: 3000-5000 | CT7: Acopiador | CU7: 1-1.20 | CV7: Zona de pesca en la altura (>50 mn) va desde Atico a Pucusana y luego va bajando de nuevo a Lomas. TSM del pez volador: 18-19°C. En Lomas hay 4 acopiadores de ova, pero en temporada son de 8 a 10. Precio de ova con ojo: S/. 5 a 10. Otro acopiador compra la ova con ojo.
A8: CC-LOMAS-007 | B8: Cristel Cordero | C8: 45826 | D8: Victor Medina | E8: 30498849 | F8: 35 | G8: 35 | H8: Lomas | I8: Lomas | J8: Lomas | K8: 25702 | L8: =DATEDIF(K8, DATE(2025,8,29), "Y") -> 55 | M8: M | N8: Casado/Conviviente | O8: Secundaria | P8: si | Q8: si | R8: Armador, Patrón | S8: si | T8: ABEMALOS | U8: si | V8: Buceo compresora | W8: mariscos, pulpo | X8: NA | Y8: NA | Z8: NA | AA8: NA | AB8: si | AC8: Vende comida | AD8: 1 | AE8: 3 | AF8: si | AG8: Pescadora (pinta: cabrilla, lenguado) | AH8: si | AI8: Pareja (tripulante) | AJ8: si | AK8: NA | AL8: si | AM8: NA | AN8: 2 | AO8: si | AP8: MATHIAS | AQ8: SN-04280-BM | AR8: no | AS8: no | AT8: si | AU8: 3 | AV8: MATHIAS | AW8: SN-55206-BM | AX8: no | AY8: no | AZ8: si | BA8: 3 | BB8: 40-50 | BC8: Trampa Ovas | BD8: 3 | BE8: 30-40 | BF8: Peruana | BG8: Ova | BH8: no | BI8: Octubre-Enero | BJ8: 4 | BK8: Usa esteras y sargazo/palmeras | BL8: 15 | BM8: 72 | BN8: 5 | BO8: 100-150 | BP8: 800-1000 | BQ8: Acopiador | BR8: 28-45 | BS8: Espinel superficial | BT8: 4 | BU8: 30-40 | BV8: Peruana | BW8: Perico | BX8: pez volador, pota | BY8: Diciembre-Febrero | BZ8: 5 | CA8: Linea madre: 2500 m, #anzuelos/linea: 1, # anzuelos: 300, Calibre: 5 | CB8: 7-10 | CC8: 2-4 | CD8: 8 | CE8: 200-300 | CF8: 2000-2500 | CG8: Acopiador | CH8: 7-10 | CI8: NA | CJ8: NA | CK8: NA | CL8: NA | CM8: NA | CN8: NA | CO8: NA | CP8: NA | CQ8: NA | CR8: NA | CS8: NA | CT8: NA | CU8: NA | CV8: Ova con ojo lo compra un comerciante en muelle a S/.3. En la OSPA ABEMALOS, 3 mujeres salen a la altura.
A9: CC-LOMAS-008 | B9: Cristel Cordero | C9: 45826 | D9: Wilfredo Mauricio Polo | E9: 30498571 | F9: 47 | G9: 30 | H9: Lomas | I9: Lomas | J9: Lomas | K9: 21107 | L9: =DATEDIF(K9, DATE(2025,8,29), "Y") -> 67 | M9: M | N9: Divorciado | O9: Secundaria | P9: si | Q9: si | R9: Armador, Patrón | S9: si | T9: ABEMALOS | U9: si | V9: Buceo compresora | W9: mariscos, pulpo, pintadilla, congrio, cabrilla | X9: NA | Y9: NA | Z9: NA | AA9: NA | AB9: no | AC9: NA | AD9: 1 | AE9: 3 | AF9: no | AG9: NA | AH9: no | AI9: NA | AJ9: si | AK9: NA | AL9: si | AM9: NA | AN9: 1 | AO9: si | AP9: BLAKY | AQ9: SN-25309-BM | AR9: no | AS9: no | AT9: si | AU9: 3 | AV9: NA | AW9: NA | AX9: NA | AY9: NA | AZ9: NA | BA9: NA | BB9: 136 | BC9: Trampa Ovas | BD9: 2 | BE9: 64-67 | BF9: Peruana | BG9: Ova | BH9: no | BI9: Noviembre-Enero | BJ9: 4-5 | BK9: Usa esteras (4: 3x1.5 m) con manta (12: 6x1.5 m) y sargazo/palmeras | BL9: 15 | BM9: 72 | BN9: 3-5 | BO9: 50-200 | BP9: 500-700 | BQ9: Comerciante | BR9: 35-40 | BS9: NA | BT9: NA | BU9: NA | BV9: NA | BW9: NA | BX9: NA | BY9: NA | BZ9: NA | CA9: NA | CB9: NA | CC9: NA | CD9: NA | CE9: NA | CF9: NA | CG9: NA | CH9: NA | CI9: NA | CJ9: NA | CK9: NA | CL9: NA | CM9: NA | CN9: NA | CO9: NA | CP9: NA | CQ9: NA | CR9: NA | CS9: NA | CT9: NA | CU9: NA | CV9: Las esteras son de totora, la manta de plástico, la manguera de plástico y es la que usan en el campo para el riego a goteo (va a probar como le va para la siguiente temporada). Ova con ojo se descarta en el mar. Indica que en Lomas no hay pesca de boliche.
A10: CC-LOMAS-009 | B10: Cristel Cordero | C10: 45826 | D10: Leonel Antayhua | E10: 80426025 | F10: 35 | G10: 25 | H10: Lomas | I10: Lomas | J10: Lomas, Planchada, Matarani | K10: 27506 | L10: =DATEDIF(K10, DATE(2025,8,29), "Y") -> 50 | M10: M | N10: Casado/Conviviente | O10: Secundaria | P10: si | Q10: si | R10: Armador, Patrón | S10: si | T10: ABEMALOS | U10: si | V10: Buceo compresora | W10: mariscos, pulpo | X10: NA | Y10: NA | Z10: NA | AA10: NA | AB10: si | AC10: Mecánico | AD10: 2 | AE10: 2 | AF10: si | AG10: Ama de casa | AH10: no | AI10: NA | AJ10: si | AK10: NA | AL10: si | AM10: NA | AN10: 2 | AO10: si | AP10: ADRIANELA | AQ10: SN-55525-BM | AR10: no | AS10: no | AT10: si | AU10: 8 | AV10: NS | AW10: NS | AX10: NS | AY10: NS | AZ10: NS | BA10: NS | BB10: 250-300 | BC10: Trampa Ovas | BD10: 3 | BE10: 30-40 | BF10: Peruana | BG10: Ova | BH10: no | BI10: Noviembre-Enero | BJ10: 3-4 | BK10: Usa esteras (4: 3x1.5 m) con manta (10: 8x1.8 m) y sargazo/palmeras | BL10: 25-28 | BM10: 48-72 | BN10: 4-12 | BO10: 100-200 | BP10: 1000-1500 | BQ10: Acopiador | BR10: 23-25 | BS10: Espinel superficial | BT10: 4 | BU10: 30-40 | BV10: Peruana | BW10: Perico | BX10: pota | BY10: Enero-Febrero | BZ10: 4-5 | CA10: Linea madre: 5800 m, #anzuelos/linea: 1, # anzuelos: 400, Calibre: 4 | CB10: 12 | CC10: 2 | CD10: 10 | CE10: 300 | CF10: 1800-2500 | CG10: Acopiador | CH10: 10 | CI10: NA | CJ10: NA | CK10: NA | CL10: NA | CM10: NA | CN10: NA | CO10: NA | CP10: NA | CQ10: NA | CR10: NA | CS10: NA | CT10: NA | CU10: NA | CV10: Pesca de pota en la altura es esporádico, la última vez que salió fue en octubre 2024 a más de 80 mn.
A11: FV-LOMAS-001 | B11: Florinda Ventura | C11: 45825 | D11: Jose Pastor Valdez | E11: 30498921 | F11: 40 | G11: 20 | H11: Lomas | I11: Lomas | J11: Lomas | K11: 23386 | L11: =DATEDIF(K11, DATE(2025,8,29), "Y") -> 61 | M11: M | N11: Soltero | O11: Secundaria | P11: si | Q11: si | R11: Patrón | S11: si | T11: ASOCIACIÓN DE PESCADORES ARTESANALES Y RECOLECTORES DE PRODUCTOR HIDROBIOLÓGICOS "LA PERLA DE PUERTO LOMAS" | U11: no | V11: NA | W11: NA | X11: NA | Y11: NA | Z11: NA | AA11: NA | AB11: si | AC11: Pintor | AD11: 1 | AE11: 0 | AF11: no | AG11: NA | AH11: no | AI11: NA | AJ11: si | AK11: NA | AL11: si | AM11: NA | AN11: 0 | AO11: NA | AP11: EL AMADOR | AQ11: NS | AR11: no | AS11: no | AT11: si | AU11: 12 | AV11: NA | AW11: NA | AX11: NA | AY11: NA | AZ11: NA | BA11: NA | BB11: 238 | BC11: Trampa Ovas | BD11: 3 | BE11: 28-60 | BF11: Peruana | BG11: Ova | BH11: no | BI11: Octubre-Enero | BJ11: 4-6 | BK11: Usa esteras y sargazo/palmeras | BL11: 20-30 | BM11: 72 | BN11: 8-10 | BO11: 130-260 | BP11: 1200-1500 | BQ11: Acopiador | BR11: 30-50 | BS11: Espinel superficial | BT11: 3 | BU11: 28-60 | BV11: Peruana | BW11: Perico | BX11: pez volador, caballa | BY11: Enero-Abril | BZ11: 8 | CA11: Linea madre: 2000 m, #anzuelos/linea: 1, # anzuelos: 400, Calibre: 7 | CB11: 7 | CC11: 2-3 | CD11: 5-7 | CE11: 500-600 | CF11: 5000 | CG11: Acopiador | CH11: 10-13 | CI11: Pinta potera | CJ11: Pota | CK11: no | CL11: Todo el año (cuota) | CM11: 2-4/mes | CN11: NA | CO11: 3 | CP11: NA | CQ11: NA | CR11: NA | CS11: 200-400 | CT11: Acopiador | CU11: 6-12
A12: FV-LOMAS-002 | B12: Florinda Ventura | C12: 45825 | D12: Yohan Lima Maquera | E12: 72677790 | F12: 15 | G12: 15 | H12: Lomas | I12: Lomas | J12: Lomas | K12: 33236 | L12: =DATEDIF(K12, DATE(2025,8,29), "Y") -> 34 | M12: M | N12: Casado/Conviviente | O12: Superior Técnico | P12: si | Q12: si | R12: Armador | S12: si | T12: ASOCIACIÓN DE PROPIETARIOS DE EMBARCACIONES PESQUERAS ARTESANALES DEL PUERTO DE LOMAS (APEPAL) | U12: si | V12: Buceo compresora | W12: mariscos | X12: NA | Y12: NA | Z12: NA | AA12: NA | AB12: si | AC12: Mecánico | AD12: 3 | AE12: 3 | AF12: si | AG12: Costurera | AH12: no | AI12: NA | AJ12: si | AK12: NA | AL12: si | AM12: NA | AN12: 0 | AO12: si | AP12: LUIS ADRIANO | AQ12: NS | AR12: no | AS12: no | AT12: si | AU12: 9 | AV12: NA | AW12: NA | AX12: NA | AY12: NA | AZ12: NA | BA12: NA | BB12: 204 | BC12: Trampa Ovas | BD12: 3 | BE12: 30-35 | BF12: Peruana | BG12: Ova | BH12: no | BI12: Diciembre-Enero | BJ12: 4 | BK12: Usa manta y sargazo/palmera | BL12: 20-35 | BM12: 96 | BN12: 4-5 | BO12: 100 | BP12: 1000 | BQ12: Acopiador | BR12: 25-45 | BS12: Espinel superficial | BT12: 4 | BU12: 30-35 | BV12: Peruana | BW12: Perico | BX12: pez volador, pota | BY12: Enero-Marzo | BZ12: 3 | CA12: Linea madre: 4000 m, #anzuelos/linea: 1, # anzuelos: 250, Calibre: 8 | CB12: 10-12 | CC12: 2-3 | CD12: 10 | CE12: 500 | CF12: 3000 | CG12: Acopiador | CH12: 6-9 | CI12: Pinta potera | CJ12: Pota | CK12: no | CL12: Mayo-Junio | CM12: 10 | CN12: NA | CO12: 7 | CP12: NA | CQ12: NA | CR12: NA | CS12: 8000 | CT12: Acopiador | CU12: 4 | CV12: Acopiadores Lomas: Duber, Janet, Efrain, Zoraya
A13: FV-LOMAS-003 | B13: Florinda Ventura | C13: 45826 | D13: Florinda Ventura | E13: 45921520 | F13: 8 | G13: 7 | H13: Lomas | I13: Lomas | J13: Lomas | K13: 29549 | L13: =DATEDIF(K13, DATE(2025,8,29), "Y") -> 44 | M13: M | N13: Soltero | O13: Secundaria | P13: si | Q13: si | R13: Armador | S13: si | T13: ABEMALOS | U13: no | V13: NA | W13: NA | X13: NA | Y13: NA | Z13: NA | AA13: NA | AB13: no | AC13: NA | AD13: 2 | AE13: 0 | AF13: no | AG13: NA | AH13: no | AI13: NA | AJ13: si | AK13: NA | AL13: si | AM13: NA | AN13: 1 | AO13: si | AP13: CUSQUEÑITO | AQ13: PS-00623-BM | AR13: no | AS13: no | AT13: no | AU13: 6 | AV13: NA | AW13: NA | AX13: NA | AY13: NA | AZ13: NA | BA13: NA | BB13: 170 | BC13: Trampa Ovas | BD13: 3 | BE13: 20-50 | BF13: Peruana | BG13: Ova | BH13: no | BI13: Octubre-Enero | BJ13: 3 | BK13: Usa manta y sargazo/palmera | BL13: 20-30 | BM13: 48-72 | BN13: 10 | BO13: 80-100 | BP13: 700 | BQ13: Acopiador | BR13: 30-40 | BS13: NA | BT13: NA | BU13: NA | BV13: NA | BW13: NA | BX13: NA | BY13: NA | BZ13: NA | CA13: NA | CB13: NA | CC13: NA | CD13: NA | CE13: NA | CF13: NA | CG13: NA | CH13: NA | CI13: NA | CJ13: NA | CK13: NA | CL13: NA | CM13: NA | CN13: NA | CO13: NA | CP13: NA | CQ13: NA | CR13: NA | CS13: NA | CT13: NA | CU13: NA | CV13: Acopiador de ova: Duber.
A14: FV-LOMAS-004 | B14: Florinda Ventura | C14: 45826 | D14: Jose Miguel Chambi Cure | E14: 22082282 | F14: 38 | G14: 30 | H14: Lomas | I14: Lomas | J14: Lomas, Planchada, Atico | K14: 26627 | L14: =DATEDIF(K14, DATE(2025,8,29), "Y") -> 52 | M14: M | N14: Casado/Conviviente | O14: Primaria | P14: si | Q14: si | R14: Armador, Patrón | S14: si | T14: ABEMALOS | U14: si | V14: Buceo compresora | W14: mariscos | X14: NA | Y14: NA | Z14: NA | AA14: NA | AB14: no | AC14: NA | AD14: 2 | AE14: 3 | AF14: no | AG14: Ama de casa | AH14: no | AI14: NA | AJ14: si | AK14: NA | AL14: si | AM14: NA | AN14: 1 | AO14: si | AP14: SATURNINA | AQ14: MO-32934-BM | AR14: no | AS14: no | AT14: si | AU14: 4 | AV14: NA | AW14: NA | AX14: NA | AY14: NA | AZ14: NA | BA14: NA | BB14: 204 | BC14: Trampa Ovas | BD14: 2 | BE14: 28-35 | BF14: Peruana | BG14: Ova | BH14: no | BI14: Octubre-Diciembre | BJ14: 2-3 | BK14: Usa manta y sargazo/palmera | BL14: 30 | BM14: 72-96 | BN14: 7-9 | BO14: 100 | BP14: 1000 | BQ14: Acopiador | BR14: 23-41 | BS14: Espinel superficial | BT14: 4 | BU14: 28-35 | BV14: Peruana | BW14: Perico | BX14: pota, caballa | BY14: Enero-Febrero | BZ14: 6 | CA14: Linea madre: 4000 m, #anzuelos/linea: 1, # anzuelos: 500, Calibre :4 | CB14: 7 | CC14: 2-3 | CD14: 10-15 | CE14: 150-500 | CF14: 2500-3000 | CG14: Acopiador | CH14: 4-8 | CI14: NA | CJ14: NA | CK14: NA | CL14: NA | CM14: NA | CN14: NA | CO14: NA | CP14: NA | CQ14: NA | CR14: NA | CS14: NA | CT14: NA | CU14: NA
A15: FV-LOMAS-005 | B15: Florinda Ventura | C15: 45826 | D15: Mario Lizano Aybar | E15: 30498807 | F15: 50 | G15: 40 | H15: Lomas | I15: Lomas | J15: Lomas | K15: 23524 | L15: =DATEDIF(K15, DATE(2025,8,29), "Y") -> 61 | M15: M | N15: Casado/Conviviente | O15: Primaria | P15: si | Q15: si | R15: Armador, Patrón | S15: si | T15: ABEMALOS | U15: si | V15: Buceo compresora | W15: mariscos | X15: Cortina de fondo | Y15: lenguado, raya, tollo | Z15: NA | AA15: NA | AB15: no | AC15: NA | AD15: 1 | AE15: 3 | AF15: si | AG15: Ama de casa | AH15: no | AI15: 1 hijo (tripulante) | AJ15: si | AK15: NA | AL15: no | AM15: Ya que van en familia y no se les paga igual | AN15: 1 | AO15: si | AP15: ANGELES Y LUCIA | AQ15: PS-20879-BM | AR15: no | AS15: no | AT15: si | AU15: 5 | AV15: NA | AW15: NA | AX15: NA | AY15: NA | AZ15: NA | BA15: NA | BB15: 136-170 | BC15: Trampa Ovas | BD15: 3 | BE15: 25-50 | BF15: Peruana | BG15: Ova | BH15: no | BI15: Noviembre-Enero | BJ15: 4-5 | BK15: Usa esteras y sargazo | BL15: 12-15 | BM15: 72-96 | BN15: 3-5 | BO15: 250-400 | BP15: 800-1000 | BQ15: Acopiador | BR15: 25-40 | BS15: Espinel superficial | BT15: 4 | BU15: 25-40 | BV15: Peruana | BW15: Perico | BX15: pez volador | BY15: Octubre-Febrero | BZ15: 4-6 | CA15: Linea madre: 1000 m, #anzuelos/linea: 1, # anzuelos: 200, Calibre :5 | CB15: 4-5 | CC15: 2-3 | CD15: 4-5 | CE15: 500-700 | CF15: 1200-1800 | CG15: Acopiador | CH15: 8-9 | CI15: NA | CJ15: NA | CK15: NA | CL15: NA | CM15: NA | CN15: NA | CO15: NA | CP15: NA | CQ15: NA | CR15: NA | CS15: NA | CT15: NA | CU15: NA | CV15: Hace más de 5 años que no sale al tiburón a la altura.
A16: CC-LOMAS-010 | B16: Cristel Cordero | C16: 45898 | D16: Luis Castillo Ledesma | E16: 77157908 | F16: 15 | G16: 10 | H16: Lomas | I16: Lomas | J16: Lomas | K16: 35617 | L16: =DATEDIF(K16, DATE(2025,8,29), "Y") -> 28 | M16: M | N16: Casado/Conviviente | O16: Secundaria | P16: si | Q16: si | R16: Armador | S16: si | T16: ABEMALOS | U16: si | V16: Buceo compresora | W16: mariscos | X16: NA | Y16: NA | Z16: NA | AA16: NA | AB16: no | AC16: NA | AD16: 4 | AE16: 2 | AF16: si | AG16: Ama de casa | AH16: no | AI16: NA | AJ16: no | AK16: Se requiere mucha fuerza física, la huevera si podrían pero el perico y tiburones no. | AL16: no | AM16: Se les paga menos ya que tienen menos fuerza y menos capacidad para la pesca. | AN16: 1 | AO16: si | AP16: IAN Y XIANA | AQ16: MO-36778-BM | AR16: no | AS16: no | AT16: si | AU16: 8 | AV16: NA | AW16: NA | AX16: NA | AY16: NA | AZ16: NA | BA16: NA | BB16: 170-250 | BC16: Trampa Ovas | BD16: 3 | BE16: 25-60 | BF16: Peruana | BG16: Ova | BH16: no | BI16: Octubre-Enero | BJ16: 3-4 | BK16: Usa esteras con manta y sargazo/palmeras/manguera | BL16: 30 | BM16: 48-72 | BN16: 8-12 | BO16: 20-100 | BP16: 500-800 | BQ16: Comerciante | BR16: 22-35 | BS16: Espinel superficial | BT16: 3-4 | BU16: 25-60 | BV16: Peruana | BW16: Perico | BX16: pota | BY16: Octubre-Enero | BZ16: 4-5 | CA16: Linea madre: 700 m, #anzuelos/linea: 1, # anzuelos: 300-400, Calibre: 5 | CB16: 15 | CC16: 72-96 | CD16: 10-20 | CE16: 300-600 | CF16: 3000-4500 | CG16: Comerciante | CH16: 5-7 | CI16: Espinel superficial | CJ16: Tiburón azul, Tiburón diamante, Tiburón zorro | CK16: pota, bonito | CL16: Marzo-Julio | CM16: 4-5 | CN16: Linea madre: 700 m, #anzuelos/linea: 1, # anzuelos: 300-400, Calibre: 7 | CO16: 7-10 | CP16: 8-10 | CQ16: 7-10 | CR16: 100-200 | CS16: 4000-5000 | CT16: Comerciante | CU16: NA | CV16: Zona de pesca en la altura (>50 mn) va desde Atico a Pucusana y luego va bajando de nuevo a Lomas. TSM del pez volador: 18-19°C. En Lomas hay 4 acopiadores de ova, pero en temporada son de 8 a 10. Precio de ova con ojo: S/. 5 a 10. Otro acopiador compra l

Sheet Dias de faena
A1: PUCUSANA
B2: MIN | C2: MAX | D2: DURACION | F2: DIAS | G2: FRECUENCIA
A3: Bonito | B3: 7 | C3: 7 | D3: =AVERAGE(C3,B3) -> 7 | F3: 4 | G3: =COUNTIF('Dias de faena'!$D$3:$D$23,"4") -> 3
